Workbook

Sheet Template
A1: =+'Annual Raw'!B2 -> 0 | B1: =+EOMONTH(C1,-12) -> 36981 | C1: =+EOMONTH(D1,-12) -> 37346 | D1: =+EOMONTH(E1,-12) -> 37711 | E1: =+EOMONTH(F1,-12) -> 38077 | F1: =+EOMONTH(G1,-12) -> 38442 | G1: =+EOMONTH(H1,-12) -> 38807 | H1: =+EOMONTH(I1,-12) -> 39172 | I1: =+EOMONTH(J1,-12) -> 39538 | ... N1: =+EOMONTH(O1,-12) -> 41364 | O1: 41699 | P1: 42064 | Q1: 42430 | R1: 42795 | S1: 43160 | T1: 43525 | U1: 43891 | V1: 44256 | W1: 44621 | X1: 44986 | Y1: 45352 | Z1: 45717 | AA1: 46082 | AB1: 46447 | AC1: 46813 | AD1: 47178 | AE1: 47543 | AG1: Quarterly | AH1: 42185 | AI1: =+EOMONTH(AH1,3) -> 42277 | AJ1: =+EOMONTH(AI1,3) -> 42369 | AK1: =+EOMONTH(AJ1,3) -> 42460 | AL1: =+EOMONTH(AK1,3) -> 42551 | AM1: =+EOMONTH(AL1,3) -> 42643 | AN1: =+EOMONTH(AM1,3) -> 42735 | AO1: =+EOMONTH(AN1,3) -> 42825 | AP1: =+EOMONTH(AO1,3) -> 42916 | ... CO1: =+EOMONTH(CN1,3) -> 47573
A2: Presentation Data (Start)
A4: Average eq | D4: =AVERAGE(C97:D97) -> 0 | E4: =AVERAGE(D97:E97) -> 0 | F4: =AVERAGE(E97:F97) -> 0 | G4: =AVERAGE(F97:G97) -> 0 | H4: =AVERAGE(G97:H97) -> 0 | I4: =AVERAGE(H97:I97) -> 0 | J4: =AVERAGE(I97:J97) -> 0 | K4: =AVERAGE(J97:K97) -> 0 | ... X4: =AVERAGE(W97:X97) -> 0 | Y4: =+AVERAGE(BN4:BQ4) -> 0 | Z4: =+AVERAGE(BR4:BU4) -> 0 | AA4: =+AVERAGE(BV4:BY4) -> 0 | AB4: =+AVERAGE(BZ4:CC4) -> #DIV/0! | AC4: =+AVERAGE(CD4:CG4) -> #DIV/0! | AD4: =+AVERAGE(CH4:CK4) -> #DIV/0! | AE4: =+AVERAGE(CL4:CO4) -> #DIV/0! | AH4: =+AVERAGE(AG97,AE97) -> #DIV/0! | AI4: =+AVERAGE(AI97,AG97) -> 0 | AJ4: =+AVERAGE(AI97,AG97) -> 0 | AK4: =+AVERAGE(AK97,AI97) -> 0 | AL4: =+AVERAGE(AK97,AI97) -> 0 | AM4: =+AVERAGE(AM97,AK97) -> 0 | AN4: =+AVERAGE(AM97,AK97) -> 0 | AO4: =+AVERAGE(AO97,AM97) -> 0 | AP4: =+AVERAGE(AO97,AM97) -> 0 | AQ4: =+AVERAGE(AQ97,AO97) -> 0 | AR4: =+AVERAGE(AQ97,AO97) -> 0 | AS4: =+AVERAGE(AS97,AQ97) -> 0 | AT4: =+AVERAGE(AS97,AQ97) -> 0 | AU4: =+AVERAGE(AU97,AS97) -> 0 | AV4: =+AVERAGE(AU97,AS97) -> 0 | AW4: =+AVERAGE(AW97,AU97) -> 0 | AX4: =+AVERAGE(AW97,AU97) -> 0 | AY4: =+AVERAGE(AY97,AW97) -> 0 | AZ4: =+AVERAGE(AY97,AW97) -> 0 | BA4: =+AVERAGE(BA97,AY97) -> 0 | BB4: =+AVERAGE(BA97,AY97) -> 0 | BC4: =+AVERAGE(BC97,BA97) -> 0 | BD4: =+AVERAGE(BC97,BA97) -> 0 | BE4: =+AVERAGE(BE97,BC97) -> 0 | BF4: =+AVERAGE(BE97,BC97) -> 0 | BG4: =+AVERAGE(BG97,BE97) -> 0 | BH4: =+AVERAGE(BG97,BE97) -> 0 | BI4: =+AVERAGE(BI97,BG97) -> 0 | BJ4: =+AVERAGE(BI97,BG97) -> 0 | BK4: =+AVERAGE(BK97,BI97) -> 0 | BL4: =+AVERAGE(BK97,BI97) -> 0 | BM4: =+AVERAGE(BM97,BK97) -> 0 | BN4: =+AVERAGE(BM97,BK97) -> 0 | BO4: =+AVERAGE(BO97,BM97) -> 0 | BP4: =+AVERAGE(BO97,BM97) -> 0 | BQ4: =+AVERAGE(BQ97,BO97) -> 0 | BR4: =+AVERAGE(BQ97,BO97) -> 0 | BS4: =+AVERAGE(BS97,BQ97) -> 0 | BT4: =+AVERAGE(BS97,BQ97) -> 0 | BU4: =+AVERAGE(BU97,BS97) -> 0 | BV4: =+AVERAGE(BU97,BS97) -> 0 | BW4: =+AVERAGE(BW97,BU97) -> 0 | BX4: =+AVERAGE(BW97,BU97) -> 0 | BY4: =+AVERAGE(BY97,BW97) -> 0 | BZ4: =+AVERAGE(BY97,BW97) -> 0 | CA4: =+AVERAGE(CA97,BY97) -> #DIV/0! | CB4: =+AVERAGE(CA97,BY97) -> #DIV/0! | CC4: =+AVERAGE(CC97,CA97) -> #DIV/0! | CD4: =+AVERAGE(CC97,CA97) -> #DIV/0! | CE4: =+AVERAGE(CE97,CC97) -> #DIV/0! | CF4: =+AVERAGE(CE97,CC97) -> #DIV/0! | CG4: =+AVERAGE(CG97,CE97) -> #DIV/0! | CH4: =+AVERAGE(CG97,CE97) -> #DIV/0! | CI4: =+AVERAGE(CI97,CG97) -> #DIV/0! | CJ4: =+AVERAGE(CI97,CG97) -> #DIV/0! | CK4: =+AVERAGE(CK97,CI97) -> #DIV/0! | CL4: =+AVERAGE(CK97,CI97) -> #DIV/0! | CM4: =+AVERAGE(CM97,CK97) -> #DIV/0! | CN4: =+AVERAGE(CM97,CK97) -> #DIV/0! | CO4: =+AVERAGE(CO97,CM97) -> #DIV/0!
A5: Average assets | D5: =AVERAGE(C106:D106) -> 0 | E5: =AVERAGE(D106:E106) -> 0 | F5: =AVERAGE(E106:F106) -> 0 | G5: =AVERAGE(F106:G106) -> 0 | H5: =AVERAGE(G106:H106) -> 0 | I5: =AVERAGE(H106:I106) -> 0 | J5: =AVERAGE(I106:J106) -> 0 | K5: =AVERAGE(J106:K106) -> 0 | ... X5: =AVERAGE(W106:X106) -> 0 | Y5: =+AVERAGE(BN5:BQ5) -> 0 | Z5: =+AVERAGE(BR5:BU5) -> 0 | AA5: =+AVERAGE(BV5:BY5) -> 0 | AB5: =+AVERAGE(BZ5:CC5) -> #DIV/0! | AC5: =+AVERAGE(CD5:CG5) -> #DIV/0! | AD5: =+AVERAGE(CH5:CK5) -> #DIV/0! | AE5: =+AVERAGE(CL5:CO5) -> #DIV/0! | AH5: =+AVERAGE(AG106,AE106) -> #DIV/0! | AI5: =+AVERAGE(AI106,AG106) -> 0 | AJ5: =+AVERAGE(AI106,AG106) -> 0 | AK5: =+AVERAGE(AK106,AI106) -> 0 | AL5: =+AVERAGE(AK106,AI106) -> 0 | AM5: =+AVERAGE(AM106,AK106) -> 0 | AN5: =+AVERAGE(AM106,AK106) -> 0 | AO5: =+AVERAGE(AO106,AM106) -> 0 | AP5: =+AVERAGE(AO106,AM106) -> 0 | AQ5: =+AVERAGE(AQ106,AO106) -> 0 | AR5: =+AVERAGE(AQ106,AO106) -> 0 | AS5: =+AVERAGE(AS106,AQ106) -> 0 | AT5: =+AVERAGE(AS106,AQ106) -> 0 | AU5: =+AVERAGE(AU106,AS106) -> 0 | AV5: =+AVERAGE(AU106,AS106) -> 0 | AW5: =+AVERAGE(AW106,AU106) -> 0 | AX5: =+AVERAGE(AW106,AU106) -> 0 | AY5: =+AVERAGE(AY106,AW106) -> 0 | AZ5: =+AVERAGE(AY106,AW106) -> 0 | BA5: =+AVERAGE(BA106,AY106) -> 0 | BB5: =+AVERAGE(BA106,AY106) -> 0 | BC5: =+AVERAGE(BC106,BA106) -> 0 | BD5: =+AVERAGE(BC106,BA106) -> 0 | BE5: =+AVERAGE(BE106,BC106) -> 0 | BF5: =+AVERAGE(BE106,BC106) -> 0 | BG5: =+AVERAGE(BG106,BE106) -> 0 | BH5: =+AVERAGE(BG106,BE106) -> 0 | BI5: =+AVERAGE(BI106,BG106) -> 0 | BJ5: =+AVERAGE(BI106,BG106) -> 0 | BK5: =+AVERAGE(BK106,BI106) -> 0 | BL5: =+AVERAGE(BK106,BI106) -> 0 | BM5: =+AVERAGE(BM106,BK106) -> 0 | BN5: =+AVERAGE(BM106,BK106) -> 0 | BO5: =+AVERAGE(BO106,BM106) -> 0 | BP5: =+AVERAGE(BO106,BM106) -> 0 | BQ5: =+AVERAGE(BQ106,BO106) -> 0 | BR5: =+AVERAGE(BQ106,BO106) -> 0 | BS5: =+AVERAGE(BS106,BQ106) -> 0 | BT5: =+AVERAGE(BS106,BQ106) -> 0 | BU5: =+AVERAGE(BU106,BS106) -> 0 | BV5: =+AVERAGE(BU106,BS106) -> 0 | BW5: =+AVERAGE(BW106,BU106) -> 0 | BX5: =+AVERAGE(BW106,BU106) -> 0 | BY5: =+AVERAGE(BY106,BW106) -> 0 | BZ5: =+AVERAGE(BY106,BW106) -> 0 | CA5: =+AVERAGE(CA106,BY106) -> #DIV/0! | CB5: =+AVERAGE(CA106,BY106) -> #DIV/0! | CC5: =+AVERAGE(CC106,CA106) -> #DIV/0! | CD5: =+AVERAGE(CC106,CA106) -> #DIV/0! | CE5: =+AVERAGE(CE106,CC106) -> #DIV/0! | CF5: =+AVERAGE(CE106,CC106) -> #DIV/0! | CG5: =+AVERAGE(CG106,CE106) -> #DIV/0! | CH5: =+AVERAGE(CG106,CE106) -> #DIV/0! | CI5: =+AVERAGE(CI106,CG106) -> #DIV/0! | CJ5: =+AVERAGE(CI106,CG106) -> #DIV/0! | CK5: =+AVERAGE(CK106,CI106) -> #DIV/0! | CL5: =+AVERAGE(CK106,CI106) -> #DIV/0! | CM5: =+AVERAGE(CM106,CK106) -> #DIV/0! | CN5: =+AVERAGE(CM106,CK106) -> #DIV/0! | CO5: =+AVERAGE(CO106,CM106) -> #DIV/0!
A7: Growth (%) | D7: =+D5/C5-1 -> #DIV/0! | E7: =+E5/D5-1 -> #DIV/0! | F7: =+F5/E5-1 -> #DIV/0! | G7: =+G5/F5-1 -> #DIV/0! | H7: =+H5/G5-1 -> #DIV/0! | I7: =+I5/H5-1 -> #DIV/0! | J7: =+J5/I5-1 -> #DIV/0! | K7: =+K5/J5-1 -> #DIV/0! | ... AE7: =+AE5/AD5-1 -> #DIV/0! | AL7: =AL5/AH5-1 -> #DIV/0! | AM7: =AM5/AI5-1 -> #DIV/0! | AN7: =AN5/AJ5-1 -> #DIV/0! | AO7: =AO5/AK5-1 -> #DIV/0! | AP7: =AP5/AL5-1 -> #DIV/0! | AQ7: =AQ5/AM5-1 -> #DIV/0! | AR7: =AR5/AN5-1 -> #DIV/0! | AS7: =AS5/AO5-1 -> #DIV/0! | ... CO7: =CO5/CK5-1 -> #DIV/0!
A9: Leverage | D9: =D105/D97 -> #DIV/0! | E9: =E105/E97 -> #DIV/0! | F9: =F105/F97 -> #DIV/0! | G9: =G105/G97 -> #DIV/0! | H9: =H105/H97 -> #DIV/0! | I9: =I105/I97 -> #DIV/0! | J9: =J105/J97 -> #DIV/0! | K9: =K105/K97 -> #DIV/0! | ... AE9: =AE105/AE97 -> #DIV/0! | AH9: =AH105/AH97 -> #DIV/0! | AI9: =AI105/AI97 -> #DIV/0! | AJ9: =AJ105/AJ97 -> #DIV/0! | AK9: =AK105/AK97 -> #DIV/0! | AL9: =AL105/AL97 -> #DIV/0! | AM9: =AM105/AM97 -> #DIV/0! | AN9: =AN105/AN97 -> #DIV/0! | AO9: =AO105/AO97 -> #DIV/0! | ... CO9: =CO105/CO97 -> #DIV/0!
A12: Interest Income | D12: =D27/C5 -> #DIV/0! | E12: =E27/D5 -> #DIV/0! | F12: =F27/E5 -> #DIV/0! | G12: =G27/F5 -> #DIV/0! | H12: =H27/G5 -> #DIV/0! | I12: =I27/H5 -> #DIV/0! | J12: =J27/I5 -> #DIV/0! | K12: =K27/J5 -> #DIV/0! | ... AE12: =AE27/AD5 -> #DIV/0! | AI12: =AI27/AH5 -> #DIV/0! | AJ12: =AJ27/AI5 -> #DIV/0! | AK12: =AK27/AJ5 -> #DIV/0! | AL12: =AL27/AK5 -> #DIV/0! | AM12: =AM27/AL5 -> #DIV/0! | AN12: =AN27/AM5 -> #DIV/0! | AO12: =AO27/AN5 -> #DIV/0! | AP12: =AP27/AO5 -> #DIV/0! | ... BY12: =BY27/BX5 -> #DIV/0! | BZ12: =+AVERAGE(BV12:BY12) -> #DIV/0! | CA12: =+AVERAGE(BW12:BZ12) -> #DIV/0! | CB12: =+AVERAGE(BX12:CA12) -> #DIV/0! | CC12: =+AVERAGE(BY12:CB12) -> #DIV/0! | CD12: =+AVERAGE(BZ12:CC12) -> #DIV/0! | CE12: =+AVERAGE(CA12:CD12) -> #DIV/0! | CF12: =+AVERAGE(CB12:CE12) -> #DIV/0! | CG12: =+AVERAGE(CC12:CF12) -> #DIV/0! | ... CO12: =+AVERAGE(CK12:CN12) -> #DIV/0!
A13: Interest Expenses | D13: =D28/C5 -> #DIV/0! | E13: =E28/D5 -> #DIV/0! | F13: =F28/E5 -> #DIV/0! | G13: =G28/F5 -> #DIV/0! | H13: =H28/G5 -> #DIV/0! | I13: =I28/H5 -> #DIV/0! | J13: =J28/I5 -> #DIV/0! | K13: =K28/J5 -> #DIV/0! | ... AE13: =AE28/AD5 -> #DIV/0! | AI13: =AI28/AH5 -> #DIV/0! | AJ13: =AJ28/AI5 -> #DIV/0! | AK13: =AK28/AJ5 -> #DIV/0! | AL13: =AL28/AK5 -> #DIV/0! | AM13: =AM28/AL5 -> #DIV/0! | AN13: =AN28/AM5 -> #DIV/0! | AO13: =AO28/AN5 -> #DIV/0! | AP13: =AP28/AO5 -> #DIV/0! | ... BY13: =BY28/BX5 -> #DIV/0! | BZ13: =+AVERAGE(BV13:BY13) -> #DIV/0! | CA13: =+AVERAGE(BW13:BZ13) -> #DIV/0! | CB13: =+AVERAGE(BX13:CA13) -> #DIV/0! | CC13: =+AVERAGE(BY13:CB13) -> #DIV/0! | CD13: =+AVERAGE(BZ13:CC13) -> #DIV/0! | CE13: =+AVERAGE(CA13:CD13) -> #DIV/0! | CF13: =+AVERAGE(CB13:CE13) -> #DIV/0! | CG13: =+AVERAGE(CC13:CF13) -> #DIV/0! | ... CO13: =+AVERAGE(CK13:CN13) -> #DIV/0!
A14: NII | D14: =D12-D13 -> #DIV/0! | E14: =E12-E13 -> #DIV/0! | F14: =F12-F13 -> #DIV/0! | G14: =G12-G13 -> #DIV/0! | H14: =H12-H13 -> #DIV/0! | I14: =I12-I13 -> #DIV/0! | J14: =J12-J13 -> #DIV/0! | K14: =K12-K13 -> #DIV/0! | ... AE14: =AE12-AE13 -> #DIV/0! | AI14: =AI12-AI13 -> #DIV/0! | AJ14: =AJ12-AJ13 -> #DIV/0! | AK14: =AK12-AK13 -> #DIV/0! | AL14: =AL12-AL13 -> #DIV/0! | AM14: =AM12-AM13 -> #DIV/0! | AN14: =AN12-AN13 -> #DIV/0! | AO14: =AO12-AO13 -> #DIV/0! | AP14: =AP12-AP13 -> #DIV/0! | ... CO14: =CO12-CO13 -> #DIV/0!
A15: Others income | D15: =D30/C5 -> #DIV/0! | E15: =E30/D5 -> #DIV/0! | F15: =F30/E5 -> #DIV/0! | G15: =G30/F5 -> #DIV/0! | H15: =H30/G5 -> #DIV/0! | I15: =I30/H5 -> #DIV/0! | J15: =J30/I5 -> #DIV/0! | K15: =K30/J5 -> #DIV/0! | ... AE15: =AE30/AD5 -> #DIV/0! | AI15: =AI30/AH5 -> #DIV/0! | AJ15: =AJ30/AI5 -> #DIV/0! | AK15: =AK30/AJ5 -> #DIV/0! | AL15: =AL30/AK5 -> #DIV/0! | AM15: =AM30/AL5 -> #DIV/0! | AN15: =AN30/AM5 -> #DIV/0! | AO15: =AO30/AN5 -> #DIV/0! | AP15: =AP30/AO5 -> #DIV/0! | ... BY15: =BY30/BX5 -> #DIV/0! | BZ15: =BY15 -> #DIV/0! | CA15: =BZ15 -> #DIV/0! | CB15: =CA15 -> #DIV/0! | CC15: =CB15 -> #DIV/0! | CD15: =CC15 -> #DIV/0! | CE15: =CD15 -> #DIV/0! | CF15: =CE15 -> #DIV/0! | CG15: =CF15 -> #DIV/0! | ... CO15: =CN15 -> #DIV/0!
A16: Other non-operating income
A17: Total income | D17: =D14+D15+D16 -> #DIV/0! | E17: =E14+E15+E16 -> #DIV/0! | F17: =F14+F15+F16 -> #DIV/0! | G17: =G14+G15+G16 -> #DIV/0! | H17: =H14+H15+H16 -> #DIV/0! | I17: =I14+I15+I16 -> #DIV/0! | J17: =J14+J15+J16 -> #DIV/0! | K17: =K14+K15+K16 -> #DIV/0! | ... AE17: =AE14+AE15+AE16 -> #DIV/0! | AI17: =AI14+AI15+AI16 -> #DIV/0! | AJ17: =AJ14+AJ15+AJ16 -> #DIV/0! | AK17: =AK14+AK15+AK16 -> #DIV/0! | AL17: =AL14+AL15+AL16 -> #DIV/0! | AM17: =AM14+AM15+AM16 -> #DIV/0! | AN17: =AN14+AN15+AN16 -> #DIV/0! | AO17: =AO14+AO15+AO16 -> #DIV/0! | AP17: =AP14+AP15+AP16 -> #DIV/0! | ... CO17: =CO14+CO15+CO16 -> #DIV/0!
A18: TC | D18: =D38/C5 -> #DIV/0! | E18: =E38/D5 -> #DIV/0! | F18: =F38/E5 -> #DIV/0! | G18: =G38/F5 -> #DIV/0! | H18: =H38/G5 -> #DIV/0! | I18: =I38/H5 -> #DIV/0! | J18: =J38/I5 -> #DIV/0! | K18: =K38/J5 -> #DIV/0! | ... AE18: =AE38/AD5 -> #DIV/0! | AI18: =AI38/AH5 -> #DIV/0! | AJ18: =AJ38/AI5 -> #DIV/0! | AK18: =AK38/AJ5 -> #DIV/0! | AL18: =AL38/AK5 -> #DIV/0! | AM18: =AM38/AL5 -> #DIV/0! | AN18: =AN38/AM5 -> #DIV/0! | AO18: =AO38/AN5 -> #DIV/0! | AP18: =AP38/AO5 -> #DIV/0! | ... BY18: =BY38/BX5 -> #DIV/0! | BZ18: =BY18 -> #DIV/0! | CA18: =BZ18 -> #DIV/0! | CB18: =CA18 -> #DIV/0! | CC18: =CB18 -> #DIV/0! | CD18: =CC18 -> #DIV/0! | CE18: =CD18 -> #DIV/0! | CF18: =CE18 -> #DIV/0! | CG18: =CF18 -> #DIV/0! | ... CO18: =CN18 -> #DIV/0!
A19: PPP | D19: =D17-D18 -> #DIV/0! | E19: =E17-E18 -> #DIV/0! | F19: =F17-F18 -> #DIV/0! | G19: =G17-G18 -> #DIV/0! | H19: =H17-H18 -> #DIV/0! | I19: =I17-I18 -> #DIV/0! | J19: =J17-J18 -> #DIV/0! | K19: =K17-K18 -> #DIV/0! | ... AE19: =AE17-AE18 -> #DIV/0! | AI19: =AI17-AI18 -> #DIV/0! | AJ19: =AJ17-AJ18 -> #DIV/0! | AK19: =AK17-AK18 -> #DIV/0! | AL19: =AL17-AL18 -> #DIV/0! | AM19: =AM17-AM18 -> #DIV/0! | AN19: =AN17-AN18 -> #DIV/0! | AO19: =AO17-AO18 -> #DIV/0! | AP19: =AP17-AP18 -> #DIV/0! | ... CO19: =CO17-CO18 -> #DIV/0!
A20: Provision | D20: =D41/C5 -> #DIV/0! | E20: =E41/D5 -> #DIV/0! | F20: =F41/E5 -> #DIV/0! | G20: =G41/F5 -> #DIV/0! | H20: =H41/G5 -> #DIV/0! | I20: =I41/H5 -> #DIV/0! | J20: =J41/I5 -> #DIV/0! | K20: =K41/J5 -> #DIV/0! | ... AE20: =AE41/AD5 -> #DIV/0! | AI20: =AI41/AH5 -> #DIV/0! | AJ20: =AJ41/AI5 -> #DIV/0! | AK20: =AK41/AJ5 -> #DIV/0! | AL20: =AL41/AK5 -> #DIV/0! | AM20: =AM41/AL5 -> #DIV/0! | AN20: =AN41/AM5 -> #DIV/0! | AO20: =AO41/AN5 -> #DIV/0! | AP20: =AP41/AO5 -> #DIV/0! | ... BY20: =BY41/BX5 -> #DIV/0! | BZ20: =BY20 -> #DIV/0! | CA20: =BZ20 -> #DIV/0! | CB20: =CA20 -> #DIV/0! | CC20: =CB20 -> #DIV/0! | CD20: =CC20 -> #DIV/0! | CE20: =CD20 -> #DIV/0! | CF20: =CE20 -> #DIV/0! | CG20: =CF20 -> #DIV/0! | ... CO20: =CN20 -> #DIV/0!
A21: PBT | D21: =D19-D20 -> #DIV/0! | E21: =E19-E20 -> #DIV/0! | F21: =F19-F20 -> #DIV/0! | G21: =G19-G20 -> #DIV/0! | H21: =H19-H20 -> #DIV/0! | I21: =I19-I20 -> #DIV/0! | J21: =J19-J20 -> #DIV/0! | K21: =K19-K20 -> #DIV/0! | ... AE21: =AE19-AE20 -> #DIV/0! | AI21: =AI19-AI20 -> #DIV/0! | AJ21: =AJ19-AJ20 -> #DIV/0! | AK21: =AK19-AK20 -> #DIV/0! | AL21: =AL19-AL20 -> #DIV/0! | AM21: =AM19-AM20 -> #DIV/0! | AN21: =AN19-AN20 -> #DIV/0! | AO21: =AO19-AO20 -> #DIV/0! | AP21: =AP19-AP20 -> #DIV/0! | ... CO21: =CO19-CO20 -> #DIV/0!
A22: Tax | D22: =D43/C5 -> #DIV/0! | E22: =E43/D5 -> #DIV/0! | F22: =F43/E5 -> #DIV/0! | G22: =G43/F5 -> #DIV/0! | H22: =H43/G5 -> #DIV/0! | I22: =I43/H5 -> #DIV/0! | J22: =J43/I5 -> #DIV/0! | K22: =K43/J5 -> #DIV/0! | ... AE22: =AE43/AD5 -> #DIV/0! | AI22: =AI43/AH5 -> #DIV/0! | AJ22: =AJ43/AI5 -> #DIV/0! | AK22: =AK43/AJ5 -> #DIV/0! | AL22: =AL43/AK5 -> #DIV/0! | AM22: =AM43/AL5 -> #DIV/0! | AN22: =AN43/AM5 -> #DIV/0! | AO22: =AO43/AN5 -> #DIV/0! | AP22: =AP43/AO5 -> #DIV/0! | ... CO22: =CO43/CN5 -> #DIV/0!
A23: PAT | D23: =D21-D22 -> #DIV/0! | E23: =E21-E22 -> #DIV/0! | F23: =F21-F22 -> #DIV/0! | G23: =G21-G22 -> #DIV/0! | H23: =H21-H22 -> #DIV/0! | I23: =I21-I22 -> #DIV/0! | J23: =J21-J22 -> #DIV/0! | K23: =K21-K22 -> #DIV/0! | ... AE23: =AE21-AE22 -> #DIV/0! | AI23: =AI21-AI22 -> #DIV/0! | AJ23: =AJ21-AJ22 -> #DIV/0! | AK23: =AK21-AK22 -> #DIV/0! | AL23: =AL21-AL22 -> #DIV/0! | AM23: =AM21-AM22 -> #DIV/0! | AN23: =AN21-AN22 -> #DIV/0! | AO23: =AO21-AO22 -> #DIV/0! | AP23: =AP21-AP22 -> #DIV/0! | ... CO23: =CO21-CO22 -> #DIV/0!
A25: Presentation Data (End)
A26: Profit & Loss- Annual (Start)
A27: Interest Income | B27: =+'Annual Raw'!C14 -> 0 | C27: =+'Annual Raw'!D14 -> 0 | D27: =+'Annual Raw'!E14 -> 0 | E27: =+'Annual Raw'!F14 -> 0 | F27: =+'Annual Raw'!G14 -> 0 | G27: =+'Annual Raw'!H14 -> 0 | H27: =+'Annual Raw'!I14 -> 0 | I27: =+'Annual Raw'!J14 -> 0 | ... Z27: =+'Annual Raw'!AA14 -> 0 | AA27: =SUM(BV27:BY27) -> 0 | AB27: =SUM(BZ27:CC27) -> #DIV/0! | AC27: =SUM(CD27:CG27) -> #DIV/0! | AD27: =SUM(CH27:CK27) -> #DIV/0! | AE27: =SUM(CL27:CO27) -> #DIV/0! | AH27: =+'QTR Raw'!D13 -> 0 | AI27: =+'QTR Raw'!E13 -> 0 | AJ27: =+'QTR Raw'!F13 -> 0 | AK27: =+'QTR Raw'!G13 -> 0 | AL27: =+'QTR Raw'!H13 -> 0 | AM27: =+'QTR Raw'!I13 -> 0 | AN27: =+'QTR Raw'!J13 -> 0 | AO27: =+'QTR Raw'!K13 -> 0 | ... BY27: =+'QTR Raw'!AU13 -> 0 | BZ27: =BZ12*BY5 -> #DIV/0! | CA27: =CA12*BZ5 -> #DIV/0! | CB27: =CB12*CA5 -> #DIV/0! | CC27: =CC12*CB5 -> #DIV/0! | CD27: =CD12*CC5 -> #DIV/0! | CE27: =CE12*CD5 -> #DIV/0! | CF27: =CF12*CE5 -> #DIV/0! | CG27: =CG12*CF5 -> #DIV/0! | ... CO27: =CO12*CN5 -> #DIV/0!
A28: Interest exp | B28: =+'Annual Raw'!C29 -> 0 | C28: =+'Annual Raw'!D29 -> 0 | D28: =+'Annual Raw'!E29 -> 0 | E28: =+'Annual Raw'!F29 -> 0 | F28: =+'Annual Raw'!G29 -> 0 | G28: =+'Annual Raw'!H29 -> 0 | H28: =+'Annual Raw'!I29 -> 0 | I28: =+'Annual Raw'!J29 -> 0 | ... Z28: =+'Annual Raw'!AA29 -> 0 | AA28: =SUM(BV28:BY28) -> 0 | AB28: =SUM(BZ28:CC28) -> #DIV/0! | AC28: =SUM(CD28:CG28) -> #DIV/0! | AD28: =SUM(CH28:CK28) -> #DIV/0! | AE28: =SUM(CL28:CO28) -> #DIV/0! | AH28: =+'QTR Raw'!D14+'QTR Raw'!D33 -> 0 | AI28: =+'QTR Raw'!E14+'QTR Raw'!E33 -> 0 | AJ28: =+'QTR Raw'!F14+'QTR Raw'!F33 -> 0 | AK28: =+'QTR Raw'!G14+'QTR Raw'!G33 -> 0 | AL28: =+'QTR Raw'!H14+'QTR Raw'!H33 -> 0 | AM28: =+'QTR Raw'!I14+'QTR Raw'!I33 -> 0 | AN28: =+'QTR Raw'!J14+'QTR Raw'!J33 -> 0 | AO28: =+'QTR Raw'!K14+'QTR Raw'!K33 -> 0 | ... BY28: =+'QTR Raw'!AU14+'QTR Raw'!AU33 -> 0 | BZ28: =BZ13*BY5 -> #DIV/0! | CA28: =CA13*BZ5 -> #DIV/0! | CB28: =CB13*CA5 -> #DIV/0! | CC28: =CC13*CB5 -> #DIV/0! | CD28: =CD13*CC5 -> #DIV/0! | CE28: =CE13*CD5 -> #DIV/0! | CF28: =CF13*CE5 -> #DIV/0! | CG28: =CG13*CF5 -> #DIV/0! | ... CO28: =CO13*CN5 -> #DIV/0!
A29: NII | B29: =B27-B28 -> 0 | C29: =C27-C28 -> 0 | D29: =D27-D28 -> 0 | E29: =E27-E28 -> 0 | F29: =F27-F28 -> 0 | G29: =G27-G28 -> 0 | H29: =H27-H28 -> 0 | I29: =I27-I28 -> 0 | ... AE29: =AE27-AE28 -> #DIV/0! | AH29: =AH27-AH28 -> 0 | AI29: =AI27-AI28 -> 0 | AJ29: =AJ27-AJ28 -> 0 | AK29: =AK27-AK28 -> 0 | AL29: =AL27-AL28 -> 0 | AM29: =AM27-AM28 -> 0 | AN29: =AN27-AN28 -> 0 | AO29: =AO27-AO28 -> 0 | ... CO29: =CO27-CO28 -> #DIV/0!
A30: Other Income | B30: =+'Annual Raw'!C27 -> 0 | C30: =+'Annual Raw'!D27 -> 0 | D30: =+'Annual Raw'!E27 -> 0 | E30: =+'Annual Raw'!F27 -> 0 | F30: =+'Annual Raw'!G27 -> 0 | G30: =+'Annual Raw'!H27 -> 0 | H30: =+'Annual Raw'!I27 -> 0 | I30: =+'Annual Raw'!J27 -> 0 | ... Z30: =+'Annual Raw'!AA27 -> 0 | AA30: =SUM(BV30:BY30) -> 0 | AB30: =SUM(BZ30:CC30) -> #DIV/0! | AC30: =SUM(CD30:CG30) -> #DIV/0! | AD30: =SUM(CH30:CK30) -> #DIV/0! | AE30: =SUM(CL30:CO30) -> #DIV/0! | AH30: =+'QTR Raw'!D32 -> 0 | AI30: =+'QTR Raw'!E32 -> 0 | AJ30: =+'QTR Raw'!F32 -> 0 | AK30: =+'QTR Raw'!G32 -> 0 | AL30: =+'QTR Raw'!H32 -> 0 | AM30: =+'QTR Raw'!I32 -> 0 | AN30: =+'QTR Raw'!J32 -> 0 | AO30: =+'QTR Raw'!K32 -> 0 | ... BY30: =+'QTR Raw'!AU32 -> 0 | BZ30: =BZ15*BY5 -> #DIV/0! | CA30: =CA15*BZ5 -> #DIV/0! | CB30: =CB15*CA5 -> #DIV/0! | CC30: =CC15*CB5 -> #DIV/0! | CD30: =CD15*CC5 -> #DIV/0! | CE30: =CE15*CD5 -> #DIV/0! | CF30: =CF15*CE5 -> #DIV/0! | CG30: =CG15*CF5 -> #DIV/0! | ... CO30: =CO15*CN5 -> #DIV/0!
A31: TI | B31: =B29+B30 -> 0 | C31: =C29+C30 -> 0 | D31: =D29+D30 -> 0 | E31: =E29+E30 -> 0 | F31: =F29+F30 -> 0 | G31: =G29+G30 -> 0 | H31: =H29+H30 -> 0 | I31: =I29+I30 -> 0 | ... AE31: =AE29+AE30 -> #DIV/0! | AH31: =AH29+AH30 -> 0 | AI31: =AI29+AI30 -> 0 | AJ31: =AJ29+AJ30 -> 0 | AK31: =AK29+AK30 -> 0 | AL31: =AL29+AL30 -> 0 | AM31: =AM29+AM30 -> 0 | AN31: =AN29+AN30 -> 0 | AO31: =AO29+AO30 -> 0 | ... CO31: =CO29+CO30 -> #DIV/0!
A32: YOY% | C32: =+IF(B31<0,1-C31/B31,C31/B31-1) -> #DIV/0! | D32: =+IF(C31<0,1-D31/C31,D31/C31-1) -> #DIV/0! | E32: =+IF(D31<0,1-E31/D31,E31/D31-1) -> #DIV/0! | F32: =+IF(E31<0,1-F31/E31,F31/E31-1) -> #DIV/0! | G32: =+IF(F31<0,1-G31/F31,G31/F31-1) -> #DIV/0! | H32: =+IF(G31<0,1-H31/G31,H31/G31-1) -> #DIV/0! | I32: =+IF(H31<0,1-I31/H31,I31/H31-1) -> #DIV/0! | J32: =+IF(I31<0,1-J31/I31,J31/I31-1) -> #DIV/0! | ... AE32: =+IF(AD31<0,1-AE31/AD31,AE31/AD31-1) -> #DIV/0! | AL32: =+IF(AH31<0,1-AL31/AH31,AL31/AH31-1) -> #DIV/0! | AM32: =+IF(AI31<0,1-AM31/AI31,AM31/AI31-1) -> #DIV/0! | AN32: =+IF(AJ31<0,1-AN31/AJ31,AN31/AJ31-1) -> #DIV/0! | AO32: =+IF(AK31<0,1-AO31/AK31,AO31/AK31-1) -> #DIV/0! | AP32: =+IF(AL31<0,1-AP31/AL31,AP31/AL31-1) -> #DIV/0! | AQ32: =+IF(AM31<0,1-AQ31/AM31,AQ31/AM31-1) -> #DIV/0! | AR32: =+IF(AN31<0,1-AR31/AN31,AR31/AN31-1) -> #DIV/0! | AS32: =+IF(AO31<0,1-AS31/AO31,AS31/AO31-1) -> #DIV/0! | ... CO32: =+IF(CK31<0,1-CO31/CK31,CO31/CK31-1) -> #DIV/0!
A33: Employee Cost | B33: =+'Annual Raw'!C18 -> 0 | C33: =+'Annual Raw'!D18 -> 0 | D33: =+'Annual Raw'!E18 -> 0 | E33: =+'Annual Raw'!F18 -> 0 | F33: =+'Annual Raw'!G18 -> 0 | G33: =+'Annual Raw'!H18 -> 0 | H33: =+'Annual Raw'!I18 -> 0 | I33: =+'Annual Raw'!J18 -> 0 | ... Z33: =+'Annual Raw'!AA18 -> 0 | AA33: =SUM(BV33:BY33) -> 0 | AB33: =SUM(BZ33:CC33) -> #DIV/0! | AC33: =SUM(CD33:CG33) -> #DIV/0! | AD33: =SUM(CH33:CK33) -> #DIV/0! | AE33: =SUM(CL33:CO33) -> #DIV/0! | AH33: =+'QTR Raw'!D20 -> 0 | AI33: =+'QTR Raw'!E20 -> 0 | AJ33: =+'QTR Raw'!F20 -> 0 | AK33: =+'QTR Raw'!G20 -> 0 | AL33: =+'QTR Raw'!H20 -> 0 | AM33: =+'QTR Raw'!I20 -> 0 | AN33: =+'QTR Raw'!J20 -> 0 | AO33: =+'QTR Raw'!K20 -> 0 | ... BY33: =+'QTR Raw'!AU20 -> 0 | BZ33: =BZ18*BY5 -> #DIV/0! | CA33: =CA18*BZ5 -> #DIV/0! | CB33: =CB18*CA5 -> #DIV/0! | CC33: =CC18*CB5 -> #DIV/0! | CD33: =CD18*CC5 -> #DIV/0! | CE33: =CE18*CD5 -> #DIV/0! | CF33: =CF18*CE5 -> #DIV/0! | CG33: =CG18*CF5 -> #DIV/0! | ... CO33: =CO18*CN5 -> #DIV/0!
A34: Operating & Establishment Expenses | B34: =+'Annual Raw'!C19+'Annual Raw'!C20+'Annual Raw'!C21+'Annual Raw'!C17+'Annual Raw'!C16+'Annual Raw'!C15-'Annual Raw'!C24 -> 0 | C34: =+'Annual Raw'!D19+'Annual Raw'!D20+'Annual Raw'!D21+'Annual Raw'!D17+'Annual Raw'!D16+'Annual Raw'!D15-'Annual Raw'!D24 -> 0 | D34: =+'Annual Raw'!E19+'Annual Raw'!E20+'Annual Raw'!E21+'Annual Raw'!E17+'Annual Raw'!E16+'Annual Raw'!E15-'Annual Raw'!E24 -> 0 | E34: =+'Annual Raw'!F19+'Annual Raw'!F20+'Annual Raw'!F21+'Annual Raw'!F17+'Annual Raw'!F16+'Annual Raw'!F15-'Annual Raw'!F24 -> 0 | F34: =+'Annual Raw'!G19+'Annual Raw'!G20+'Annual Raw'!G21+'Annual Raw'!G17+'Annual Raw'!G16+'Annual Raw'!G15-'Annual Raw'!G24 -> 0 | G34: =+'Annual Raw'!H19+'Annual Raw'!H20+'Annual Raw'!H21+'Annual Raw'!H17+'Annual Raw'!H16+'Annual Raw'!H15-'Annual Raw'!H24 -> 0 | H34: =+'Annual Raw'!I19+'Annual Raw'!I20+'Annual Raw'!I21+'Annual Raw'!I17+'Annual Raw'!I16+'Annual Raw'!I15-'Annual Raw'!I24 -> 0 | I34: =+'Annual Raw'!J19+'Annual Raw'!J20+'Annual Raw'!J21+'Annual Raw'!J17+'Annual Raw'!J16+'Annual Raw'!J15-'Annual Raw'!J24 -> 0 | ... Z34: =+'Annual Raw'!AA19+'Annual Raw'!AA20+'Annual Raw'!AA21+'Annual Raw'!AA17+'Annual Raw'!AA16+'Annual Raw'!AA15-'Annual Raw'!AA24 -> 0 | AA34: =SUM(BV34:BY34) -> 0 | AB34: =SUM(BZ34:CC34) -> 0 | AC34: =SUM(CD34:CG34) -> 0 | AD34: =SUM(CH34:CK34) -> 0 | AE34: =SUM(CL34:CO34) -> 0 | AH34: =+'QTR Raw'!D15+'QTR Raw'!D21+'QTR Raw'!D17+'QTR Raw'!D18+'QTR Raw'!D19+'QTR Raw'!D16+'QTR Raw'!D25 -> 0 | AI34: =+'QTR Raw'!E15+'QTR Raw'!E21+'QTR Raw'!E17+'QTR Raw'!E18+'QTR Raw'!E19+'QTR Raw'!E16+'QTR Raw'!E25 -> 0 | AJ34: =+'QTR Raw'!F15+'QTR Raw'!F21+'QTR Raw'!F17+'QTR Raw'!F18+'QTR Raw'!F19+'QTR Raw'!F16+'QTR Raw'!F25 -> 0 | AK34: =+'QTR Raw'!G15+'QTR Raw'!G21+'QTR Raw'!G17+'QTR Raw'!G18+'QTR Raw'!G19+'QTR Raw'!G16+'QTR Raw'!G25 -> 0 | AL34: =+'QTR Raw'!H15+'QTR Raw'!H21+'QTR Raw'!H17+'QTR Raw'!H18+'QTR Raw'!H19+'QTR Raw'!H16+'QTR Raw'!H25 -> 0 | AM34: =+'QTR Raw'!I15+'QTR Raw'!I21+'QTR Raw'!I17+'QTR Raw'!I18+'QTR Raw'!I19+'QTR Raw'!I16+'QTR Raw'!I25 -> 0 | AN34: =+'QTR Raw'!J15+'QTR Raw'!J21+'QTR Raw'!J17+'QTR Raw'!J18+'QTR Raw'!J19+'QTR Raw'!J16+'QTR Raw'!J25 -> 0 | AO34: =+'QTR Raw'!K15+'QTR Raw'!K21+'QTR Raw'!K17+'QTR Raw'!K18+'QTR Raw'!K19+'QTR Raw'!K16+'QTR Raw'!K25 -> 0 | ... BY34: =+'QTR Raw'!AU15+'QTR Raw'!AU21+'QTR Raw'!AU17+'QTR Raw'!AU18+'QTR Raw'!AU19+'QTR Raw'!AU16+'QTR Raw'!AU25 -> 0
A35: Depreciation | B35: =+'Annual Raw'!C31 -> 0 | C35: =+'Annual Raw'!D31 -> 0 | D35: =+'Annual Raw'!E31 -> 0 | E35: =+'Annual Raw'!F31 -> 0 | F35: =+'Annual Raw'!G31 -> 0 | G35: =+'Annual Raw'!H31 -> 0 | H35: =+'Annual Raw'!I31 -> 0 | I35: =+'Annual Raw'!J31 -> 0 | ... Z35: =+'Annual Raw'!AA31 -> 0 | AA35: =SUM(BV35:BY35) -> 0 | AB35: =SUM(BZ35:CC35) -> 0 | AC35: =SUM(CD35:CG35) -> 0 | AD35: =SUM(CH35:CK35) -> 0 | AE35: =SUM(CL35:CO35) -> 0 | AH35: =+'QTR Raw'!D37 -> 0 | AI35: =+'QTR Raw'!E37 -> 0 | AJ35: =+'QTR Raw'!F37 -> 0 | AK35: =+'QTR Raw'!G37 -> 0 | AL35: =+'QTR Raw'!H37 -> 0 | AM35: =+'QTR Raw'!I37 -> 0 | AN35: =+'QTR Raw'!J37 -> 0 | AO35: =+'QTR Raw'!K37 -> 0 | ... BY35: =+'QTR Raw'!AU37 -> 0
A36: Advertisement & Sales Promotion | B36: =+'Annual Raw'!C22 -> 0 | C36: =+'Annual Raw'!D22 -> 0 | D36: =+'Annual Raw'!E22 -> 0 | E36: =+'Annual Raw'!F22 -> 0 | F36: =+'Annual Raw'!G22 -> 0 | G36: =+'Annual Raw'!H22 -> 0 | H36: =+'Annual Raw'!I22 -> 0 | I36: =+'Annual Raw'!J22 -> 0 | ... Z36: =+'Annual Raw'!AA22 -> 0 | AA36: =SUM(BV36:BY36) -> 0 | AB36: =SUM(BZ36:CC36) -> 0 | AC36: =SUM(CD36:CG36) -> 0 | AD36: =SUM(CH36:CK36) -> 0 | AE36: =SUM(CL36:CO36) -> 0 | AH36: =+'QTR Raw'!D22 -> 0 | AI36: =+'QTR Raw'!E22 -> 0 | AJ36: =+'QTR Raw'!F22 -> 0 | AK36: =+'QTR Raw'!G22 -> 0 | AL36: =+'QTR Raw'!H22 -> 0 | AM36: =+'QTR Raw'!I22 -> 0 | AN36: =+'QTR Raw'!J22 -> 0 | AO36: =+'QTR Raw'!K22 -> 0 | ... BY36: =+'QTR Raw'!AU22 -> 0
A37: Other Expenses | AH37: =+'QTR Raw'!D23+'QTR Raw'!D24+'QTR Raw'!D26 -> 0 | AI37: =+'QTR Raw'!E23+'QTR Raw'!E24+'QTR Raw'!E26 -> 0 | AJ37: =+'QTR Raw'!F23+'QTR Raw'!F24+'QTR Raw'!F26 -> 0 | AK37: =+'QTR Raw'!G23+'QTR Raw'!G24+'QTR Raw'!G26 -> 0 | AL37: =+'QTR Raw'!H23+'QTR Raw'!H24+'QTR Raw'!H26 -> 0 | AM37: =+'QTR Raw'!I23+'QTR Raw'!I24+'QTR Raw'!I26 -> 0 | AN37: =+'QTR Raw'!J23+'QTR Raw'!J24+'QTR Raw'!J26 -> 0 | AO37: =+'QTR Raw'!K23+'QTR Raw'!K24+'QTR Raw'!K26 -> 0 | ... BY37: =+'QTR Raw'!AU23+'QTR Raw'!AU24+'QTR Raw'!AU26 -> 0
A38: TC | B38: =SUM(B33:B37) -> 0 | C38: =SUM(C33:C37) -> 0 | D38: =SUM(D33:D37) -> 0 | E38: =SUM(E33:E37) -> 0 | F38: =SUM(F33:F37) -> 0 | G38: =SUM(G33:G37) -> 0 | H38: =SUM(H33:H37) -> 0 | I38: =SUM(I33:I37) -> 0 | ... AE38: =SUM(AE33:AE37) -> #DIV/0! | AH38: =SUM(AH33:AH37) -> 0 | AI38: =SUM(AI33:AI37) -> 0 | AJ38: =SUM(AJ33:AJ37) -> 0 | AK38: =SUM(AK33:AK37) -> 0 | AL38: =SUM(AL33:AL37) -> 0 | AM38: =SUM(AM33:AM37) -> 0 | AN38: =SUM(AN33:AN37) -> 0 | AO38: =SUM(AO33:AO37) -> 0 | ... CO38: =SUM(CO33:CO37) -> #DIV/0!
A39: PPP | B39: =+B31-B38 -> 0 | C39: =+C31-C38 -> 0 | D39: =+D31-D38 -> 0 | E39: =+E31-E38 -> 0 | F39: =+F31-F38 -> 0 | G39: =+G31-G38 -> 0 | H39: =+H31-H38 -> 0 | I39: =+I31-I38 -> 0 | ... AE39: =+AE31-AE38 -> #DIV/0! | AH39: =+AH31-AH38 -> 0 | AI39: =+AI31-AI38 -> 0 | AJ39: =+AJ31-AJ38 -> 0 | AK39: =+AK31-AK38 -> 0 | AL39: =+AL31-AL38 -> 0 | AM39: =+AM31-AM38 -> 0 | AN39: =+AN31-AN38 -> 0 | AO39: =+AO31-AO38 -> 0 | ... CO39: =+CO31-CO38 -> #DIV/0!
A40: YOY% | C40: =+IF(B39<0,1-C39/B39,C39/B39-1) -> #DIV/0! | D40: =+IF(C39<0,1-D39/C39,D39/C39-1) -> #DIV/0! | E40: =+IF(D39<0,1-E39/D39,E39/D39-1) -> #DIV/0! | F40: =+IF(E39<0,1-F39/E39,F39/E39-1) -> #DIV/0! | G40: =+IF(F39<0,1-G39/F39,G39/F39-1) -> #DIV/0! | H40: =+IF(G39<0,1-H39/G39,H39/G39-1) -> #DIV/0! | I40: =+IF(H39<0,1-I39/H39,I39/H39-1) -> #DIV/0! | J40: =+IF(I39<0,1-J39/I39,J39/I39-1) -> #DIV/0! | ... AE40: =+IF(AD39<0,1-AE39/AD39,AE39/AD39-1) -> #DIV/0! | AL40: =+IF(AH39<0,1-AL39/AH39,AL39/AH39-1) -> #DIV/0! | AM40: =+IF(AI39<0,1-AM39/AI39,AM39/AI39-1) -> #DIV/0! | AN40: =+IF(AJ39<0,1-AN39/AJ39,AN39/AJ39-1) -> #DIV/0! | AO40: =+IF(AK39<0,1-AO39/AK39,AO39/AK39-1) -> #DIV/0! | AP40: =+IF(AL39<0,1-AP39/AL39,AP39/AL39-1) -> #DIV/0! | AQ40: =+IF(AM39<0,1-AQ39/AM39,AQ39/AM39-1) -> #DIV/0! | AR40: =+IF(AN39<0,1-AR39/AN39,AR39/AN39-1) -> #DIV/0! | AS40: =+IF(AO39<0,1-AS39/AO39,AS39/AO39-1) -> #DIV/0! | ... CO40: =+IF(CK39<0,1-CO39/CK39,CO39/CK39-1) -> #DIV/0!
A41: Provisions and Contingencies | B41: =+'Annual Raw'!C23 -> 0 | C41: =+'Annual Raw'!D23 -> 0 | D41: =+'Annual Raw'!E23 -> 0 | E41: =+'Annual Raw'!F23 -> 0 | F41: =+'Annual Raw'!G23 -> 0 | G41: =+'Annual Raw'!H23 -> 0 | H41: =+'Annual Raw'!I23 -> 0 | I41: =+'Annual Raw'!J23 -> 0 | ... Z41: =+'Annual Raw'!AA23 -> 0 | AA41: =SUM(BV41:BY41) -> 0 | AB41: =SUM(BZ41:CC41) -> #DIV/0! | AC41: =SUM(CD41:CG41) -> #DIV/0! | AD41: =SUM(CH41:CK41) -> #DIV/0! | AE41: =SUM(CL41:CO41) -> #DIV/0! | AH41: =+'QTR Raw'!D36+'QTR Raw'!D27 -> 0 | AI41: =+'QTR Raw'!E36+'QTR Raw'!E27 -> 0 | AJ41: =+'QTR Raw'!F36+'QTR Raw'!F27 -> 0 | AK41: =+'QTR Raw'!G36+'QTR Raw'!G27 -> 0 | AL41: =+'QTR Raw'!H36+'QTR Raw'!H27 -> 0 | AM41: =+'QTR Raw'!I36+'QTR Raw'!I27 -> 0 | AN41: =+'QTR Raw'!J36+'QTR Raw'!J27 -> 0 | AO41: =+'QTR Raw'!K36+'QTR Raw'!K27 -> 0 | ... BY41: =+'QTR Raw'!AU36+'QTR Raw'!AU27 -> 0 | BZ41: =BZ20*BY5 -> #DIV/0! | CA41: =CA20*BZ5 -> #DIV/0! | CB41: =CB20*CA5 -> #DIV/0! | CC41: =CC20*CB5 -> #DIV/0! | CD41: =CD20*CC5 -> #DIV/0! | CE41: =CE20*CD5 -> #DIV/0! | CF41: =CF20*CE5 -> #DIV/0! | CG41: =CG20*CF5 -> #DIV/0! | ... CO41: =CO20*CN5 -> #DIV/0!
A42: PBT | B42: =B39-B41 -> 0 | C42: =C39-C41 -> 0 | D42: =D39-D41 -> 0 | E42: =E39-E41 -> 0 | F42: =F39-F41 -> 0 | G42: =G39-G41 -> 0 | H42: =H39-H41 -> 0 | I42: =I39-I41 -> 0 | ... AE42: =AE39-AE41 -> #DIV/0! | AH42: =AH39-AH41 -> 0 | AI42: =AI39-AI41 -> 0 | AJ42: =AJ39-AJ41 -> 0 | AK42: =AK39-AK41 -> 0 | AL42: =AL39-AL41 -> 0 | AM42: =AM39-AM41 -> 0 | AN42: =AN39-AN41 -> 0 | AO42: =AO39-AO41 -> 0 | ... CO42: =CO39-CO41 -> #DIV/0!
A43: Tax | B43: =+'Annual Raw'!C36 -> 0 | C43: =+'Annual Raw'!D36 -> 0 | D43: =+'Annual Raw'!E36 -> 0 | E43: =+'Annual Raw'!F36 -> 0 | F43: =+'Annual Raw'!G36 -> 0 | G43: =+'Annual Raw'!H36 -> 0 | H43: =+'Annual Raw'!I36 -> 0 | I43: =+'Annual Raw'!J36 -> 0 | ... Z43: =+'Annual Raw'!AA36 -> 0 | AA43: =SUM(BV43:BY43) -> 0 | AB43: =SUM(BZ43:CC43) -> #DIV/0! | AC43: =SUM(CD43:CG43) -> #DIV/0! | AD43: =SUM(CH43:CK43) -> #DIV/0! | AE43: =SUM(CL43:CO43) -> #DIV/0! | AH43: =+'QTR Raw'!D38 -> 0 | AI43: =+'QTR Raw'!E38 -> 0 | AJ43: =+'QTR Raw'!F38 -> 0 | AK43: =+'QTR Raw'!G38 -> 0 | AL43: =+'QTR Raw'!H38 -> 0 | AM43: =+'QTR Raw'!I38 -> 0 | AN43: =+'QTR Raw'!J38 -> 0 | AO43: =+'QTR Raw'!K38 -> 0 | ... BY43: =+'QTR Raw'!AU38 -> 0 | BZ43: =BZ42*0.26 -> #DIV/0! | CA43: =CA42*0.26 -> #DIV/0! | CB43: =CB42*0.26 -> #DIV/0! | CC43: =CC42*0.26 -> #DIV/0! | CD43: =CD42*0.26 -> #DIV/0! | CE43: =CE42*0.26 -> #DIV/0! | CF43: =CF42*0.26 -> #DIV/0! | CG43: =CG42*0.26 -> #DIV/0! | ... CO43: =CO42*0.26 -> #DIV/0!
A44: PAT | B44: =B42-B43 -> 0 | C44: =C42-C43 -> 0 | D44: =D42-D43 -> 0 | E44: =E42-E43 -> 0 | F44: =F42-F43 -> 0 | G44: =G42-G43 -> 0 | H44: =H42-H43 -> 0 | I44: =I42-I43 -> 0 | ... AE44: =AE42-AE43 -> #DIV/0! | AH44: =AH42-AH43 -> 0 | AI44: =AI42-AI43 -> 0 | AJ44: =AJ42-AJ43 -> 0 | AK44: =AK42-AK43 -> 0 | AL44: =AL42-AL43 -> 0 | AM44: =AM42-AM43 -> 0 | AN44: =AN42-AN43 -> 0 | AO44: =AO42-AO43 -> 0 | ... CO44: =CO42-CO43 -> #DIV/0!
A45: Minority Interest | B45: =+'Annual Raw'!C42 -> 0 | C45: =+'Annual Raw'!D42 -> 0 | D45: =+'Annual Raw'!E42 -> 0 | E45: =+'Annual Raw'!F42 -> 0 | F45: =+'Annual Raw'!G42 -> 0 | G45: =+'Annual Raw'!H42 -> 0 | H45: =+'Annual Raw'!I42 -> 0 | I45: =+'Annual Raw'!J42 -> 0 | ... Z45: =+'Annual Raw'!AA42 -> 0 | AA45: =SUM(BV45:BY45) -> 0 | AB45: =SUM(BZ45:CC45) -> 0 | AC45: =SUM(CD45:CG45) -> 0 | AD45: =SUM(CH45:CK45) -> 0 | AE45: =SUM(CL45:CO45) -> 0 | AH45: =+'QTR Raw'!D39 -> 0 | AI45: =+'QTR Raw'!E39 -> 0 | AJ45: =+'QTR Raw'!F39 -> 0 | AK45: =+'QTR Raw'!G39 -> 0 | AL45: =+'QTR Raw'!H39 -> 0 | AM45: =+'QTR Raw'!I39 -> 0 | AN45: =+'QTR Raw'!J39 -> 0 | AO45: =+'QTR Raw'!K39 -> 0 | ... BY45: =+'QTR Raw'!AU39 -> 0 | BZ45: =+BY45 -> 0 | CA45: =+BZ45 -> 0 | CB45: =+CA45 -> 0 | CC45: =+CB45 -> 0 | CD45: =+CC45 -> 0 | CE45: =+CD45 -> 0 | CF45: =+CE45 -> 0 | CG45: =+CF45 -> 0 | ... CO45: =+CN45 -> 0
A46: Share of Associates | B46: =+'Annual Raw'!C43 -> 0 | C46: =+'Annual Raw'!D43 -> 0 | D46: =+'Annual Raw'!E43 -> 0 | E46: =+'Annual Raw'!F43 -> 0 | F46: =+'Annual Raw'!G43 -> 0 | G46: =+'Annual Raw'!H43 -> 0 | H46: =+'Annual Raw'!I43 -> 0 | I46: =+'Annual Raw'!J43 -> 0 | ... Z46: =+'Annual Raw'!AA43 -> 0 | AA46: =SUM(BV46:BY46) -> 0 | AB46: =SUM(BZ46:CC46) -> 0 | AC46: =SUM(CD46:CG46) -> 0 | AD46: =SUM(CH46:CK46) -> 0 | AE46: =SUM(CL46:CO46) -> 0 | AH46: =+'QTR Raw'!D40 -> 0 | AI46: =+'QTR Raw'!E40 -> 0 | AJ46: =+'QTR Raw'!F40 -> 0 | AK46: =+'QTR Raw'!G40 -> 0 | AL46: =+'QTR Raw'!H40 -> 0 | AM46: =+'QTR Raw'!I40 -> 0 | AN46: =+'QTR Raw'!J40 -> 0 | AO46: =+'QTR Raw'!K40 -> 0 | ... BY46: =+'QTR Raw'!AU40 -> 0 | BZ46: =+BY46 -> 0 | CA46: =+BZ46 -> 0 | CB46: =+CA46 -> 0 | CC46: =+CB46 -> 0 | CD46: =+CC46 -> 0 | CE46: =+CD46 -> 0 | CF46: =+CE46 -> 0 | CG46: =+CF46 -> 0 | ... CO46: =+CN46 -> 0
A47: Exceptional Income/Expenses | B47: =+'Annual Raw'!C34+'Annual Raw'!C44+'Annual Raw'!C33+'Annual Raw'!C40 -> 0 | C47: =+'Annual Raw'!D34+'Annual Raw'!D44+'Annual Raw'!D33+'Annual Raw'!D40 -> 0 | D47: =+'Annual Raw'!E34+'Annual Raw'!E44+'Annual Raw'!E33+'Annual Raw'!E40 -> 0 | E47: =+'Annual Raw'!F34+'Annual Raw'!F44+'Annual Raw'!F33+'Annual Raw'!F40 -> 0 | F47: =+'Annual Raw'!G34+'Annual Raw'!G44+'Annual Raw'!G33+'Annual Raw'!G40 -> 0 | G47: =+'Annual Raw'!H34+'Annual Raw'!H44+'Annual Raw'!H33+'Annual Raw'!H40 -> 0 | H47: =+'Annual Raw'!I34+'Annual Raw'!I44+'Annual Raw'!I33+'Annual Raw'!I40 -> 0 | I47: =+'Annual Raw'!J34+'Annual Raw'!J44+'Annual Raw'!J33+'Annual Raw'!J40 -> 0 | ... Z47: =+'Annual Raw'!AA34+'Annual Raw'!AA44+'Annual Raw'!AA33+'Annual Raw'!AA40 -> 0 | AH47: =+'QTR Raw'!D41+'QTR Raw'!D34+'QTR Raw'!D35 -> 0 | AI47: =+'QTR Raw'!E41+'QTR Raw'!E34+'QTR Raw'!E35 -> 0 | AJ47: =+'QTR Raw'!F41+'QTR Raw'!F34+'QTR Raw'!F35 -> 0 | AK47: =+'QTR Raw'!G41+'QTR Raw'!G34+'QTR Raw'!G35 -> 0 | AL47: =+'QTR Raw'!H41+'QTR Raw'!H34+'QTR Raw'!H35 -> 0 | AM47: =+'QTR Raw'!I41+'QTR Raw'!I34+'QTR Raw'!I35 -> 0 | AN47: =+'QTR Raw'!J41+'QTR Raw'!J34+'QTR Raw'!J35 -> 0 | AO47: =+'QTR Raw'!K41+'QTR Raw'!K34+'QTR Raw'!K35 -> 0 | ... BY47: =+'QTR Raw'!AU41+'QTR Raw'!AU34+'QTR Raw'!AU35 -> 0
A48: Consolidated Net Profit | B48: =B44+B45+B46+B47 -> 0 | C48: =C44+C45+C46+C47 -> 0 | D48: =D44+D45+D46+D47 -> 0 | E48: =E44+E45+E46+E47 -> 0 | F48: =F44+F45+F46+F47 -> 0 | G48: =G44+G45+G46+G47 -> 0 | H48: =H44+H45+H46+H47 -> 0 | I48: =I44+I45+I46+I47 -> 0 | ... Z48: =Z44+Z45+Z46+Z47 -> 0 | AA48: =AA44+AA45+AA46 -> 0 | AB48: =AB44+AB45+AB46 -> #DIV/0! | AC48: =AC44+AC45+AC46 -> #DIV/0! | AD48: =AD44+AD45+AD46 -> #DIV/0! | AE48: =AE44+AE45+AE46 -> #DIV/0! | AH48: =AH44+AH45+AH46+AH47 -> 0 | AI48: =AI44+AI45+AI46+AI47 -> 0 | AJ48: =AJ44+AJ45+AJ46+AJ47 -> 0 | AK48: =AK44+AK45+AK46+AK47 -> 0 | AL48: =AL44+AL45+AL46+AL47 -> 0 | AM48: =AM44+AM45+AM46+AM47 -> 0 | AN48: =AN44+AN45+AN46+AN47 -> 0 | AO48: =AO44+AO45+AO46+AO47 -> 0 | ... BY48: =BY44+BY45+BY46+BY47 -> 0 | BZ48: =BZ44+BZ45+BZ46 -> #DIV/0! | CA48: =CA44+CA45+CA46 -> #DIV/0! | CB48: =CB44+CB45+CB46 -> #DIV/0! | CC48: =CC44+CC45+CC46 -> #DIV/0! | CD48: =CD44+CD45+CD46 -> #DIV/0! | CE48: =CE44+CE45+CE46 -> #DIV/0! | CF48: =CF44+CF45+CF46 -> #DIV/0! | CG48: =CG44+CG45+CG46 -> #DIV/0! | ... CO48: =CO44+CO45+CO46 -> #DIV/0!
A49: YOY% | C49: =+IF(B48<0,1-C48/B48,C48/B48-1) -> #DIV/0! | D49: =+IF(C48<0,1-D48/C48,D48/C48-1) -> #DIV/0! | E49: =+IF(D48<0,1-E48/D48,E48/D48-1) -> #DIV/0! | F49: =+IF(E48<0,1-F48/E48,F48/E48-1) -> #DIV/0! | G49: =+IF(F48<0,1-G48/F48,G48/F48-1) -> #DIV/0! | H49: =+IF(G48<0,1-H48/G48,H48/G48-1) -> #DIV/0! | I49: =+IF(H48<0,1-I48/H48,I48/H48-1) -> #DIV/0! | J49: =+IF(I48<0,1-J48/I48,J48/I48-1) -> #DIV/0! | ... AE49: =+IF(AD48<0,1-AE48/AD48,AE48/AD48-1) -> #DIV/0! | AL49: =+IF(AH48<0,1-AL48/AH48,AL48/AH48-1) -> #DIV/0! | AM49: =+IF(AI48<0,1-AM48/AI48,AM48/AI48-1) -> #DIV/0! | AN49: =+IF(AJ48<0,1-AN48/AJ48,AN48/AJ48-1) -> #DIV/0! | AO49: =+IF(AK48<0,1-AO48/AK48,AO48/AK48-1) -> #DIV/0! | AP49: =+IF(AL48<0,1-AP48/AL48,AP48/AL48-1) -> #DIV/0! | AQ49: =+IF(AM48<0,1-AQ48/AM48,AQ48/AM48-1) -> #DIV/0! | AR49: =+IF(AN48<0,1-AR48/AN48,AR48/AN48-1) -> #DIV/0! | AS49: =+IF(AO48<0,1-AS48/AO48,AS48/AO48-1) -> #DIV/0! | ... CO49: =+IF(CK48<0,1-CO48/CK48,CO48/CK48-1) -> #DIV/0!
A50: Profit & Loss- Annual (End)
A51: ACE | B51: =+'Annual Raw'!C45 -> 0 | C51: =+'Annual Raw'!D45 -> 0 | D51: =+'Annual Raw'!E45 -> 0 | E51: =+'Annual Raw'!F45 -> 0 | F51: =+'Annual Raw'!G45 -> 0 | G51: =+'Annual Raw'!H45 -> 0 | H51: =+'Annual Raw'!I45 -> 0 | I51: =+'Annual Raw'!J45 -> 0 | ... Z51: =+'Annual Raw'!AA45 -> 0 | AH51: =+'QTR Raw'!D45 -> 0 | AI51: =+'QTR Raw'!E45 -> 0 | AJ51: =+'QTR Raw'!F45 -> 0 | AK51: =+'QTR Raw'!G45 -> 0 | AL51: =+'QTR Raw'!H45 -> 0 | AM51: =+'QTR Raw'!I45 -> 0 | AN51: =+'QTR Raw'!J45 -> 0 | AO51: =+'QTR Raw'!K45 -> 0 | ... BY51: =+'QTR Raw'!AU45 -> 0
A52: Checksum - PAT | B52: =+B48-B51 -> 0 | C52: =+C48-C51 -> 0 | D52: =+D48-D51 -> 0 | E52: =+E48-E51 -> 0 | F52: =+F48-F51 -> 0 | G52: =+G48-G51 -> 0 | H52: =+H48-H51 -> 0 | I52: =+I48-I51 -> 0 | ... Z52: =+Z48-Z51 -> 0 | AH52: =+AH48-AH51 -> 0 | AI52: =+AI48-AI51 -> 0 | AJ52: =+AJ48-AJ51 -> 0 | AK52: =+AK48-AK51 -> 0 | AL52: =+AL48-AL51 -> 0 | AM52: =+AM48-AM51 -> 0 | AN52: =+AN48-AN51 -> 0 | AO52: =+AO48-AO51 -> 0 | ... BY52: =+BY48-BY51 -> 0
A53: Ratios (Start)
A54: Eq | B54: =+C54 -> 0 | C54: =+D54 -> 0 | D54: =+E54 -> 0 | E54: =+F54 -> 0 | F54: =+G54 -> 0 | G54: =+H54 -> 0 | H54: =+I54 -> 0 | I54: =+J54 -> 0 | ... Z54: =+AA54 -> 0 | AA54: =+BY54 -> 0 | AB54: =+CC54 -> 0 | AC54: =+CG54 -> 0 | AD54: =+CK54 -> 0 | AE54: =+CO54 -> 0 | AH54: =+AI54 -> 0 | AI54: =+AJ54 -> 0 | AJ54: =+AK54 -> 0 | AK54: =+AL54 -> 0 | AL54: =+AM54 -> 0 | AM54: =+AN54 -> 0 | AN54: =+AO54 -> 0 | AO54: =+AP54 -> 0 | ... BV54: =+BW54 -> 0 | BW54: =+'QTR Raw'!AS51 -> 0 | BX54: =+'QTR Raw'!AT51 -> 0 | BY54: =+'QTR Raw'!AU51 -> 0 | BZ54: =BZ95 -> 0 | CA54: =CA95 -> 0 | CB54: =CB95 -> 0 | CC54: =CC95 -> 0 | CD54: =CD95 -> 0 | CE54: =CE95 -> 0 | CF54: =CF95 -> 0 | CG54: =CG95 -> 0 | ... CO54: =CO95 -> 0
A55: FV | B55: =+C55 -> 0 | C55: =+D55 -> 0 | D55: =+E55 -> 0 | E55: =+F55 -> 0 | F55: =+G55 -> 0 | G55: =+H55 -> 0 | H55: =+I55 -> 0 | I55: =+J55 -> 0 | ... Z55: =+AA55 -> 0 | AA55: =+BY55 -> 0 | AB55: =+CC55 -> 0 | AC55: =+CG55 -> 0 | AD55: =+CK55 -> 0 | AE55: =+CO55 -> 0 | AH55: =+AI55 -> 0 | AI55: =+AJ55 -> 0 | AJ55: =+AK55 -> 0 | AK55: =+AL55 -> 0 | AL55: =+AM55 -> 0 | AM55: =+AN55 -> 0 | AN55: =+AO55 -> 0 | AO55: =+AP55 -> 0 | ... BV55: =+BW55 -> 0 | BW55: =+'QTR Raw'!AS52 -> 0 | BX55: =+'QTR Raw'!AT52 -> 0 | BY55: =+'QTR Raw'!AU52 -> 0 | BZ55: =+BY55 -> 0 | CA55: =+BZ55 -> 0 | CB55: =+CA55 -> 0 | CC55: =+CB55 -> 0 | CD55: =+CC55 -> 0 | CE55: =+CD55 -> 0 | CF55: =+CE55 -> 0 | CG55: =+CF55 -> 0 | ... CO55: =+CN55 -> 0
A56: No of share | B56: =B54/B55 -> #DIV/0! | C56: =C54/C55 -> #DIV/0! | D56: =D54/D55 -> #DIV/0! | E56: =E54/E55 -> #DIV/0! | F56: =F54/F55 -> #DIV/0! | G56: =G54/G55 -> #DIV/0! | H56: =H54/H55 -> #DIV/0! | I56: =I54/I55 -> #DIV/0! | ... AE56: =AE54/AE55 -> #DIV/0! | AH56: =AH54/AH55 -> #DIV/0! | AI56: =AI54/AI55 -> #DIV/0! | AJ56: =AJ54/AJ55 -> #DIV/0! | AK56: =AK54/AK55 -> #DIV/0! | AL56: =AL54/AL55 -> #DIV/0! | AM56: =AM54/AM55 -> #DIV/0! | AN56: =AN54/AN55 -> #DIV/0! | AO56: =AO54/AO55 -> #DIV/0! | ... CO56: =CO54/CO55 -> #DIV/0!
A57: EPS | B57: =B48/B56 -> #DIV/0! | C57: =C48/C56 -> #DIV/0! | D57: =D48/D56 -> #DIV/0! | E57: =E48/E56 -> #DIV/0! | F57: =F48/F56 -> #DIV/0! | G57: =G48/G56 -> #DIV/0! | H57: =H48/H56 -> #DIV/0! | I57: =I48/I56 -> #DIV/0! | ... AE57: =AE48/AE56 -> #DIV/0! | AH57: =AH48/AH56 -> #DIV/0! | AI57: =AI48/AI56 -> #DIV/0! | AJ57: =AJ48/AJ56 -> #DIV/0! | AK57: =AK48/AK56 -> #DIV/0! | AL57: =AL48/AL56 -> #DIV/0! | AM57: =AM48/AM56 -> #DIV/0! | AN57: =AN48/AN56 -> #DIV/0! | AO57: =AO48/AO56 -> #DIV/0! | ... CO57: =CO48/CO56 -> #DIV/0!
A58: EPS TTM | B58: =+B57 -> #DIV/0! | C58: =+C57 -> #DIV/0! | D58: =+D57 -> #DIV/0! | E58: =+E57 -> #DIV/0! | F58: =+F57 -> #DIV/0! | G58: =+G57 -> #DIV/0! | H58: =+H57 -> #DIV/0! | I58: =+I57 -> #DIV/0! | ... AE58: =+AE57 -> #DIV/0! | AO58: =AO57+AN57+AM57+AL57 -> #DIV/0! | AP58: =AP57+AO57+AN57+AM57 -> #DIV/0! | AQ58: =AQ57+AP57+AO57+AN57 -> #DIV/0! | AR58: =AR57+AQ57+AP57+AO57 -> #DIV/0! | AS58: =AS57+AR57+AQ57+AP57 -> #DIV/0! | AT58: =AT57+AS57+AR57+AQ57 -> #DIV/0! | AU58: =AU57+AT57+AS57+AR57 -> #DIV/0! | AV58: =AV57+AU57+AT57+AS57 -> #DIV/0! | ... CO58: =CO57+CN57+CM57+CL57 -> #DIV/0!
A59: Bloomberg Estimate
A60: Estimate Deviation | CC60: =+CC58/CC59-1 -> #DIV/0! | CG60: =+CG58/CG59-1 -> #DIV/0! | CK60: =+CK58/CK59-1 -> #DIV/0! | CO60: =+CO58/CO59-1 -> #DIV/0!
A61: BVPS | B61: =B97/B56 -> #DIV/0! | C61: =C97/C56 -> #DIV/0! | D61: =D97/D56 -> #DIV/0! | E61: =E97/E56 -> #DIV/0! | F61: =F97/F56 -> #DIV/0! | G61: =G97/G56 -> #DIV/0! | H61: =H97/H56 -> #DIV/0! | I61: =I97/I56 -> #DIV/0! | ... AE61: =AE97/AE56 -> #DIV/0! | AH61: =AH97/AH56 -> #DIV/0! | AI61: =AI97/AI56 -> #DIV/0! | AJ61: =AJ97/AJ56 -> #DIV/0! | AK61: =AK97/AK56 -> #DIV/0! | AL61: =AL97/AL56 -> #DIV/0! | AM61: =AM97/AM56 -> #DIV/0! | AN61: =AN97/AN56 -> #DIV/0! | AO61: =AO97/AO56 -> #DIV/0! | ... CO61: =CO97/CO56 -> #DIV/0!
A62: ABVPS | C62: =+C61-C66 -> #DIV/0! | D62: =+D61-D66 -> #DIV/0! | E62: =+E61-E66 -> #DIV/0! | F62: =+F61-F66 -> #DIV/0! | G62: =+G61-G66 -> #DIV/0! | H62: =+H61-H66 -> #DIV/0! | I62: =+I61-I66 -> #DIV/0! | J62: =+J61-J66 -> #DIV/0! | ... AE62: =+AE61-AE66 -> #DIV/0! | AH62: =+AH61-AH66 -> #DIV/0! | AI62: =+AI61-AI66 -> #DIV/0! | AJ62: =+AJ61-AJ66 -> #DIV/0! | AK62: =+AK61-AK66 -> #DIV/0! | AL62: =+AL61-AL66 -> #DIV/0! | AM62: =+AM61-AM66 -> #DIV/0! | AN62: =+AN61-AN66 -> #DIV/0! | AO62: =+AO61-AO66 -> #DIV/0! | ... CO62: =+CO61-CO66 -> #DIV/0!
A64: GNPA | B64: =+'Annual Raw'!C151 -> 0 | C64: =+'Annual Raw'!D151 -> 0 | D64: =+'Annual Raw'!E151 -> 0 | E64: =+'Annual Raw'!F151 -> 0 | F64: =+'Annual Raw'!G151 -> 0 | G64: =+'Annual Raw'!H151 -> 0 | H64: =+'Annual Raw'!I151 -> 0 | I64: =+'Annual Raw'!J151 -> 0 | ... Z64: =+'Annual Raw'!AA151 -> 0 | AW64: =+AW68*AW109 -> 0 | AX64: =+AX68*AX109 -> 0 | AY64: =+AY68*AY109 -> 0 | AZ64: =+AZ68*AZ109 -> 0 | BA64: =+BA68*BA109 -> 0 | BB64: =+BB68*BB109 -> 0 | BC64: =+BC68*BC109 -> 0 | BD64: =+BD68*BD109 -> 0 | ... BY64: =+BY68*BY109 -> 0
A65: NNPA | B65: =+'Annual Raw'!C152 -> 0 | C65: =+'Annual Raw'!D152 -> 0 | D65: =+'Annual Raw'!E152 -> 0 | E65: =+'Annual Raw'!F152 -> 0 | F65: =+'Annual Raw'!G152 -> 0 | G65: =+'Annual Raw'!H152 -> 0 | H65: =+'Annual Raw'!I152 -> 0 | I65: =+'Annual Raw'!J152 -> 0 | ... Z65: =+'Annual Raw'!AA152 -> 0 | AW65: =+AW69*AW109 -> 0 | AX65: =+AX69*AX109 -> 0 | AY65: =+AY69*AY109 -> 0 | AZ65: =+AZ69*AZ109 -> 0 | BA65: =+BA69*BA109 -> 0 | BB65: =+BB69*BB109 -> 0 | BC65: =+BC69*BC109 -> 0 | BD65: =+BD69*BD109 -> 0 | ... CO65: =+CO69*CO109 -> #DIV/0!
A66: NNPA Per Share | C66: =+C65/C56 -> #DIV/0! | D66: =+D65/D56 -> #DIV/0! | E66: =+E65/E56 -> #DIV/0! | F66: =+F65/F56 -> #DIV/0! | G66: =+G65/G56 -> #DIV/0! | H66: =+H65/H56 -> #DIV/0! | I66: =+I65/I56 -> #DIV/0! | J66: =+J65/J56 -> #DIV/0! | ... Z66: =+Z65/Z56 -> #DIV/0! | AW66: =+AW65/AW56 -> #DIV/0! | AX66: =+AX65/AX56 -> #DIV/0! | AY66: =+AY65/AY56 -> #DIV/0! | AZ66: =+AZ65/AZ56 -> #DIV/0! | BA66: =+BA65/BA56 -> #DIV/0! | BB66: =+BB65/BB56 -> #DIV/0! | BC66: =+BC65/BC56 -> #DIV/0! | BD66: =+BD65/BD56 -> #DIV/0! | ... CO66: =+CO65/CO56 -> #DIV/0!
A68: GNPA %(taken from quarterly results) | B68: =+B64/B109 -> #DIV/0! | C68: =+C64/C109 -> #DIV/0! | D68: =+D64/D109 -> #DIV/0! | E68: =+E64/E109 -> #DIV/0! | F68: =+F64/F109 -> #DIV/0! | G68: =+G64/G109 -> #DIV/0! | H68: =+H64/H109 -> #DIV/0! | I68: =+I64/I109 -> #DIV/0! | ... Z68: =+Z64/Z109 -> #DIV/0!
A69: NNPA %(taken from quarterly results) | B69: =+B65/B109 -> #DIV/0! | C69: =+C65/C109 -> #DIV/0! | D69: =+D65/D109 -> #DIV/0! | E69: =+E65/E109 -> #DIV/0! | F69: =+F65/F109 -> #DIV/0! | G69: =+G65/G109 -> #DIV/0! | H69: =+H65/H109 -> #DIV/0! | I69: =+I65/I109 -> #DIV/0! | ... Z69: =+Z65/Z109 -> #DIV/0! | BZ69: =+BY69 -> 0 | CA69: =+BZ69 -> 0 | CB69: =+CA69 -> 0 | CC69: =+CB69 -> 0 | CD69: =+CC69 -> 0 | CE69: =+CD69 -> 0 | CF69: =+CE69 -> 0 | CG69: =+CF69 -> 0 | ... CO69: =+CN69 -> 0
A72: NIIM % | D72: =+D29/D74 -> #DIV/0! | E72: =+E29/E74 -> #DIV/0! | F72: =+F29/F74 -> #DIV/0! | G72: =+G29/G74 -> #DIV/0! | H72: =+H29/H74 -> #DIV/0! | I72: =+I29/I74 -> #DIV/0! | J72: =+J29/J74 -> #DIV/0! | K72: =+K29/K74 -> #DIV/0! | ... Z72: =+Z29/Z74 -> #DIV/0! | AI72: =+AI29/AI74*4 -> #DIV/0! | AJ72: =+AJ29/AJ74*4 -> #DIV/0! | AK72: =+AK29/AK74*4 -> #DIV/0! | AL72: =+AL29/AL74*4 -> #DIV/0! | AM72: =+AM29/AM74*4 -> #DIV/0! | AN72: =+AN29/AN74*4 -> #DIV/0! | AO72: =+AO29/AO74*4 -> #DIV/0! | AP72: =+AP29/AP74*4 -> #DIV/0! | ... CO72: =+CO29/CO74*4 -> #DIV/0!
A73: Earning Asset | B73: =+B113+B109 -> 0 | C73: =+C113+C109 -> 0 | D73: =+D113+D109 -> 0 | E73: =+E113+E109 -> 0 | F73: =+F113+F109 -> 0 | G73: =+G113+G109 -> 0 | H73: =+H113+H109 -> 0 | I73: =+I113+I109 -> 0 | ... Z73: =+Z113+Z109 -> 0 | AI73: =+AI113+AI109 -> 0 | AJ73: =+AJ113+AJ109 -> 0 | AK73: =+AK113+AK109 -> 0 | AL73: =+AL113+AL109 -> 0 | AM73: =+AM113+AM109 -> 0 | AN73: =+AN113+AN109 -> 0 | AO73: =+AO113+AO109 -> 0 | AP73: =+AP113+AP109 -> 0 | ... CO73: =+CO113+CO109 -> #DIV/0!
A74: Average Earning Asset | D74: =+AVERAGE(C73:D73) -> 0 | E74: =+AVERAGE(D73:E73) -> 0 | F74: =+AVERAGE(E73:F73) -> 0 | G74: =+AVERAGE(F73:G73) -> 0 | H74: =+AVERAGE(G73:H73) -> 0 | I74: =+AVERAGE(H73:I73) -> 0 | J74: =+AVERAGE(I73:J73) -> 0 | K74: =+AVERAGE(J73:K73) -> 0 | ... Z74: =+AVERAGE(Y73:Z73) -> 0 | AI74: =+AVERAGE(AH73:AI73) -> 0 | AJ74: =+AVERAGE(AI73:AJ73) -> 0 | AK74: =+AVERAGE(AJ73:AK73) -> 0 | AL74: =+AVERAGE(AK73:AL73) -> 0 | AM74: =+AVERAGE(AL73:AM73) -> 0 | AN74: =+AVERAGE(AM73:AN73) -> 0 | AO74: =+AVERAGE(AN73:AO73) -> 0 | AP74: =+AVERAGE(AO73:AP73) -> 0 | ... CO74: =+AVERAGE(CN73:CO73) -> #DIV/0!
A75: ROE % | D75: =D48/D97 -> #DIV/0! | E75: =E48/E97 -> #DIV/0! | F75: =F48/F97 -> #DIV/0! | G75: =G48/G97 -> #DIV/0! | H75: =H48/H97 -> #DIV/0! | I75: =I48/I97 -> #DIV/0! | J75: =J48/J97 -> #DIV/0! | K75: =K48/K97 -> #DIV/0! | ... AE75: =AE48/AE97 -> #DIV/0!
A77: Ratios (End)
A78: Valuation (Start)
A80: Share Price
A81: Share Price - Close | B81: =+'Annual Raw'!C59 -> 0 | C81: =+'Annual Raw'!D59 -> 0 | D81: =+'Annual Raw'!E59 -> 0 | E81: =+'Annual Raw'!F59 -> 0 | F81: =+'Annual Raw'!G59 -> 0 | G81: =+'Annual Raw'!H59 -> 0 | H81: =+'Annual Raw'!I59 -> 0 | I81: =+'Annual Raw'!J59 -> 0 | ... Z81: =+'Annual Raw'!AA59 -> 0 | AA81: =+BY81 -> 0 | AB81: =+CC81 -> 0 | AC81: =+CG81 -> 0 | AD81: =+CK81 -> 0 | AE81: =+CO81 -> 0 | AH81: =+'QTR Share Price'!IA21 -> 0 | AI81: =+'QTR Share Price'!IB21 -> 0 | AJ81: =+'QTR Share Price'!IC21 -> 0 | AK81: =+'QTR Share Price'!ID21 -> 0 | AL81: =+'QTR Share Price'!IE21 -> 0 | AM81: =+'QTR Share Price'!IF21 -> 0 | AN81: =+'QTR Share Price'!IG21 -> 0 | AO81: =+'QTR Share Price'!IH21 -> 0 | ... BY81: =+'QTR Share Price'!JR21 -> 0 | BZ81: =+BY81 -> 0 | CA81: =+BZ81 -> 0 | CB81: =+CA81 -> 0 | CC81: =+CB81 -> 0 | CD81: =+CC81 -> 0 | CE81: =+CD81 -> 0 | CF81: =+CE81 -> 0 | CG81: =+CF81 -> 0 | ... CO81: =+CN81 -> 0
A82: Share Price - High | B82: =+'Annual Raw'!C60 -> 0 | C82: =+'Annual Raw'!D60 -> 0 | D82: =+'Annual Raw'!E60 -> 0 | E82: =+'Annual Raw'!F60 -> 0 | F82: =+'Annual Raw'!G60 -> 0 | G82: =+'Annual Raw'!H60 -> 0 | H82: =+'Annual Raw'!I60 -> 0 | I82: =+'Annual Raw'!J60 -> 0 | ... Z82: =+'Annual Raw'!AA60 -> 0 | AA82: =+MAX(BV82:BY82) -> 0 | AB82: =+MAX(BZ82:CC82) -> #DIV/0! | AC82: =+MAX(CD82:CG82) -> #DIV/0! | AD82: =+MAX(CH82:CK82) -> #DIV/0! | AE82: =+MAX(CL82:CO82) -> #DIV/0! | AH82: =+'QTR Share Price'!IA19 -> 0 | AI82: =+'QTR Share Price'!IB19 -> 0 | AJ82: =+'QTR Share Price'!IC19 -> 0 | AK82: =+'QTR Share Price'!ID19 -> 0 | AL82: =+'QTR Share Price'!IE19 -> 0 | AM82: =+'QTR Share Price'!IF19 -> 0 | AN82: =+'QTR Share Price'!IG19 -> 0 | AO82: =+'QTR Share Price'!IH19 -> 0 | ... BY82: =+'QTR Share Price'!JR19 -> 0 | BZ82: =+BZ90*BZ62 -> #DIV/0! | CA82: =+CA90*CA62 -> #DIV/0! | CB82: =+CB90*CB62 -> #DIV/0! | CC82: =+CC90*CC62 -> #DIV/0! | CD82: =+CD90*CD62 -> #DIV/0! | CE82: =+CE90*CE62 -> #DIV/0! | CF82: =+CF90*CF62 -> #DIV/0! | CG82: =+CG90*CG62 -> #DIV/0! | ... CO82: =+CO90*CO62 -> #DIV/0!
A83: Share Price - Low | B83: =+'Annual Raw'!C61 -> 0 | C83: =+'Annual Raw'!D61 -> 0 | D83: =+'Annual Raw'!E61 -> 0 | E83: =+'Annual Raw'!F61 -> 0 | F83: =+'Annual Raw'!G61 -> 0 | G83: =+'Annual Raw'!H61 -> 0 | H83: =+'Annual Raw'!I61 -> 0 | I83: =+'Annual Raw'!J61 -> 0 | ... Z83: =+'Annual Raw'!AA61 -> 0 | AA83: =+MIN(BV83:BY83) -> 0 | AB83: =+MIN(BZ83:CC83) -> #DIV/0! | AC83: =+MIN(CD83:CG83) -> #DIV/0! | AD83: =+MIN(CH83:CK83) -> #DIV/0! | AE83: =+MIN(CL83:CO83) -> #DIV/0! | AH83: =+'QTR Share Price'!IA20 -> 0 | AI83: =+'QTR Share Price'!IB20 -> 0 | AJ83: =+'QTR Share Price'!IC20 -> 0 | AK83: =+'QTR Share Price'!ID20 -> 0 | AL83: =+'QTR Share Price'!IE20 -> 0 | AM83: =+'QTR Share Price'!IF20 -> 0 | AN83: =+'QTR Share Price'!IG20 -> 0 | AO83: =+'QTR Share Price'!IH20 -> 0 | ... BY83: =+'QTR Share Price'!JR20 -> 0 | BZ83: =+BZ91*BZ62 -> #DIV/0! | CA83: =+CA91*CA62 -> #DIV/0! | CB83: =+CB91*CB62 -> #DIV/0! | CC83: =+CC91*CC62 -> #DIV/0! | CD83: =+CD91*CD62 -> #DIV/0! | CE83: =+CE91*CE62 -> #DIV/0! | CF83: =+CF91*CF62 -> #DIV/0! | CG83: =+CG91*CG62 -> #DIV/0! | ... CO83: =+CO91*CO62 -> #DIV/0!
A85: Upside (%) | BZ85: =+BZ82/BZ81-1 -> #DIV/0! | CA85: =+CA82/CA81-1 -> #DIV/0! | CB85: =+CB82/CB81-1 -> #DIV/0! | CC85: =+CC82/CC81-1 -> #DIV/0! | CD85: =+CD82/CD81-1 -> #DIV/0! | CE85: =+CE82/CE81-1 -> #DIV/0! | CF85: =+CF82/CF81-1 -> #DIV/0! | CG85: =+CG82/CG81-1 -> #DIV/0! | ... CO85: =+CO82/CO81-1 -> #DIV/0!
A86: Downside (%) | BZ86: =+BZ83/BZ81-1 -> #DIV/0! | CA86: =+CA83/CA81-1 -> #DIV/0! | CB86: =+CB83/CB81-1 -> #DIV/0! | CC86: =+CC83/CC81-1 -> #DIV/0! | CD86: =+CD83/CD81-1 -> #DIV/0! | CE86: =+CE83/CE81-1 -> #DIV/0! | CF86: =+CF83/CF81-1 -> #DIV/0! | CG86: =+CG83/CG81-1 -> #DIV/0! | ... CO86: =+CO83/CO81-1 -> #DIV/0!
A88: P/ABVPS
A89: P/ABVPS - Close | B89: =+B81/B62 -> #DIV/0! | C89: =+C81/C62 -> #DIV/0! | D89: =+D81/D62 -> #DIV/0! | E89: =+E81/E62 -> #DIV/0! | F89: =+F81/F62 -> #DIV/0! | G89: =+G81/G62 -> #DIV/0! | H89: =+H81/H62 -> #DIV/0! | I89: =+I81/I62 -> #DIV/0! | ... AE89: =+AE81/AE62 -> #DIV/0! | AH89: =+AH81/AH62 -> #DIV/0! | AI89: =+AI81/AI62 -> #DIV/0! | AJ89: =+AJ81/AJ62 -> #DIV/0! | AK89: =+AK81/AK62 -> #DIV/0! | AL89: =+AL81/AL62 -> #DIV/0! | AM89: =+AM81/AM62 -> #DIV/0! | AN89: =+AN81/AN62 -> #DIV/0! | AO89: =+AO81/AO62 -> #DIV/0! | ... CO89: =+CO81/CO62 -> #DIV/0!
A90: P/ABVPS - High | B90: =B82/B57 -> #DIV/0! | C90: =C82/C57 -> #DIV/0! | D90: =D82/D62 -> #DIV/0! | E90: =E82/E62 -> #DIV/0! | F90: =F82/F62 -> #DIV/0! | G90: =G82/G62 -> #DIV/0! | H90: =H82/H62 -> #DIV/0! | I90: =I82/I62 -> #DIV/0! | J90: =J82/J62 -> #DIV/0! | K90: =K82/K62 -> #DIV/0! | ... AE90: =AE82/AE62 -> #DIV/0! | AH90: =AH82/AH62 -> #DIV/0! | AI90: =AI82/AI62 -> #DIV/0! | AJ90: =AJ82/AJ62 -> #DIV/0! | AK90: =AK82/AK62 -> #DIV/0! | AL90: =AL82/AL62 -> #DIV/0! | AM90: =AM82/AM62 -> #DIV/0! | AN90: =AN82/AN62 -> #DIV/0! | AO90: =AO82/AO62 -> #DIV/0! | ... BY90: =BY82/BY62 -> #DIV/0! | BZ90: =BY90 -> #DIV/0! | CA90: =BZ90 -> #DIV/0! | CB90: =CA90 -> #DIV/0! | CC90: =CB90 -> #DIV/0! | CD90: =CC90 -> #DIV/0! | CE90: =CD90 -> #DIV/0! | CF90: =CE90 -> #DIV/0! | CG90: =CF90 -> #DIV/0! | ... CO90: =CN90 -> #DIV/0!
A91: P/ABVPS - Low | B91: =B83/B57 -> #DIV/0! | C91: =C83/C57 -> #DIV/0! | D91: =D83/D62 -> #DIV/0! | E91: =E83/E62 -> #DIV/0! | F91: =F83/F62 -> #DIV/0! | G91: =G83/G62 -> #DIV/0! | H91: =H83/H62 -> #DIV/0! | I91: =I83/I62 -> #DIV/0! | J91: =J83/J62 -> #DIV/0! | K91: =K83/K62 -> #DIV/0! | ... AE91: =AE83/AE62 -> #DIV/0! | AH91: =AH83/AH62 -> #DIV/0! | AI91: =AI83/AI62 -> #DIV/0! | AJ91: =AJ83/AJ62 -> #DIV/0! | AK91: =AK83/AK62 -> #DIV/0! | AL91: =AL83/AL62 -> #DIV/0! | AM91: =AM83/AM62 -> #DIV/0! | AN91: =AN83/AN62 -> #DIV/0! | AO91: =AO83/AO62 -> #DIV/0! | ... BY91: =BY83/BY62 -> #DIV/0! | BZ91: =BY91 -> #DIV/0! | CA91: =BZ91 -> #DIV/0! | CB91: =CA91 -> #DIV/0! | CC91: =CB91 -> #DIV/0! | CD91: =CC91 -> #DIV/0! | CE91: =CD91 -> #DIV/0! | CF91: =CE91 -> #DIV/0! | CG91: =CF91 -> #DIV/0! | ... CO91: =CN91 -> #DIV/0!
A93: Valuation (End)
A94: Balance Sheet (Start)
A95: Share Capital | B95: =+'Annual Raw'!C77 -> 0 | C95: =+'Annual Raw'!D77 -> 0 | D95: =+'Annual Raw'!E77 -> 0 | E95: =+'Annual Raw'!F77 -> 0 | F95: =+'Annual Raw'!G77 -> 0 | G95: =+'Annual Raw'!H77 -> 0 | H95: =+'Annual Raw'!I77 -> 0 | I95: =+'Annual Raw'!J77 -> 0 | ... Z95: =+'Annual Raw'!AA77 -> 0 | AA95: =+BY95 -> 0 | AB95: =+CC95 -> 0 | AC95: =+CG95 -> 0 | AD95: =+CK95 -> 0 | AE95: =+CO95 -> 0 | AH95: =+'QTR Raw'!D55 -> 0 | AI95: =+'QTR Raw'!E55 -> 0 | AJ95: =AI95 -> 0 | AK95: =+'QTR Raw'!G55 -> 0 | AL95: =AK95 -> 0 | AM95: =+'QTR Raw'!I55 -> 0 | AN95: =AM95 -> 0 | AO95: =+'QTR Raw'!K55 -> 0 | AP95: =AO95 -> 0 | AQ95: =+'QTR Raw'!M55 -> 0 | AR95: =AQ95 -> 0 | AS95: =+'QTR Raw'!O55 -> 0 | AT95: =AS95 -> 0 | AU95: =+'QTR Raw'!Q55 -> 0 | AV95: =AU95 -> 0 | AW95: =+'QTR Raw'!S55 -> 0 | AX95: =AW95 -> 0 | AY95: =+'QTR Raw'!U55 -> 0 | AZ95: =AY95 -> 0 | BA95: =+'QTR Raw'!W55 -> 0 | BB95: =BA95 -> 0 | BC95: =+'QTR Raw'!Y55 -> 0 | BD95: =BC95 -> 0 | BE95: =+'QTR Raw'!AA55 -> 0 | BF95: =BE95 -> 0 | BG95: =+'QTR Raw'!AC55 -> 0 | BH95: =BG95 -> 0 | BI95: =+'QTR Raw'!AE55 -> 0 | BJ95: =BI95 -> 0 | BK95: =+'QTR Raw'!AG55 -> 0 | BL95: =BK95 -> 0 | BM95: =+'QTR Raw'!AI55 -> 0 | BN95: =BM95 -> 0 | BO95: =+'QTR Raw'!AK55 -> 0 | BP95: =BO95 -> 0 | BQ95: =+'QTR Raw'!AM55 -> 0 | BR95: =BQ95 -> 0 | BS95: =+'QTR Raw'!AO55 -> 0 | BT95: =BS95 -> 0 | BU95: =+'QTR Raw'!AQ55 -> 0 | BV95: =BU95 -> 0 | BW95: =+'QTR Raw'!AS55 -> 0 | BX95: =BW95 -> 0 | BY95: =+'QTR Raw'!AU55 -> 0 | BZ95: =BY95 -> 0 | CA95: =BZ95 -> 0 | CB95: =CA95 -> 0 | CC95: =CB95 -> 0 | CD95: =CC95 -> 0 | CE95: =CD95 -> 0 | CF95: =CE95 -> 0 | CG95: =CF95 -> 0 | ... CO95: =CN95 -> 0
A96: Total Reserves | B96: =+'Annual Raw'!C79++'Annual Raw'!C78 -> 0 | C96: =+'Annual Raw'!D79++'Annual Raw'!D78 -> 0 | D96: =+'Annual Raw'!E79++'Annual Raw'!E78 -> 0 | E96: =+'Annual Raw'!F79++'Annual Raw'!F78 -> 0 | F96: =+'Annual Raw'!G79++'Annual Raw'!G78 -> 0 | G96: =+'Annual Raw'!H79++'Annual Raw'!H78 -> 0 | H96: =+'Annual Raw'!I79++'Annual Raw'!I78 -> 0 | I96: =+'Annual Raw'!J79++'Annual Raw'!J78 -> 0 | ... Z96: =+'Annual Raw'!AA79++'Annual Raw'!AA78 -> 0 | AA96: =+BY96 -> 0 | AB96: =+CC96 -> #DIV/0! | AC96: =+CG96 -> #DIV/0! | AD96: =+CK96 -> #DIV/0! | AE96: =+CO96 -> #DIV/0! | AH96: =+'QTR Raw'!D57 -> 0 | AI96: =+'QTR Raw'!E57 -> 0 | AJ96: =AI96+AJ48 -> 0 | AK96: =+'QTR Raw'!G57 -> 0 | AL96: =AK96+AL48 -> 0 | AM96: =+'QTR Raw'!I57 -> 0 | AN96: =AM96+AN48 -> 0 | AO96: =+'QTR Raw'!K57 -> 0 | AP96: =AO96+AP48 -> 0 | AQ96: =+'QTR Raw'!M57 -> 0 | AR96: =AQ96+AR48 -> 0 | AS96: =+'QTR Raw'!O57 -> 0 | AT96: =AS96+AT48 -> 0 | AU96: =+'QTR Raw'!Q57 -> 0 | AV96: =AU96+AV48 -> 0 | AW96: =+'QTR Raw'!S57 -> 0 | AX96: =AW96+AX48 -> 0 | AY96: =+'QTR Raw'!U57 -> 0 | AZ96: =AY96+AZ48 -> 0 | BA96: =+'QTR Raw'!W57 -> 0 | BB96: =BA96+BB48 -> 0 | BC96: =+'QTR Raw'!Y57 -> 0 | BD96: =BC96+BD48 -> 0 | BE96: =+'QTR Raw'!AA57 -> 0 | BF96: =BE96+BF48 -> 0 | BG96: =+'QTR Raw'!AC57 -> 0 | BH96: =BG96+BH48 -> 0 | BI96: =+'QTR Raw'!AE57 -> 0 | BJ96: =BI96+BJ48 -> 0 | BK96: =+'QTR Raw'!AG57 -> 0 | BL96: =BK96+BL48 -> 0 | BM96: =+'QTR Raw'!AI57 -> 0 | BN96: =BM96+BN48 -> 0 | BO96: =+'QTR Raw'!AK57 -> 0 | BP96: =BO96+BP48 -> 0 | BQ96: =+'QTR Raw'!AM57 -> 0 | BR96: =BQ96+BR48 -> 0 | BS96: =+'QTR Raw'!AO57 -> 0 | BT96: =BS96+BT48 -> 0 | BU96: =+'QTR Raw'!AQ57 -> 0 | BV96: =BU96+BV48 -> 0 | BW96: =+'QTR Raw'!AS57 -> 0 | BX96: =BW96+BX48 -> 0 | BY96: =+'QTR Raw'!AU57 -> 0 | BZ96: =BY96+BZ48 -> #DIV/0! | CA96: =BZ96+CA48 -> #DIV/0! | CB96: =CA96+CB48 -> #DIV/0! | CC96: =CB96+CC48 -> #DIV/0! | CD96: =CC96+CD48 -> #DIV/0! | CE96: =CD96+CE48 -> #DIV/0! | CF96: =CE96+CF48 -> #DIV/0! | CG96: =CF96+CG48 -> #DIV/0! | ... CO96: =CN96+CO48 -> #DIV/0!
A97: Shareholder's Funds | B97: =SUM(B95:B96) -> 0 | C97: =SUM(C95:C96) -> 0 | D97: =SUM(D95:D96) -> 0 | E97: =SUM(E95:E96) -> 0 | F97: =SUM(F95:F96) -> 0 | G97: =SUM(G95:G96) -> 0 | H97: =SUM(H95:H96) -> 0 | I97: =SUM(I95:I96) -> 0 | ... AE97: =SUM(AE95:AE96) -> #DIV/0! | AH97: =SUM(AH95:AH96) -> 0 | AI97: =SUM(AI95:AI96) -> 0 | AJ97: =SUM(AJ95:AJ96) -> 0 | AK97: =SUM(AK95:AK96) -> 0 | AL97: =SUM(AL95:AL96) -> 0 | AM97: =SUM(AM95:AM96) -> 0 | AN97: =SUM(AN95:AN96) -> 0 | AO97: =SUM(AO95:AO96) -> 0 | ... CO97: =SUM(CO95:CO96) -> #DIV/0!
A99: Minority Interest | B99: =+'Annual Raw'!C81 -> 0 | C99: =+'Annual Raw'!D81 -> 0 | D99: =+'Annual Raw'!E81 -> 0 | E99: =+'Annual Raw'!F81 -> 0 | F99: =+'Annual Raw'!G81 -> 0 | G99: =+'Annual Raw'!H81 -> 0 | H99: =+'Annual Raw'!I81 -> 0 | I99: =+'Annual Raw'!J81 -> 0 | ... Z99: =+'Annual Raw'!AA81 -> 0 | AA99: =+BY99 -> 0 | AB99: =+CC99 -> 0 | AC99: =+CG99 -> 0 | AD99: =+CK99 -> 0 | AE99: =+CO99 -> 0 | AH99: =+'QTR Raw'!D59 -> 0 | AI99: =+'QTR Raw'!E59 -> 0 | AJ99: =AI99 -> 0 | AK99: =+'QTR Raw'!G59 -> 0 | AL99: =AK99 -> 0 | AM99: =+'QTR Raw'!I59 -> 0 | AN99: =AM99 -> 0 | AO99: =+'QTR Raw'!K59 -> 0 | AP99: =AO99 -> 0 | AQ99: =+'QTR Raw'!M59 -> 0 | AR99: =AQ99 -> 0 | AS99: =+'QTR Raw'!O59 -> 0 | AT99: =AS99 -> 0 | AU99: =+'QTR Raw'!Q59 -> 0 | AV99: =AU99 -> 0 | AW99: =+'QTR Raw'!S59 -> 0 | AX99: =AW99 -> 0 | AY99: =+'QTR Raw'!U59 -> 0 | AZ99: =AY99 -> 0 | BA99: =+'QTR Raw'!W59 -> 0 | BB99: =BA99 -> 0 | BC99: =+'QTR Raw'!Y59 -> 0 | BD99: =BC99 -> 0 | BE99: =+'QTR Raw'!AA59 -> 0 | BF99: =BE99 -> 0 | BG99: =+'QTR Raw'!AC59 -> 0 | BH99: =BG99 -> 0 | BI99: =+'QTR Raw'!AE59 -> 0 | BJ99: =BI99 -> 0 | BK99: =+'QTR Raw'!AG59 -> 0 | BL99: =BK99 -> 0 | BM99: =+'QTR Raw'!AI59 -> 0 | BN99: =BM99 -> 0 | BO99: =+'QTR Raw'!AK59 -> 0 | BP99: =BO99 -> 0 | BQ99: =+'QTR Raw'!AM59 -> 0 | BR99: =BQ99 -> 0 | BS99: =+'QTR Raw'!AO59 -> 0 | BT99: =BS99 -> 0 | BU99: =+'QTR Raw'!AQ59 -> 0 | BV99: =BU99 -> 0 | BW99: =+'QTR Raw'!AS59 -> 0 | BX99: =BW99 -> 0 | BY99: =+'QTR Raw'!AU59 -> 0 | BZ99: =BY99 -> 0 | CA99: =BZ99 -> 0 | CB99: =CA99 -> 0 | CC99: =CB99 -> 0 | CD99: =CC99 -> 0 | CE99: =CD99 -> 0 | CF99: =CE99 -> 0 | CG99: =CF99 -> 0 | ... CO99: =CN99 -> 0
A101: Secured Loans | B101: =+'Annual Raw'!C83++'Annual Raw'!C84-B103-B104 -> 0 | C101: =+'Annual Raw'!D83++'Annual Raw'!D84-C103-C104 -> 0 | D101: =+'Annual Raw'!E83++'Annual Raw'!E84-D103-D104 -> 0 | E101: =+'Annual Raw'!F83++'Annual Raw'!F84-E103-E104 -> 0 | F101: =+'Annual Raw'!G83++'Annual Raw'!G84-F103-F104 -> 0 | G101: =+'Annual Raw'!H83++'Annual Raw'!H84-G103-G104 -> 0 | H101: =+'Annual Raw'!I83++'Annual Raw'!I84-H103-H104 -> 0 | I101: =+'Annual Raw'!J83++'Annual Raw'!J84-I103-I104 -> 0 | ... Z101: =+'Annual Raw'!AA83++'Annual Raw'!AA84-Z103-Z104 -> 0 | AA101: =+BY101 -> 0 | AB101: =+CC101 -> 0 | AC101: =+CG101 -> 0 | AD101: =+CK101 -> 0 | AE101: =+CO101 -> 0 | AH101: =+'QTR Raw'!D61 -> 0 | AI101: =+'QTR Raw'!E61++'QTR Raw'!E62 -> 0 | AK101: =+'QTR Raw'!G61++'QTR Raw'!G62 -> 0 | AM101: =+'QTR Raw'!I61++'QTR Raw'!I62 -> 0 | AO101: =+'QTR Raw'!K61++'QTR Raw'!K62 -> 0 | AQ101: =+'QTR Raw'!M61++'QTR Raw'!M62 -> 0 | AS101: =+'QTR Raw'!O61++'QTR Raw'!O62 -> 0 | AU101: =+'QTR Raw'!Q61++'QTR Raw'!Q62 -> 0 | AW101: =+'QTR Raw'!S61++'QTR Raw'!S62 -> 0 | AY101: =+'QTR Raw'!U61++'QTR Raw'!U62 -> 0 | BA101: =+'QTR Raw'!W61++'QTR Raw'!W62 -> 0 | BC101: =+'QTR Raw'!Y61++'QTR Raw'!Y62 -> 0 | BE101: =+'QTR Raw'!AA61++'QTR Raw'!AA62 -> 0 | BG101: =+'QTR Raw'!AC61++'QTR Raw'!AC62 -> 0 | BI101: =+'QTR Raw'!AE61++'QTR Raw'!AE62 -> 0 | BK101: =+'QTR Raw'!AG61++'QTR Raw'!AG62 -> 0 | BM101: =+'QTR Raw'!AI61++'QTR Raw'!AI62 -> 0 | BO101: =+'QTR Raw'!AK61++'QTR Raw'!AK62 -> 0 | BQ101: =+'QTR Raw'!AM61++'QTR Raw'!AM62 -> 0 | BS101: =+'QTR Raw'!AO61++'QTR Raw'!AO62 -> 0 | BU101: =+'QTR Raw'!AQ61++'QTR Raw'!AQ62 -> 0 | BW101: =+'QTR Raw'!AS61++'QTR Raw'!AS62 -> 0 | BY101: =+'QTR Raw'!AU61++'QTR Raw'!AU62 -> 0
A102: Short Term Borrowings | B102: =+'Annual Raw'!C100 -> 0 | C102: =+'Annual Raw'!D100 -> 0 | D102: =+'Annual Raw'!E100 -> 0 | E102: =+'Annual Raw'!F100 -> 0 | F102: =+'Annual Raw'!G100 -> 0 | G102: =+'Annual Raw'!H100 -> 0 | H102: =+'Annual Raw'!I100 -> 0 | I102: =+'Annual Raw'!J100 -> 0 | ... Z102: =+'Annual Raw'!AA100 -> 0 | AA102: =+BY102 -> 0 | AB102: =+CC102 -> #DIV/0! | AC102: =+CG102 -> #DIV/0! | AD102: =+CK102 -> #DIV/0! | AE102: =+CO102 -> #DIV/0! | AH102: =+'QTR Raw'!D87 -> 0 | AI102: =+'QTR Raw'!E87 -> 0 | AJ102: =+AI102 -> 0 | AK102: =+'QTR Raw'!G87 -> 0 | AL102: =+AK102 -> 0 | AM102: =+'QTR Raw'!I87 -> 0 | AN102: =+AM102 -> 0 | AO102: =+'QTR Raw'!K87 -> 0 | AP102: =+AO102 -> 0 | AQ102: =+'QTR Raw'!M87 -> 0 | AR102: =+AQ102 -> 0 | AS102: =+'QTR Raw'!O87 -> 0 | AT102: =+AS102 -> 0 | AU102: =+'QTR Raw'!Q87 -> 0 | AV102: =+AU102 -> 0 | AW102: =+'QTR Raw'!S87 -> 0 | AX102: =+AW102 -> 0 | AY102: =+'QTR Raw'!U87 -> 0 | AZ102: =+AY102 -> 0 | BA102: =+'QTR Raw'!W87 -> 0 | BB102: =+BA102 -> 0 | BC102: =+'QTR Raw'!Y87 -> 0 | BD102: =+BC102 -> 0 | BE102: =+'QTR Raw'!AA87 -> 0 | BF102: =+BE102 -> 0 | BG102: =+'QTR Raw'!AC87 -> 0 | BH102: =+BG102 -> 0 | BI102: =+'QTR Raw'!AE87 -> 0 | BJ102: =+BI102 -> 0 | BK102: =+'QTR Raw'!AG87 -> 0 | BL102: =+BK102 -> 0 | BM102: =+'QTR Raw'!AI87 -> 0 | BN102: =+BN109*BN133 -> #DIV/0! | BO102: =+'QTR Raw'!AK87 -> 0 | BP102: =+BP109*BP133 -> #DIV/0! | BQ102: =+'QTR Raw'!AM87 -> 0 | BR102: =+BR109*BR133 -> #DIV/0! | BS102: =+'QTR Raw'!AO87 -> 0 | BT102: =+BS102 -> 0 | BU102: =+'QTR Raw'!AQ87 -> 0 | BV102: =+BU102 -> 0 | BW102: =+'QTR Raw'!AS87 -> 0 | BX102: =+BW102 -> 0 | BY102: =+'QTR Raw'!AU87 -> 0 | BZ102: =+BZ109*BZ133 -> #DIV/0! | CA102: =+CA109*CA133 -> #DIV/0! | CB102: =+CB109*CB133 -> #DIV/0! | CC102: =+CC109*CC133 -> #DIV/0! | CD102: =+CD109*CD133 -> #DIV/0! | CE102: =+CE109*CE133 -> #DIV/0! | CF102: =+CF109*CF133 -> #DIV/0! | CG102: =+CG109*CG133 -> #DIV/0! | ... CO102: =+CO109*CO133 -> #DIV/0!
A103: Deposits | B103: =+'Annual Raw'!C96 -> 0 | C103: =+'Annual Raw'!D96 -> 0 | D103: =+'Annual Raw'!E96 -> 0 | E103: =+'Annual Raw'!F96 -> 0 | F103: =+'Annual Raw'!G96 -> 0 | G103: =+'Annual Raw'!H96 -> 0 | H103: =+'Annual Raw'!I96 -> 0 | I103: =+'Annual Raw'!J96 -> 0 | ... Z103: =+'Annual Raw'!AA96 -> 0 | AA103: =+BY103 -> 0 | AB103: =+CC103 -> 0 | AC103: =+CG103 -> 0 | AD103: =+CK103 -> 0 | AE103: =+CO103 -> 0 | AH103: =+AG103 -> 0 | AI103: =+'QTR Raw'!E91 -> 0 | AJ103: =+AI103 -> 0 | AK103: =+'QTR Raw'!G91 -> 0 | AL103: =+AK103 -> 0 | AM103: =+'QTR Raw'!I91 -> 0 | AN103: =+AM103 -> 0 | AO103: =+'QTR Raw'!K91 -> 0 | AP103: =+AO103 -> 0 | AQ103: =+'QTR Raw'!M91 -> 0 | AR103: =+AQ103 -> 0 | AS103: =+'QTR Raw'!O91 -> 0 | AT103: =+AS103 -> 0 | AU103: =+'QTR Raw'!Q91 -> 0 | AV103: =+AU103 -> 0 | AW103: =+'QTR Raw'!S91 -> 0 | AX103: =+AW103 -> 0 | AY103: =+'QTR Raw'!U91 -> 0 | AZ103: =+AY103 -> 0 | BA103: =+'QTR Raw'!W91 -> 0 | BB103: =+BA103 -> 0 | BC103: =+'QTR Raw'!Y91 -> 0 | BD103: =+BC103 -> 0 | BE103: =+'QTR Raw'!AA91 -> 0 | BF103: =+BE103 -> 0 | BG103: =+'QTR Raw'!AC91 -> 0 | BH103: =+BG103 -> 0 | BI103: =+'QTR Raw'!AE91 -> 0 | BJ103: =+BI103 -> 0 | BK103: =+'QTR Raw'!AG91 -> 0 | BL103: =+BK103 -> 0 | BM103: =+'QTR Raw'!AI91 -> 0 | BN103: =+BM103 -> 0 | BO103: =+'QTR Raw'!AK91 -> 0 | BP103: =+BO103 -> 0 | BQ103: =+'QTR Raw'!AM91 -> 0 | BR103: =+BQ103 -> 0 | BS103: =+'QTR Raw'!AO91 -> 0 | BT103: =+BS103 -> 0 | BU103: =+'QTR Raw'!AQ91 -> 0 | BV103: =+BU103 -> 0 | BW103: =+'QTR Raw'!AS91 -> 0 | BX103: =+BW103 -> 0 | BY103: =+'QTR Raw'!AU91 -> 0 | BZ103: =+BY103 -> 0 | CA103: =+BZ103 -> 0 | CB103: =+CA103 -> 0 | CC103: =+CB103 -> 0 | CD103: =+CC103 -> 0 | CE103: =+CD103 -> 0 | CF103: =+CE103 -> 0 | CG103: =+CF103 -> 0 | ... CO103: =+CN103 -> 0
A104: Debt Other Than Borrowing | B104: =+'Annual Raw'!C95 -> 0 | C104: =+'Annual Raw'!D95 -> 0 | D104: =+'Annual Raw'!E95 -> 0 | E104: =+'Annual Raw'!F95 -> 0 | F104: =+'Annual Raw'!G95 -> 0 | G104: =+'Annual Raw'!H95 -> 0 | H104: =+'Annual Raw'!I95 -> 0 | I104: =+'Annual Raw'!J95 -> 0 | ... Z104: =+'Annual Raw'!AA95 -> 0 | AA104: =+BY104 -> 0 | AB104: =+CC104 -> 0 | AC104: =+CG104 -> 0 | AD104: =+CK104 -> 0 | AE104: =+CO104 -> 0 | AH104: =+AG104 -> 0 | AI104: =+'QTR Raw'!E90 -> 0 | AJ104: =+AI104 -> 0 | AK104: =+'QTR Raw'!G90 -> 0 | AL104: =+AK104 -> 0 | AM104: =+'QTR Raw'!I90 -> 0 | AN104: =+AM104 -> 0 | AO104: =+'QTR Raw'!K90 -> 0 | AP104: =+AO104 -> 0 | AQ104: =+'QTR Raw'!M90 -> 0 | AR104: =+AQ104 -> 0 | AS104: =+'QTR Raw'!O90 -> 0 | AT104: =+AS104 -> 0 | AU104: =+'QTR Raw'!Q90 -> 0 | AV104: =+AU104 -> 0 | AW104: =+'QTR Raw'!S90 -> 0 | AX104: =+AW104 -> 0 | AY104: =+'QTR Raw'!U90 -> 0 | AZ104: =+AY104 -> 0 | BA104: =+'QTR Raw'!W90 -> 0 | BB104: =+BA104 -> 0 | BC104: =+'QTR Raw'!Y90 -> 0 | BD104: =+BC104 -> 0 | BE104: =+'QTR Raw'!AA90 -> 0 | BF104: =+BE104 -> 0 | BG104: =+'QTR Raw'!AC90 -> 0 | BH104: =+BG104 -> 0 | BI104: =+'QTR Raw'!AE90 -> 0 | BJ104: =+BI104 -> 0 | BK104: =+'QTR Raw'!AG90 -> 0 | BL104: =+BK104 -> 0 | BM104: =+'QTR Raw'!AI90 -> 0 | BN104: =+BM104 -> 0 | BO104: =+'QTR Raw'!AK90 -> 0 | BP104: =+BO104 -> 0 | BQ104: =+'QTR Raw'!AM90 -> 0 | BR104: =+BQ104 -> 0 | BS104: =+'QTR Raw'!AO90 -> 0 | BT104: =+BS104 -> 0 | BU104: =+'QTR Raw'!AQ90 -> 0 | BV104: =+BU104 -> 0 | BW104: =+'QTR Raw'!AS90 -> 0 | BX104: =+BW104 -> 0 | BY104: =+'QTR Raw'!AU90 -> 0 | BZ104: =+BY104 -> 0 | CA104: =+BZ104 -> 0 | CB104: =+CA104 -> 0 | CC104: =+CB104 -> 0 | CD104: =+CC104 -> 0 | CE104: =+CD104 -> 0 | CF104: =+CE104 -> 0 | CG104: =+CF104 -> 0 | ... CO104: =+CN104 -> 0
A105: Debt | B105: =SUM(B101:B104) -> 0 | C105: =SUM(C101:C104) -> 0 | D105: =SUM(D101:D104) -> 0 | E105: =SUM(E101:E104) -> 0 | F105: =SUM(F101:F104) -> 0 | G105: =SUM(G101:G104) -> 0 | H105: =SUM(H101:H104) -> 0 | I105: =SUM(I101:I104) -> 0 | ... AE105: =SUM(AE101:AE104) -> #DIV/0! | AH105: =SUM(AH101:AH104) -> 0 | AI105: =SUM(AI101:AI104) -> 0 | AJ105: =SUM(AJ101:AJ104) -> 0 | AK105: =SUM(AK101:AK104) -> 0 | AL105: =SUM(AL101:AL104) -> 0 | AM105: =SUM(AM101:AM104) -> 0 | AN105: =SUM(AN101:AN104) -> 0 | AO105: =SUM(AO101:AO104) -> 0 | ... CO105: =SUM(CO101:CO104) -> #DIV/0!
A106: Sources of Funds | B106: =B105+B99+B97 -> 0 | C106: =C105+C99+C97 -> 0 | D106: =D105+D99+D97 -> 0 | E106: =E105+E99+E97 -> 0 | F106: =F105+F99+F97 -> 0 | G106: =G105+G99+G97 -> 0 | H106: =H105+H99+H97 -> 0 | I106: =I105+I99+I97 -> 0 | ... AE106: =AE105+AE99+AE97 -> #DIV/0! | AH106: =AH105+AH99+AH97 -> 0 | AI106: =AI105+AI99+AI97 -> 0 | AJ106: =AJ105+AJ99+AJ97 -> 0 | AK106: =AK105+AK99+AK97 -> 0 | AL106: =AL105+AL99+AL97 -> 0 | AM106: =AM105+AM99+AM97 -> 0 | AN106: =AN105+AN99+AN97 -> 0 | AO106: =AO105+AO99+AO97 -> 0 | ... CO106: =CO105+CO99+CO97 -> #DIV/0!
A109: Advances | B109: =+'Annual Raw'!C125+'Annual Raw'!C106++'Annual Raw'!C117 -> 0 | C109: =+'Annual Raw'!D125+'Annual Raw'!D106++'Annual Raw'!D117 -> 0 | D109: =+'Annual Raw'!E125+'Annual Raw'!E106++'Annual Raw'!E117 -> 0 | E109: =+'Annual Raw'!F125+'Annual Raw'!F106++'Annual Raw'!F117 -> 0 | F109: =+'Annual Raw'!G125+'Annual Raw'!G106++'Annual Raw'!G117 -> 0 | G109: =+'Annual Raw'!H125+'Annual Raw'!H106++'Annual Raw'!H117 -> 0 | H109: =+'Annual Raw'!I125+'Annual Raw'!I106++'Annual Raw'!I117 -> 0 | I109: =+'Annual Raw'!J125+'Annual Raw'!J106++'Annual Raw'!J117 -> 0 | ... Z109: =+'Annual Raw'!AA125+'Annual Raw'!AA106++'Annual Raw'!AA117 -> 0 | AA109: =+BY109 -> 0 | AB109: =+CC109 -> #DIV/0! | AC109: =+CG109 -> #DIV/0! | AD109: =+CK109 -> #DIV/0! | AE109: =+CO109 -> #DIV/0! | AH109: =+'QTR Raw'!D84 -> 0 | AI109: =+'QTR Raw'!E84++'QTR Raw'!E77 -> 0 | AJ109: =+AI109 -> 0 | AK109: =+'QTR Raw'!G84++'QTR Raw'!G77 -> 0 | AL109: =+AK109 -> 0 | AM109: =+'QTR Raw'!I84++'QTR Raw'!I77 -> 0 | AN109: =+AM109 -> 0 | AO109: =+'QTR Raw'!K84++'QTR Raw'!K77 -> 0 | AP109: =+AO109 -> 0 | AQ109: =+'QTR Raw'!M84++'QTR Raw'!M77 -> 0 | AR109: =+AQ109 -> 0 | AS109: =+'QTR Raw'!O84++'QTR Raw'!O77 -> 0 | AT109: =+AS109 -> 0 | AU109: =+'QTR Raw'!Q84++'QTR Raw'!Q77 -> 0 | AV109: =+AU109 -> 0 | AW109: =+'QTR Raw'!S84++'QTR Raw'!S77 -> 0 | AX109: =+AW109 -> 0 | AY109: =+'QTR Raw'!U84++'QTR Raw'!U77 -> 0 | AZ109: =+AY109 -> 0 | BA109: =+'QTR Raw'!W84++'QTR Raw'!W77 -> 0 | BB109: =+BA109 -> 0 | BC109: =+'QTR Raw'!Y84++'QTR Raw'!Y77 -> 0 | BD109: =+BC109 -> 0 | BE109: =+'QTR Raw'!AA84++'QTR Raw'!AA77 -> 0 | BF109: =+BE109 -> 0 | BG109: =+'QTR Raw'!AC84++'QTR Raw'!AC77 -> 0 | BH109: =+BG109 -> 0 | BI109: =+'QTR Raw'!AE84++'QTR Raw'!AE77 -> 0 | BJ109: =+BI109 -> 0 | BK109: =+'QTR Raw'!AG84++'QTR Raw'!AG77 -> 0 | BL109: =+BK109 -> 0 | BM109: =+'QTR Raw'!AI84++'QTR Raw'!AI77 -> 0 | BN109: =+BM109 -> 0 | BO109: =+'QTR Raw'!AK84++'QTR Raw'!AK77 -> 0 | BP109: =+BO109 -> 0 | BQ109: =+'QTR Raw'!AM84++'QTR Raw'!AM77 -> 0 | BR109: =+BQ109 -> 0 | BS109: =+'QTR Raw'!AO84++'QTR Raw'!AO77 -> 0 | BT109: =+BS109 -> 0 | BU109: =+'QTR Raw'!AQ84++'QTR Raw'!AQ77 -> 0 | BV109: =+BU109 -> 0 | BW109: =+'QTR Raw'!AS84++'QTR Raw'!AS77 -> 0 | BX109: =+BW109 -> 0 | BY109: =+'QTR Raw'!AU84++'QTR Raw'!AU77 -> 0 | BZ109: =+BV109*(1+BZ131) -> #DIV/0! | CA109: =+BW109*(1+CA131) -> #DIV/0! | CB109: =+BX109*(1+CB131) -> #DIV/0! | CC109: =+BY109*(1+CC131) -> #DIV/0! | CD109: =+BZ109*(1+CD131) -> #DIV/0! | CE109: =+CA109*(1+CE131) -> #DIV/0! | CF109: =+CB109*(1+CF131) -> #DIV/0! | CG109: =+CC109*(1+CG131) -> #DIV/0! | ... CO109: =+CK109*(1+CO131) -> #DIV/0!
AA110: =+BY110 -> 0 | AB110: =+CC110 -> 0 | AC110: =+CG110 -> 0 | AD110: =+CK110 -> 0 | AE110: =+CO110 -> 0
A111: TFA | B111: =+'Annual Raw'!C110+'Annual Raw'!C111+'Annual Raw'!C112+'Annual Raw'!C113 -> 0 | C111: =+'Annual Raw'!D110+'Annual Raw'!D111+'Annual Raw'!D112+'Annual Raw'!D113 -> 0 | D111: =+'Annual Raw'!E110+'Annual Raw'!E111+'Annual Raw'!E112+'Annual Raw'!E113 -> 0 | E111: =+'Annual Raw'!F110+'Annual Raw'!F111+'Annual Raw'!F112+'Annual Raw'!F113 -> 0 | F111: =+'Annual Raw'!G110+'Annual Raw'!G111+'Annual Raw'!G112+'Annual Raw'!G113 -> 0 | G111: =+'Annual Raw'!H110+'Annual Raw'!H111+'Annual Raw'!H112+'Annual Raw'!H113 -> 0 | H111: =+'Annual Raw'!I110+'Annual Raw'!I111+'Annual Raw'!I112+'Annual Raw'!I113 -> 0 | I111: =+'Annual Raw'!J110+'Annual Raw'!J111+'Annual Raw'!J112+'Annual Raw'!J113 -> 0 | ... Z111: =+'Annual Raw'!AA110+'Annual Raw'!AA111+'Annual Raw'!AA112+'Annual Raw'!AA113 -> 0 | AA111: =+BY111 -> 0 | AB111: =+CC111 -> 0 | AC111: =+CG111 -> 0 | AD111: =+CK111 -> 0 | AE111: =+CO111 -> 0 | AH111: =+#REF!+#REF!+#REF!+#REF! -> #REF! | AI111: =+'QTR Raw'!E70++'QTR Raw'!E71++'QTR Raw'!E73+'QTR Raw'!E74 -> 0 | AK111: =+'QTR Raw'!G70++'QTR Raw'!G71++'QTR Raw'!G73+'QTR Raw'!G74 -> 0 | AM111: =+'QTR Raw'!I70++'QTR Raw'!I71++'QTR Raw'!I73+'QTR Raw'!I74 -> 0 | AO111: =+'QTR Raw'!K70++'QTR Raw'!K71++'QTR Raw'!K73+'QTR Raw'!K74 -> 0 | AQ111: =+'QTR Raw'!M70++'QTR Raw'!M71++'QTR Raw'!M73+'QTR Raw'!M74 -> 0 | AS111: =+'QTR Raw'!O70++'QTR Raw'!O71++'QTR Raw'!O73+'QTR Raw'!O74 -> 0 | AU111: =+'QTR Raw'!Q70++'QTR Raw'!Q71++'QTR Raw'!Q73+'QTR Raw'!Q74 -> 0 | AW111: =+'QTR Raw'!S70++'QTR Raw'!S71++'QTR Raw'!S73+'QTR Raw'!S74 -> 0 | AY111: =+'QTR Raw'!U70++'QTR Raw'!U71++'QTR Raw'!U73+'QTR Raw'!U74 -> 0 | BA111: =+'QTR Raw'!W70++'QTR Raw'!W71++'QTR Raw'!W73+'QTR Raw'!W74 -> 0 | BC111: =+'QTR Raw'!Y70++'QTR Raw'!Y71++'QTR Raw'!Y73+'QTR Raw'!Y74 -> 0 | BE111: =+'QTR Raw'!AA70++'QTR Raw'!AA71++'QTR Raw'!AA73+'QTR Raw'!AA74 -> 0 | BG111: =+'QTR Raw'!AC70++'QTR Raw'!AC71++'QTR Raw'!AC73+'QTR Raw'!AC74 -> 0 | BI111: =+'QTR Raw'!AE70++'QTR Raw'!AE71++'QTR Raw'!AE73+'QTR Raw'!AE74 -> 0 | BK111: =+'QTR Raw'!AG70++'QTR Raw'!AG71++'QTR Raw'!AG73+'QTR Raw'!AG74 -> 0 | BM111: =+'QTR Raw'!AI70++'QTR Raw'!AI71++'QTR Raw'!AI73+'QTR Raw'!AI74 -> 0 | BO111: =+'QTR Raw'!AK70++'QTR Raw'!AK71++'QTR Raw'!AK73+'QTR Raw'!AK74 -> 0 | BQ111: =+'QTR Raw'!AM70++'QTR Raw'!AM71++'QTR Raw'!AM73+'QTR Raw'!AM74 -> 0 | BS111: =+'QTR Raw'!AO70++'QTR Raw'!AO71++'QTR Raw'!AO73+'QTR Raw'!AO74 -> 0 | BU111: =+'QTR Raw'!AQ70++'QTR Raw'!AQ71++'QTR Raw'!AQ73+'QTR Raw'!AQ74 -> 0 | BW111: =+'QTR Raw'!AS70++'QTR Raw'!AS71++'QTR Raw'!AS73+'QTR Raw'!AS74 -> 0 | BY111: =+'QTR Raw'!AU70++'QTR Raw'!AU71++'QTR Raw'!AU73+'QTR Raw'!AU74 -> 0
A113: Non Current Investments | B113: =+'Annual Raw'!C116 -> 0 | C113: =+'Annual Raw'!D116 -> 0 | D113: =+'Annual Raw'!E116 -> 0 | E113: =+'Annual Raw'!F116 -> 0 | F113: =+'Annual Raw'!G116 -> 0 | G113: =+'Annual Raw'!H116 -> 0 | H113: =+'Annual Raw'!I116 -> 0 | I113: =+'Annual Raw'!J116 -> 0 | ... Z113: =+'Annual Raw'!AA116 -> 0 | AA113: =+BY113 -> 0 | AB113: =+CC113 -> 0 | AC113: =+CG113 -> 0 | AD113: =+CK113 -> 0 | AE113: =+CO113 -> 0 | AH113: =+'QTR Raw'!D76 -> 0 | AI113: =+'QTR Raw'!E76 -> 0 | AK113: =+'QTR Raw'!G76 -> 0 | AM113: =+'QTR Raw'!I76 -> 0 | AO113: =+'QTR Raw'!K76 -> 0 | AQ113: =+'QTR Raw'!M76 -> 0 | AS113: =+'QTR Raw'!O76 -> 0 | AU113: =+'QTR Raw'!Q76 -> 0 | AW113: =+'QTR Raw'!S76 -> 0 | AY113: =+'QTR Raw'!U76 -> 0 | BA113: =+'QTR Raw'!W76 -> 0 | BC113: =+'QTR Raw'!Y76 -> 0 | BE113: =+'QTR Raw'!AA76 -> 0 | BG113: =+'QTR Raw'!AC76 -> 0 | BI113: =+'QTR Raw'!AE76 -> 0 | BK113: =+'QTR Raw'!AG76 -> 0 | BM113: =+'QTR Raw'!AI76 -> 0 | BO113: =+'QTR Raw'!AK76 -> 0 | BQ113: =+'QTR Raw'!AM76 -> 0 | BS113: =+'QTR Raw'!AO76 -> 0 | BU113: =+'QTR Raw'!AQ76 -> 0 | BW113: =+'QTR Raw'!AS76 -> 0 | BY113: =+'QTR Raw'!AU76 -> 0
AA114: =+BY114 -> 0 | AB114: =+CC114 -> 0 | AC114: =+CG114 -> 0 | AD114: =+CK114 -> 0 | AE114: =+CO114 -> 0
A115: Other Non Current Assets | B115: =+'Annual Raw'!C118+'Annual Raw'!C115+'Annual Raw'!C111++'Annual Raw'!C121 -> 0 | C115: =+'Annual Raw'!D118+'Annual Raw'!D115+'Annual Raw'!D111++'Annual Raw'!D121 -> 0 | D115: =+'Annual Raw'!E118+'Annual Raw'!E115+'Annual Raw'!E111++'Annual Raw'!E121 -> 0 | E115: =+'Annual Raw'!F118+'Annual Raw'!F115+'Annual Raw'!F111++'Annual Raw'!F121 -> 0 | F115: =+'Annual Raw'!G118+'Annual Raw'!G115+'Annual Raw'!G111++'Annual Raw'!G121 -> 0 | G115: =+'Annual Raw'!H118+'Annual Raw'!H115+'Annual Raw'!H111++'Annual Raw'!H121 -> 0 | H115: =+'Annual Raw'!I118+'Annual Raw'!I115+'Annual Raw'!I111++'Annual Raw'!I121 -> 0 | I115: =+'Annual Raw'!J118+'Annual Raw'!J115+'Annual Raw'!J111++'Annual Raw'!J121 -> 0 | ... Z115: =+'Annual Raw'!AA118+'Annual Raw'!AA115+'Annual Raw'!AA111++'Annual Raw'!AA121 -> 0 | AA115: =+BY115 -> 0 | AB115: =+CC115 -> 0 | AC115: =+CG115 -> 0 | AD115: =+CK115 -> 0 | AE115: =+CO115 -> 0 | AH115: =+'QTR Raw'!D78 -> 0 | AI115: =+'QTR Raw'!E78++'QTR Raw'!E80 -> 0 | AK115: =+'QTR Raw'!G78++'QTR Raw'!G80 -> 0 | AM115: =+'QTR Raw'!I78++'QTR Raw'!I80 -> 0 | AO115: =+'QTR Raw'!K78++'QTR Raw'!K80 -> 0 | AQ115: =+'QTR Raw'!M78++'QTR Raw'!M80 -> 0 | AS115: =+'QTR Raw'!O78++'QTR Raw'!O80 -> 0 | AU115: =+'QTR Raw'!Q78++'QTR Raw'!Q80 -> 0 | AW115: =+'QTR Raw'!S78++'QTR Raw'!S80 -> 0 | AY115: =+'QTR Raw'!U78++'QTR Raw'!U80 -> 0 | BA115: =+'QTR Raw'!W78++'QTR Raw'!W80 -> 0 | BC115: =+'QTR Raw'!Y78++'QTR Raw'!Y80 -> 0 | BE115: =+'QTR Raw'!AA78++'QTR Raw'!AA80 -> 0 | BG115: =+'QTR Raw'!AC78++'QTR Raw'!AC80 -> 0 | BI115: =+'QTR Raw'!AE78++'QTR Raw'!AE80 -> 0 | BK115: =+'QTR Raw'!AG78++'QTR Raw'!AG80 -> 0 | BM115: =+'QTR Raw'!AI78++'QTR Raw'!AI80 -> 0 | BO115: =+'QTR Raw'!AK78++'QTR Raw'!AK80 -> 0 | BQ115: =+'QTR Raw'!AM78++'QTR Raw'!AM80 -> 0 | BS115: =+'QTR Raw'!AO78++'QTR Raw'!AO80 -> 0 | BU115: =+'QTR Raw'!AQ78++'QTR Raw'!AQ80 -> 0 | BW115: =+'QTR Raw'!AS78++'QTR Raw'!AS80 -> 0 | BY115: =+'QTR Raw'!AU78++'QTR Raw'!AU80 -> 0
A116: Other Current Assets | B116: =+'Annual Raw'!C124+'Annual Raw'!C126++'Annual Raw'!C120++'Annual Raw'!C123++'Annual Raw'!C122 -> 0 | C116: =+'Annual Raw'!D124+'Annual Raw'!D126++'Annual Raw'!D120++'Annual Raw'!D123++'Annual Raw'!D122 -> 0 | D116: =+'Annual Raw'!E124+'Annual Raw'!E126++'Annual Raw'!E120++'Annual Raw'!E123++'Annual Raw'!E122 -> 0 | E116: =+'Annual Raw'!F124+'Annual Raw'!F126++'Annual Raw'!F120++'Annual Raw'!F123++'Annual Raw'!F122 -> 0 | F116: =+'Annual Raw'!G124+'Annual Raw'!G126++'Annual Raw'!G120++'Annual Raw'!G123++'Annual Raw'!G122 -> 0 | G116: =+'Annual Raw'!H124+'Annual Raw'!H126++'Annual Raw'!H120++'Annual Raw'!H123++'Annual Raw'!H122 -> 0 | H116: =+'Annual Raw'!I124+'Annual Raw'!I126++'Annual Raw'!I120++'Annual Raw'!I123++'Annual Raw'!I122 -> 0 | I116: =+'Annual Raw'!J124+'Annual Raw'!J126++'Annual Raw'!J120++'Annual Raw'!J123++'Annual Raw'!J122 -> 0 | ... Z116: =+'Annual Raw'!AA124+'Annual Raw'!AA126++'Annual Raw'!AA120++'Annual Raw'!AA123++'Annual Raw'!AA122 -> 0 | AA116: =+BY116 -> 0 | AB116: =+CC116 -> 0 | AC116: =+CG116 -> 0 | AD116: =+CK116 -> 0 | AE116: =+CO116 -> 0 | AH116: =+'QTR Raw'!D83 -> 0 | AI116: =+'QTR Raw'!E83+'QTR Raw'!E79++'QTR Raw'!E82++'QTR Raw'!E81 -> 0 | AJ116: =+AI117 -> 0 | AK116: =+'QTR Raw'!G83+'QTR Raw'!G79++'QTR Raw'!G82++'QTR Raw'!G81 -> 0 | AL116: =+AK117 -> 0 | AM116: =+'QTR Raw'!I83+'QTR Raw'!I79++'QTR Raw'!I82++'QTR Raw'!I81 -> 0 | AN116: =+AM117 -> 0 | AO116: =+'QTR Raw'!K83+'QTR Raw'!K79++'QTR Raw'!K82++'QTR Raw'!K81 -> 0 | AP116: =+AO117 -> 0 | AQ116: =+'QTR Raw'!M83+'QTR Raw'!M79++'QTR Raw'!M82++'QTR Raw'!M81 -> 0 | AR116: =+AQ117 -> 0 | AS116: =+'QTR Raw'!O83+'QTR Raw'!O79++'QTR Raw'!O82++'QTR Raw'!O81 -> 0 | AT116: =+AS117 -> 0 | AU116: =+'QTR Raw'!Q83+'QTR Raw'!Q79++'QTR Raw'!Q82++'QTR Raw'!Q81 -> 0 | AV116: =+AU117 -> 0 | AW116: =+'QTR Raw'!S83+'QTR Raw'!S79++'QTR Raw'!S82++'QTR Raw'!S81 -> 0 | AX116: =+AW117 -> 0 | AY116: =+'QTR Raw'!U83+'QTR Raw'!U79++'QTR Raw'!U82++'QTR Raw'!U81 -> 0 | AZ116: =+AY117 -> 0 | BA116: =+'QTR Raw'!W83+'QTR Raw'!W79++'QTR Raw'!W82++'QTR Raw'!W81 -> 0 | BB116: =+BA117 -> 0 | BC116: =+'QTR Raw'!Y83+'QTR Raw'!Y79++'QTR Raw'!Y82++'QTR Raw'!Y81 -> 0 | BD116: =+BC117 -> 0 | BE116: =+'QTR Raw'!AA83+'QTR Raw'!AA79++'QTR Raw'!AA82++'QTR Raw'!AA81 -> 0 | BF116: =+BE117 -> 0 | BG116: =+'QTR Raw'!AC83+'QTR Raw'!AC79++'QTR Raw'!AC82++'QTR Raw'!AC81 -> 0 | BH116: =+BG117 -> 0 | BI116: =+'QTR Raw'!AE83+'QTR Raw'!AE79++'QTR Raw'!AE82++'QTR Raw'!AE81 -> 0 | BJ116: =+BI117 -> 0 | BK116: =+'QTR Raw'!AG83+'QTR Raw'!AG79++'QTR Raw'!AG82++'QTR Raw'!AG81 -> 0 | BL116: =+BK117 -> 0 | BM116: =+'QTR Raw'!AI83+'QTR Raw'!AI79++'QTR Raw'!AI82++'QTR Raw'!AI81 -> 0 | BN116: =+BM117 -> 0 | BO116: =+'QTR Raw'!AK83++'QTR Raw'!AK79++'QTR Raw'!AK82++'QTR Raw'!AK81 -> 0 | BP116: =+BO117 -> 0 | BQ116: =+'QTR Raw'!AM83++'QTR Raw'!AM79++'QTR Raw'!AM82++'QTR Raw'!AM81 -> 0 | BR116: =+BQ117 -> 0 | BS116: =+'QTR Raw'!AO83++'QTR Raw'!AO79++'QTR Raw'!AO82++'QTR Raw'!AO81 -> 0 | BT116: =+BS117 -> 0 | BU116: =+'QTR Raw'!AQ83++'QTR Raw'!AQ79++'QTR Raw'!AQ82++'QTR Raw'!AQ81 -> 0 | BV116: =+BU117 -> 0 | BW116: =+'QTR Raw'!AS83++'QTR Raw'!AS79++'QTR Raw'!AS82++'QTR Raw'!AS81 -> 0 | BX116: =+BW117 -> 0 | BY116: =+'QTR Raw'!AU83+'QTR Raw'!AU79++'QTR Raw'!AU82++'QTR Raw'!AU81 -> 0
A117: TCA | B117: =+SUM(B115:B116) -> 0 | C117: =+SUM(C115:C116) -> 0 | D117: =+SUM(D115:D116) -> 0 | E117: =+SUM(E115:E116) -> 0 | F117: =+SUM(F115:F116) -> 0 | G117: =+SUM(G115:G116) -> 0 | H117: =+SUM(H115:H116) -> 0 | I117: =+SUM(I115:I116) -> 0 | ... Z117: =+SUM(Z115:Z116) -> 0 | AA117: =+BY117 -> 0 | AB117: =+CC117 -> 0 | AC117: =+CG117 -> 0 | AD117: =+CK117 -> 0 | AE117: =+CO117 -> 0 | AH117: =+SUM(AH115:AH116) -> 0 | AI117: =+SUM(AI115:AI116) -> 0 | AJ117: =+SUM(AJ115:AJ116) -> 0 | AK117: =+SUM(AK115:AK116) -> 0 | AL117: =+SUM(AL115:AL116) -> 0 | AM117: =+SUM(AM115:AM116) -> 0 | AN117: =+SUM(AN115:AN116) -> 0 | AO117: =+SUM(AO115:AO116) -> 0 | ... BY117: =+SUM(BY115:BY116) -> 0
A118: Other Long Term Liabilities | B118: =+'Annual Raw'!C89++'Annual Raw'!C90++'Annual Raw'!C91 -> 0 | C118: =+'Annual Raw'!D89++'Annual Raw'!D90++'Annual Raw'!D91 -> 0 | D118: =+'Annual Raw'!E89++'Annual Raw'!E90++'Annual Raw'!E91 -> 0 | E118: =+'Annual Raw'!F89++'Annual Raw'!F90++'Annual Raw'!F91 -> 0 | F118: =+'Annual Raw'!G89++'Annual Raw'!G90++'Annual Raw'!G91 -> 0 | G118: =+'Annual Raw'!H89++'Annual Raw'!H90++'Annual Raw'!H91 -> 0 | H118: =+'Annual Raw'!I89++'Annual Raw'!I90++'Annual Raw'!I91 -> 0 | I118: =+'Annual Raw'!J89++'Annual Raw'!J90++'Annual Raw'!J91 -> 0 | ... Z118: =+'Annual Raw'!AA89++'Annual Raw'!AA90++'Annual Raw'!AA91 -> 0 | AA118: =+BY118 -> 0 | AB118: =+CC118 -> 0 | AC118: =+CG118 -> 0 | AD118: =+CK118 -> 0 | AE118: =+CO118 -> 0 | AH118: =+'QTR Raw'!D63 -> 0 | AI118: =+'QTR Raw'!E63++'QTR Raw'!E64++'QTR Raw'!E65 -> 0 | AK118: =+'QTR Raw'!G63++'QTR Raw'!G64++'QTR Raw'!G65 -> 0 | AM118: =+'QTR Raw'!I63++'QTR Raw'!I64++'QTR Raw'!I65 -> 0 | AO118: =+'QTR Raw'!K63++'QTR Raw'!K64++'QTR Raw'!K65 -> 0 | AQ118: =+'QTR Raw'!M63++'QTR Raw'!M64++'QTR Raw'!M65 -> 0 | AS118: =+'QTR Raw'!O63++'QTR Raw'!O64++'QTR Raw'!O65 -> 0 | AU118: =+'QTR Raw'!Q63++'QTR Raw'!Q64++'QTR Raw'!Q65 -> 0 | AW118: =+'QTR Raw'!S63++'QTR Raw'!S64++'QTR Raw'!S65 -> 0 | AY118: =+'QTR Raw'!U63++'QTR Raw'!U64++'QTR Raw'!U65 -> 0 | BA118: =+'QTR Raw'!W63++'QTR Raw'!W64++'QTR Raw'!W65 -> 0 | BC118: =+'QTR Raw'!Y63++'QTR Raw'!Y64++'QTR Raw'!Y65 -> 0 | BE118: =+'QTR Raw'!AA63++'QTR Raw'!AA64++'QTR Raw'!AA65 -> 0 | BG118: =+'QTR Raw'!AC63++'QTR Raw'!AC64++'QTR Raw'!AC65 -> 0 | BI118: =+'QTR Raw'!AE63++'QTR Raw'!AE64++'QTR Raw'!AE65 -> 0 | BK118: =+'QTR Raw'!AG63++'QTR Raw'!AG64++'QTR Raw'!AG65 -> 0 | BM118: =+'QTR Raw'!AI63++'QTR Raw'!AI64++'QTR Raw'!AI65 -> 0 | BO118: =+'QTR Raw'!AK63++'QTR Raw'!AK64++'QTR Raw'!AK65 -> 0 | BQ118: =+'QTR Raw'!AM63++'QTR Raw'!AM64++'QTR Raw'!AM65 -> 0 | BS118: =+'QTR Raw'!AO63++'QTR Raw'!AO64++'QTR Raw'!AO65 -> 0 | BU118: =+'QTR Raw'!AQ63++'QTR Raw'!AQ64++'QTR Raw'!AQ65 -> 0 | BW118: =+'QTR Raw'!AS63++'QTR Raw'!AS64++'QTR Raw'!AS65 -> 0 | BY118: =+'QTR Raw'!AU63++'QTR Raw'!AU64++'QTR Raw'!AU65 -> 0
A119: Other Current Liabilities | B119: =+'Annual Raw'!C94+'Annual Raw'!C102++'Annual Raw'!C93++'Annual Raw'!C101 -> 0 | C119: =+'Annual Raw'!D94+'Annual Raw'!D102++'Annual Raw'!D93++'Annual Raw'!D101 -> 0 | D119: =+'Annual Raw'!E94+'Annual Raw'!E102++'Annual Raw'!E93++'Annual Raw'!E101 -> 0 | E119: =+'Annual Raw'!F94+'Annual Raw'!F102++'Annual Raw'!F93++'Annual Raw'!F101 -> 0 | F119: =+'Annual Raw'!G94+'Annual Raw'!G102++'Annual Raw'!G93++'Annual Raw'!G101 -> 0 | G119: =+'Annual Raw'!H94+'Annual Raw'!H102++'Annual Raw'!H93++'Annual Raw'!H101 -> 0 | H119: =+'Annual Raw'!I94+'Annual Raw'!I102++'Annual Raw'!I93++'Annual Raw'!I101 -> 0 | I119: =+'Annual Raw'!J94+'Annual Raw'!J102++'Annual Raw'!J93++'Annual Raw'!J101 -> 0 | ... Z119: =+'Annual Raw'!AA94+'Annual Raw'!AA102++'Annual Raw'!AA93++'Annual Raw'!AA101 -> 0 | AA119: =+BY119 -> 0 | AB119: =+CC119 -> 0 | AC119: =+CG119 -> 0 | AD119: =+CK119 -> 0 | AE119: =+CO119 -> 0 | AH119: =+'QTR Raw'!D89 -> 0 | AI119: =+'QTR Raw'!E89-'QTR Raw'!E90-'QTR Raw'!E91+'QTR Raw'!E88 -> 0 | AJ119: =+AI120 -> 0 | AK119: =+'QTR Raw'!G89-'QTR Raw'!G90-'QTR Raw'!G91+'QTR Raw'!G88 -> 0 | AL119: =+AK120 -> 0 | AM119: =+'QTR Raw'!I89-'QTR Raw'!I90-'QTR Raw'!I91+'QTR Raw'!I88 -> 0 | AN119: =+AM120 -> 0 | AO119: =+'QTR Raw'!K89-'QTR Raw'!K90-'QTR Raw'!K91+'QTR Raw'!K88 -> 0 | AP119: =+AO120 -> 0 | AQ119: =+'QTR Raw'!M89-'QTR Raw'!M90-'QTR Raw'!M91+'QTR Raw'!M88 -> 0 | AR119: =+AQ120 -> 0 | AS119: =+'QTR Raw'!O89-'QTR Raw'!O90-'QTR Raw'!O91+'QTR Raw'!O88 -> 0 | AT119: =+AS120 -> 0 | AU119: =+'QTR Raw'!Q89-'QTR Raw'!Q90-'QTR Raw'!Q91+'QTR Raw'!Q88 -> 0 | AV119: =+AU120 -> 0 | AW119: =+'QTR Raw'!S89-'QTR Raw'!S90-'QTR Raw'!S91+'QTR Raw'!S88 -> 0 | AX119: =+AW120 -> 0 | AY119: =+'QTR Raw'!U89-'QTR Raw'!U90-'QTR Raw'!U91+'QTR Raw'!U88 -> 0 | AZ119: =+AY120 -> 0 | BA119: =+'QTR Raw'!W89-'QTR Raw'!W90-'QTR Raw'!W91+'QTR Raw'!W88 -> 0 | BB119: =+BA120 -> 0 | BC119: =+'QTR Raw'!Y89-'QTR Raw'!Y90-'QTR Raw'!Y91+'QTR Raw'!Y88 -> 0 | BD119: =+BC120 -> 0 | BE119: =+'QTR Raw'!AA89-'QTR Raw'!AA90-'QTR Raw'!AA91+'QTR Raw'!AA88 -> 0 | BF119: =+BE120 -> 0 | BG119: =+'QTR Raw'!AC89-'QTR Raw'!AC90-'QTR Raw'!AC91+'QTR Raw'!AC88 -> 0 | BH119: =+BG120 -> 0 | BI119: =+'QTR Raw'!AE89-'QTR Raw'!AE90-'QTR Raw'!AE91+'QTR Raw'!AE88 -> 0 | BJ119: =+BI120 -> 0 | BK119: =+'QTR Raw'!AG89-'QTR Raw'!AG90-'QTR Raw'!AG91+'QTR Raw'!AG88 -> 0 | BL119: =+BK120 -> 0 | BM119: =+'QTR Raw'!AI89-'QTR Raw'!AI90-'QTR Raw'!AI91+'QTR Raw'!AI88 -> 0 | BN119: =+BM120 -> 0 | BO119: =+'QTR Raw'!AK89-'QTR Raw'!AK90-'QTR Raw'!AK91+'QTR Raw'!AK88 -> 0 | BP119: =+BO120 -> 0 | BQ119: =+'QTR Raw'!AM89-'QTR Raw'!AM90-'QTR Raw'!AM91+'QTR Raw'!AM88 -> 0 | BR119: =+BQ120 -> 0 | BS119: =+'QTR Raw'!AO89-'QTR Raw'!AO90-'QTR Raw'!AO91+'QTR Raw'!AO88 -> 0 | BT119: =+BS120 -> 0 | BU119: =+'QTR Raw'!AQ89-'QTR Raw'!AQ90-'QTR Raw'!AQ91+'QTR Raw'!AQ88 -> 0 | BV119: =+BU120 -> 0 | BW119: =+'QTR Raw'!AS89-'QTR Raw'!AS90-'QTR Raw'!AS91+'QTR Raw'!AS88 -> 0 | BX119: =+BW120 -> 0 | BY119: =+'QTR Raw'!AU89-'QTR Raw'!AU90-'QTR Raw'!AU91+'QTR Raw'!AU88 -> 0
A120: TCL | B120: =+SUM(B118:B119) -> 0 | C120: =+SUM(C118:C119) -> 0 | D120: =+SUM(D118:D119) -> 0 | E120: =+SUM(E118:E119) -> 0 | F120: =+SUM(F118:F119) -> 0 | G120: =+SUM(G118:G119) -> 0 | H120: =+SUM(H118:H119) -> 0 | I120: =+SUM(I118:I119) -> 0 | ... AE120: =+SUM(AE118:AE119) -> 0 | AH120: =+SUM(AH118:AH119) -> 0 | AI120: =+SUM(AI118:AI119) -> 0 | AJ120: =+SUM(AJ118:AJ119) -> 0 | AK120: =+SUM(AK118:AK119) -> 0 | AL120: =+SUM(AL118:AL119) -> 0 | AM120: =+SUM(AM118:AM119) -> 0 | AN120: =+SUM(AN118:AN119) -> 0 | AO120: =+SUM(AO118:AO119) -> 0 | ... BY120: =+SUM(BY118:BY119) -> 0
...

Sheet Annual Raw
B1: X | C1: 200103 | D1: 200203 | E1: 200303 | F1: 200403 | G1: 200503 | H1: 200603 | I1: 200703 | J1: 200803 | K1: 200903 | L1: 201003 | M1: 201103 | N1: 201203 | O1: 201303 | P1: 201403 | Q1: 201503 | R1: 201603 | S1: 201703 | T1: 201803 | U1: 201903 | V1: 202003 | W1: 202103 | X1: 202203 | Y1: 202303 | Z1: 202403 | AA1: 202503 | AB1: 202603 | AC1: 202703 | AD1: 202803 | AE1: 202903 | AF1: 203003
B2: {=_xll.EQNXTDZ($A$1,$B3,C$2)} -> 0
A3: Company Name | B3: CD_COMPNAME
A4: Field Description | B4: Field Name
A5: No of Months | B5: BPL_NO_MONTHS | C5: {=_xll.EQNXTDZ($A$1,$B5,C$1,$B$1)} -> 0 | D5: {=_xll.EQNXTDZ($A$1,$B5,D$1,$B$1)} -> 0 | E5: {=_xll.EQNXTDZ($A$1,$B5,E$1,$B$1)} -> 0 | F5: {=_xll.EQNXTDZ($A$1,$B5,F$1,$B$1)} -> 0 | G5: {=_xll.EQNXTDZ($A$1,$B5,G$1,$B$1)} -> 0 | H5: {=_xll.EQNXTDZ($A$1,$B5,H$1,$B$1)} -> 0 | I5: {=_xll.EQNXTDZ($A$1,$B5,I$1,$B$1)} -> 0 | J5: {=_xll.EQNXTDZ($A$1,$B5,J$1,$B$1)} -> 0 | ... AF5: {=_xll.EQNXTDZ($A$1,$B5,AF$1,$B$1)} -> 0
A6: Year end date | B6: BPL_YEAR_ENDDATE | C6: {=_xll.EQNXTDZ($A$1,$B6,C$1,$B$1)} -> 0 | D6: {=_xll.EQNXTDZ($A$1,$B6,D$1,$B$1)} -> 0 | E6: {=_xll.EQNXTDZ($A$1,$B6,E$1,$B$1)} -> 0 | F6: {=_xll.EQNXTDZ($A$1,$B6,F$1,$B$1)} -> 0 | G6: {=_xll.EQNXTDZ($A$1,$B6,G$1,$B$1)} -> 0 | H6: {=_xll.EQNXTDZ($A$1,$B6,H$1,$B$1)} -> 0 | I6: {=_xll.EQNXTDZ($A$1,$B6,I$1,$B$1)} -> 0 | J6: {=_xll.EQNXTDZ($A$1,$B6,J$1,$B$1)} -> 0 | ... AF6: {=_xll.EQNXTDZ($A$1,$B6,AF$1,$B$1)} -> 0
A8: Field Description | B8: Field Name
A9: Year End | B9: PL_YEAR_END | C9: {=_xll.EQNXTDZ($A$1,$B9,C$1,$B$1)} -> 0 | D9: {=_xll.EQNXTDZ($A$1,$B9,D$1,$B$1)} -> 0 | E9: {=_xll.EQNXTDZ($A$1,$B9,E$1,$B$1)} -> 0 | F9: {=_xll.EQNXTDZ($A$1,$B9,F$1,$B$1)} -> 0 | G9: {=_xll.EQNXTDZ($A$1,$B9,G$1,$B$1)} -> 0 | H9: {=_xll.EQNXTDZ($A$1,$B9,H$1,$B$1)} -> 0 | I9: {=_xll.EQNXTDZ($A$1,$B9,I$1,$B$1)} -> 0 | J9: {=_xll.EQNXTDZ($A$1,$B9,J$1,$B$1)} -> 0 | ... AF9: {=_xll.EQNXTDZ($A$1,$B9,AF$1,$B$1)} -> 0
A10: Year | B10: PL_YEAR | C10: {=_xll.EQNXTDZ($A$1,$B10,C$1,$B$1)} -> 0 | D10: {=_xll.EQNXTDZ($A$1,$B10,D$1,$B$1)} -> 0 | E10: {=_xll.EQNXTDZ($A$1,$B10,E$1,$B$1)} -> 0 | F10: {=_xll.EQNXTDZ($A$1,$B10,F$1,$B$1)} -> 0 | G10: {=_xll.EQNXTDZ($A$1,$B10,G$1,$B$1)} -> 0 | H10: {=_xll.EQNXTDZ($A$1,$B10,H$1,$B$1)} -> 0 | I10: {=_xll.EQNXTDZ($A$1,$B10,I$1,$B$1)} -> 0 | J10: {=_xll.EQNXTDZ($A$1,$B10,J$1,$B$1)} -> 0 | ... AF10: {=_xll.EQNXTDZ($A$1,$B10,AF$1,$B$1)} -> 0
A11: Year end date | B11: PL_YEAR_ENDDATE | C11: {=_xll.EQNXTDZ($A$1,$B11,C$1,$B$1)} -> 0 | D11: {=_xll.EQNXTDZ($A$1,$B11,D$1,$B$1)} -> 0 | E11: {=_xll.EQNXTDZ($A$1,$B11,E$1,$B$1)} -> 0 | F11: {=_xll.EQNXTDZ($A$1,$B11,F$1,$B$1)} -> 0 | G11: {=_xll.EQNXTDZ($A$1,$B11,G$1,$B$1)} -> 0 | H11: {=_xll.EQNXTDZ($A$1,$B11,H$1,$B$1)} -> 0 | I11: {=_xll.EQNXTDZ($A$1,$B11,I$1,$B$1)} -> 0 | J11: {=_xll.EQNXTDZ($A$1,$B11,J$1,$B$1)} -> 0 | ... AF11: {=_xll.EQNXTDZ($A$1,$B11,AF$1,$B$1)} -> 0
A12: No of Months | B12: PL_NO_MONTHS | C12: {=_xll.EQNXTDZ($A$1,$B12,C$1,$B$1)} -> 0 | D12: {=_xll.EQNXTDZ($A$1,$B12,D$1,$B$1)} -> 0 | E12: {=_xll.EQNXTDZ($A$1,$B12,E$1,$B$1)} -> 0 | F12: {=_xll.EQNXTDZ($A$1,$B12,F$1,$B$1)} -> 0 | G12: {=_xll.EQNXTDZ($A$1,$B12,G$1,$B$1)} -> 0 | H12: {=_xll.EQNXTDZ($A$1,$B12,H$1,$B$1)} -> 0 | I12: {=_xll.EQNXTDZ($A$1,$B12,I$1,$B$1)} -> 0 | J12: {=_xll.EQNXTDZ($A$1,$B12,J$1,$B$1)} -> 0 | ... AF12: {=_xll.EQNXTDZ($A$1,$B12,AF$1,$B$1)} -> 0
A13: Sales Turnover | B13: PL_TOTAL_GROSS_SALES | C13: {=_xll.EQNXTDZ($A$1,$B13,C$1,$B$1)} -> 0 | D13: {=_xll.EQNXTDZ($A$1,$B13,D$1,$B$1)} -> 0 | E13: {=_xll.EQNXTDZ($A$1,$B13,E$1,$B$1)} -> 0 | F13: {=_xll.EQNXTDZ($A$1,$B13,F$1,$B$1)} -> 0 | G13: {=_xll.EQNXTDZ($A$1,$B13,G$1,$B$1)} -> 0 | H13: {=_xll.EQNXTDZ($A$1,$B13,H$1,$B$1)} -> 0 | I13: {=_xll.EQNXTDZ($A$1,$B13,I$1,$B$1)} -> 0 | J13: {=_xll.EQNXTDZ($A$1,$B13,J$1,$B$1)} -> 0 | ... AF13: {=_xll.EQNXTDZ($A$1,$B13,AF$1,$B$1)} -> 0
A14: Net Sales | B14: PL_NET_SALES | C14: {=_xll.EQNXTDZ($A$1,$B14,C$1,$B$1)} -> 0 | D14: {=_xll.EQNXTDZ($A$1,$B14,D$1,$B$1)} -> 0 | E14: {=_xll.EQNXTDZ($A$1,$B14,E$1,$B$1)} -> 0 | F14: {=_xll.EQNXTDZ($A$1,$B14,F$1,$B$1)} -> 0 | G14: {=_xll.EQNXTDZ($A$1,$B14,G$1,$B$1)} -> 0 | H14: {=_xll.EQNXTDZ($A$1,$B14,H$1,$B$1)} -> 0 | I14: {=_xll.EQNXTDZ($A$1,$B14,I$1,$B$1)} -> 0 | J14: {=_xll.EQNXTDZ($A$1,$B14,J$1,$B$1)} -> 0 | ... AF14: {=_xll.EQNXTDZ($A$1,$B14,AF$1,$B$1)} -> 0
A15: Increase/Decrease in Stock | B15: PL_INC_DEC_INVENTORY | C15: {=_xll.EQNXTDZ($A$1,$B15,C$1,$B$1)} -> 0 | D15: {=_xll.EQNXTDZ($A$1,$B15,D$1,$B$1)} -> 0 | E15: {=_xll.EQNXTDZ($A$1,$B15,E$1,$B$1)} -> 0 | F15: {=_xll.EQNXTDZ($A$1,$B15,F$1,$B$1)} -> 0 | G15: {=_xll.EQNXTDZ($A$1,$B15,G$1,$B$1)} -> 0 | H15: {=_xll.EQNXTDZ($A$1,$B15,H$1,$B$1)} -> 0 | I15: {=_xll.EQNXTDZ($A$1,$B15,I$1,$B$1)} -> 0 | J15: {=_xll.EQNXTDZ($A$1,$B15,J$1,$B$1)} -> 0 | ... AF15: {=_xll.EQNXTDZ($A$1,$B15,AF$1,$B$1)} -> 0
A16: Raw Material Consumed | B16: PL_RAW_MATRS_CONSUMED | C16: {=_xll.EQNXTDZ($A$1,$B16,C$1,$B$1)} -> 0 | D16: {=_xll.EQNXTDZ($A$1,$B16,D$1,$B$1)} -> 0 | E16: {=_xll.EQNXTDZ($A$1,$B16,E$1,$B$1)} -> 0 | F16: {=_xll.EQNXTDZ($A$1,$B16,F$1,$B$1)} -> 0 | G16: {=_xll.EQNXTDZ($A$1,$B16,G$1,$B$1)} -> 0 | H16: {=_xll.EQNXTDZ($A$1,$B16,H$1,$B$1)} -> 0 | I16: {=_xll.EQNXTDZ($A$1,$B16,I$1,$B$1)} -> 0 | J16: {=_xll.EQNXTDZ($A$1,$B16,J$1,$B$1)} -> 0 | ... AF16: {=_xll.EQNXTDZ($A$1,$B16,AF$1,$B$1)} -> 0
A17: Power & Fuel Cost | B17: PL_POWER_FUEL | C17: {=_xll.EQNXTDZ($A$1,$B17,C$1,$B$1)} -> 0 | D17: {=_xll.EQNXTDZ($A$1,$B17,D$1,$B$1)} -> 0 | E17: {=_xll.EQNXTDZ($A$1,$B17,E$1,$B$1)} -> 0 | F17: {=_xll.EQNXTDZ($A$1,$B17,F$1,$B$1)} -> 0 | G17: {=_xll.EQNXTDZ($A$1,$B17,G$1,$B$1)} -> 0 | H17: {=_xll.EQNXTDZ($A$1,$B17,H$1,$B$1)} -> 0 | I17: {=_xll.EQNXTDZ($A$1,$B17,I$1,$B$1)} -> 0 | J17: {=_xll.EQNXTDZ($A$1,$B17,J$1,$B$1)} -> 0 | ... AF17: {=_xll.EQNXTDZ($A$1,$B17,AF$1,$B$1)} -> 0
A18: Employee Cost | B18: PL_EMPLOYEES | C18: {=_xll.EQNXTDZ($A$1,$B18,C$1,$B$1)} -> 0 | D18: {=_xll.EQNXTDZ($A$1,$B18,D$1,$B$1)} -> 0 | E18: {=_xll.EQNXTDZ($A$1,$B18,E$1,$B$1)} -> 0 | F18: {=_xll.EQNXTDZ($A$1,$B18,F$1,$B$1)} -> 0 | G18: {=_xll.EQNXTDZ($A$1,$B18,G$1,$B$1)} -> 0 | H18: {=_xll.EQNXTDZ($A$1,$B18,H$1,$B$1)} -> 0 | I18: {=_xll.EQNXTDZ($A$1,$B18,I$1,$B$1)} -> 0 | J18: {=_xll.EQNXTDZ($A$1,$B18,J$1,$B$1)} -> 0 | ... AF18: {=_xll.EQNXTDZ($A$1,$B18,AF$1,$B$1)} -> 0
A19: Operating & Manufacturing Expenses | B19: PL_GEN_OTHER_MFG_EXPS | C19: {=_xll.EQNXTDZ($A$1,$B19,C$1,$B$1)} -> 0 | D19: {=_xll.EQNXTDZ($A$1,$B19,D$1,$B$1)} -> 0 | E19: {=_xll.EQNXTDZ($A$1,$B19,E$1,$B$1)} -> 0 | F19: {=_xll.EQNXTDZ($A$1,$B19,F$1,$B$1)} -> 0 | G19: {=_xll.EQNXTDZ($A$1,$B19,G$1,$B$1)} -> 0 | H19: {=_xll.EQNXTDZ($A$1,$B19,H$1,$B$1)} -> 0 | I19: {=_xll.EQNXTDZ($A$1,$B19,I$1,$B$1)} -> 0 | J19: {=_xll.EQNXTDZ($A$1,$B19,J$1,$B$1)} -> 0 | ... AF19: {=_xll.EQNXTDZ($A$1,$B19,AF$1,$B$1)} -> 0
A20: Cost of Software development | B20: PL_COST_SW | C20: {=_xll.EQNXTDZ($A$1,$B20,C$1,$B$1)} -> 0 | D20: {=_xll.EQNXTDZ($A$1,$B20,D$1,$B$1)} -> 0 | E20: {=_xll.EQNXTDZ($A$1,$B20,E$1,$B$1)} -> 0 | F20: {=_xll.EQNXTDZ($A$1,$B20,F$1,$B$1)} -> 0 | G20: {=_xll.EQNXTDZ($A$1,$B20,G$1,$B$1)} -> 0 | H20: {=_xll.EQNXTDZ($A$1,$B20,H$1,$B$1)} -> 0 | I20: {=_xll.EQNXTDZ($A$1,$B20,I$1,$B$1)} -> 0 | J20: {=_xll.EQNXTDZ($A$1,$B20,J$1,$B$1)} -> 0 | ... AF20: {=_xll.EQNXTDZ($A$1,$B20,AF$1,$B$1)} -> 0
... A49: Consolidated Net Profit | B49: PLC_CONSOLIDATED_NETPROFIT | C49: {=_xll.EQNXTDZ($A$1,$B49,C$1,$B$1)} -> 0 | D49: {=_xll.EQNXTDZ($A$1,$B49,D$1,$B$1)} -> 0 | E49: {=_xll.EQNXTDZ($A$1,$B49,E$1,$B$1)} -> 0 | F49: {=_xll.EQNXTDZ($A$1,$B49,F$1,$B$1)} -> 0 | G49: {=_xll.EQNXTDZ($A$1,$B49,G$1,$B$1)} -> 0 | H49: {=_xll.EQNXTDZ($A$1,$B49,H$1,$B$1)} -> 0 | I49: {=_xll.EQNXTDZ($A$1,$B49,I$1,$B$1)} -> 0 | J49: {=_xll.EQNXTDZ($A$1,$B49,J$1,$B$1)} -> 0 | ... AF49: {=_xll.EQNXTDZ($A$1,$B49,AF$1,$B$1)} -> 0
A51: Field Description | B51: Field Name
A52: Equity Paid Up | B52: FH_EQUITY_PAIDUP | C52: {=_xll.EQNXTDZ($A$1,$B52,C$1,$B$1)} -> 0 | D52: {=_xll.EQNXTDZ($A$1,$B52,D$1,$B$1)} -> 0 | E52: {=_xll.EQNXTDZ($A$1,$B52,E$1,$B$1)} -> 0 | F52: {=_xll.EQNXTDZ($A$1,$B52,F$1,$B$1)} -> 0 | G52: {=_xll.EQNXTDZ($A$1,$B52,G$1,$B$1)} -> 0 | H52: {=_xll.EQNXTDZ($A$1,$B52,H$1,$B$1)} -> 0 | I52: {=_xll.EQNXTDZ($A$1,$B52,I$1,$B$1)} -> 0 | J52: {=_xll.EQNXTDZ($A$1,$B52,J$1,$B$1)} -> 0 | ... AF52: {=_xll.EQNXTDZ($A$1,$B52,AF$1,$B$1)} -> 0
A53: Reserves and Surplus | B53: FH_RESERVE | C53: {=_xll.EQNXTDZ($A$1,$B53,C$1,$B$1)} -> 0 | D53: {=_xll.EQNXTDZ($A$1,$B53,D$1,$B$1)} -> 0 | E53: {=_xll.EQNXTDZ($A$1,$B53,E$1,$B$1)} -> 0 | F53: {=_xll.EQNXTDZ($A$1,$B53,F$1,$B$1)} -> 0 | G53: {=_xll.EQNXTDZ($A$1,$B53,G$1,$B$1)} -> 0 | H53: {=_xll.EQNXTDZ($A$1,$B53,H$1,$B$1)} -> 0 | I53: {=_xll.EQNXTDZ($A$1,$B53,I$1,$B$1)} -> 0 | J53: {=_xll.EQNXTDZ($A$1,$B53,J$1,$B$1)} -> 0 | ... AF53: {=_xll.EQNXTDZ($A$1,$B53,AF$1,$B$1)} -> 0
A54: Net Worth | B54: FH_NET_WORTH | C54: {=_xll.EQNXTDZ($A$1,$B54,C$1,$B$1)} -> 0 | D54: {=_xll.EQNXTDZ($A$1,$B54,D$1,$B$1)} -> 0 | E54: {=_xll.EQNXTDZ($A$1,$B54,E$1,$B$1)} -> 0 | F54: {=_xll.EQNXTDZ($A$1,$B54,F$1,$B$1)} -> 0 | G54: {=_xll.EQNXTDZ($A$1,$B54,G$1,$B$1)} -> 0 | H54: {=_xll.EQNXTDZ($A$1,$B54,H$1,$B$1)} -> 0 | I54: {=_xll.EQNXTDZ($A$1,$B54,I$1,$B$1)} -> 0 | J54: {=_xll.EQNXTDZ($A$1,$B54,J$1,$B$1)} -> 0 | ... AF54: {=_xll.EQNXTDZ($A$1,$B54,AF$1,$B$1)} -> 0
A55: Total Debt | B55: FH_TOTAL_DEBTS | C55: {=_xll.EQNXTDZ($A$1,$B55,C$1,$B$1)} -> 0 | D55: {=_xll.EQNXTDZ($A$1,$B55,D$1,$B$1)} -> 0 | E55: {=_xll.EQNXTDZ($A$1,$B55,E$1,$B$1)} -> 0 | F55: {=_xll.EQNXTDZ($A$1,$B55,F$1,$B$1)} -> 0 | G55: {=_xll.EQNXTDZ($A$1,$B55,G$1,$B$1)} -> 0 | H55: {=_xll.EQNXTDZ($A$1,$B55,H$1,$B$1)} -> 0 | I55: {=_xll.EQNXTDZ($A$1,$B55,I$1,$B$1)} -> 0 | J55: {=_xll.EQNXTDZ($A$1,$B55,J$1,$B$1)} -> 0 | ... AF55: {=_xll.EQNXTDZ($A$1,$B55,AF$1,$B$1)} -> 0
A56: Deposits | B56: FH_DEPOSITS | C56: {=_xll.EQNXTDZ($A$1,$B56,C$1,$B$1)} -> 0 | D56: {=_xll.EQNXTDZ($A$1,$B56,D$1,$B$1)} -> 0 | E56: {=_xll.EQNXTDZ($A$1,$B56,E$1,$B$1)} -> 0 | F56: {=_xll.EQNXTDZ($A$1,$B56,F$1,$B$1)} -> 0 | G56: {=_xll.EQNXTDZ($A$1,$B56,G$1,$B$1)} -> 0 | H56: {=_xll.EQNXTDZ($A$1,$B56,H$1,$B$1)} -> 0 | I56: {=_xll.EQNXTDZ($A$1,$B56,I$1,$B$1)} -> 0 | J56: {=_xll.EQNXTDZ($A$1,$B56,J$1,$B$1)} -> 0 | ... AF56: {=_xll.EQNXTDZ($A$1,$B56,AF$1,$B$1)} -> 0
A57: Borrowings | B57: FH_BORROWINGS | C57: {=_xll.EQNXTDZ($A$1,$B57,C$1,$B$1)} -> 0 | D57: {=_xll.EQNXTDZ($A$1,$B57,D$1,$B$1)} -> 0 | E57: {=_xll.EQNXTDZ($A$1,$B57,E$1,$B$1)} -> 0 | F57: {=_xll.EQNXTDZ($A$1,$B57,F$1,$B$1)} -> 0 | G57: {=_xll.EQNXTDZ($A$1,$B57,G$1,$B$1)} -> 0 | H57: {=_xll.EQNXTDZ($A$1,$B57,H$1,$B$1)} -> 0 | I57: {=_xll.EQNXTDZ($A$1,$B57,I$1,$B$1)} -> 0 | J57: {=_xll.EQNXTDZ($A$1,$B57,J$1,$B$1)} -> 0 | ... AF57: {=_xll.EQNXTDZ($A$1,$B57,AF$1,$B$1)} -> 0
A58: Month End | B58: BMONTH_MONTHEND | C58: {=_xll.EQNXTDZ($A$1,$B58,C$1,$B$1)} -> 0 | D58: {=_xll.EQNXTDZ($A$1,$B58,D$1,$B$1)} -> 0 | E58: {=_xll.EQNXTDZ($A$1,$B58,E$1,$B$1)} -> 0 | F58: {=_xll.EQNXTDZ($A$1,$B58,F$1,$B$1)} -> 0 | G58: {=_xll.EQNXTDZ($A$1,$B58,G$1,$B$1)} -> 0 | H58: {=_xll.EQNXTDZ($A$1,$B58,H$1,$B$1)} -> 0 | I58: {=_xll.EQNXTDZ($A$1,$B58,I$1,$B$1)} -> 0 | J58: {=_xll.EQNXTDZ($A$1,$B58,J$1,$B$1)} -> 0 | ... AF58: {=_xll.EQNXTDZ($A$1,$B58,AF$1,$B$1)} -> 0
A59: Close Price (Unit Curr.) | B59: FH_YEAR_PRICE | C59: {=_xll.EQNXTDZ($A$1,$B59,C$1,$B$1)} -> 0 | D59: {=_xll.EQNXTDZ($A$1,$B59,D$1,$B$1)} -> 0 | E59: {=_xll.EQNXTDZ($A$1,$B59,E$1,$B$1)} -> 0 | F59: {=_xll.EQNXTDZ($A$1,$B59,F$1,$B$1)} -> 0 | G59: {=_xll.EQNXTDZ($A$1,$B59,G$1,$B$1)} -> 0 | H59: {=_xll.EQNXTDZ($A$1,$B59,H$1,$B$1)} -> 0 | I59: {=_xll.EQNXTDZ($A$1,$B59,I$1,$B$1)} -> 0 | J59: {=_xll.EQNXTDZ($A$1,$B59,J$1,$B$1)} -> 0 | ... AF59: {=_xll.EQNXTDZ($A$1,$B59,AF$1,$B$1)} -> 0
A60: High Price (Unit Curr.) | B60: FH_HIGH | C60: {=_xll.EQNXTDZ($A$1,$B60,C$1,$B$1)} -> 0 | D60: {=_xll.EQNXTDZ($A$1,$B60,D$1,$B$1)} -> 0 | E60: {=_xll.EQNXTDZ($A$1,$B60,E$1,$B$1)} -> 0 | F60: {=_xll.EQNXTDZ($A$1,$B60,F$1,$B$1)} -> 0 | G60: {=_xll.EQNXTDZ($A$1,$B60,G$1,$B$1)} -> 0 | H60: {=_xll.EQNXTDZ($A$1,$B60,H$1,$B$1)} -> 0 | I60: {=_xll.EQNXTDZ($A$1,$B60,I$1,$B$1)} -> 0 | J60: {=_xll.EQNXTDZ($A$1,$B60,J$1,$B$1)} -> 0 | ... AF60: {=_xll.EQNXTDZ($A$1,$B60,AF$1,$B$1)} -> 0
A61: Low Price (Unit Curr.) | B61: FH_LOW | C61: {=_xll.EQNXTDZ($A$1,$B61,C$1,$B$1)} -> 0 | D61: {=_xll.EQNXTDZ($A$1,$B61,D$1,$B$1)} -> 0 | E61: {=_xll.EQNXTDZ($A$1,$B61,E$1,$B$1)} -> 0 | F61: {=_xll.EQNXTDZ($A$1,$B61,F$1,$B$1)} -> 0 | G61: {=_xll.EQNXTDZ($A$1,$B61,G$1,$B$1)} -> 0 | H61: {=_xll.EQNXTDZ($A$1,$B61,H$1,$B$1)} -> 0 | I61: {=_xll.EQNXTDZ($A$1,$B61,I$1,$B$1)} -> 0 | J61: {=_xll.EQNXTDZ($A$1,$B61,J$1,$B$1)} -> 0 | ... AF61: {=_xll.EQNXTDZ($A$1,$B61,AF$1,$B$1)} -> 0
A62: Month end date | B62: BMONTH_CLOSEDATE | C62: {=_xll.EQNXTDZ($A$1,$B62,C$1,$B$1)} -> 0 | D62: {=_xll.EQNXTDZ($A$1,$B62,D$1,$B$1)} -> 0 | E62: {=_xll.EQNXTDZ($A$1,$B62,E$1,$B$1)} -> 0 | F62: {=_xll.EQNXTDZ($A$1,$B62,F$1,$B$1)} -> 0 | G62: {=_xll.EQNXTDZ($A$1,$B62,G$1,$B$1)} -> 0 | H62: {=_xll.EQNXTDZ($A$1,$B62,H$1,$B$1)} -> 0 | I62: {=_xll.EQNXTDZ($A$1,$B62,I$1,$B$1)} -> 0 | J62: {=_xll.EQNXTDZ($A$1,$B62,J$1,$B$1)} -> 0 | ... AF62: {=_xll.EQNXTDZ($A$1,$B62,AF$1,$B$1)} -> 0
A63: Volume ('000) | B63: BMONTH_VOLUME | C63: {=_xll.EQNXTDZ($A$1,$B63,C$1,$B$1)} -> 0 | D63: {=_xll.EQNXTDZ($A$1,$B63,D$1,$B$1)} -> 0 | E63: {=_xll.EQNXTDZ($A$1,$B63,E$1,$B$1)} -> 0 | F63: {=_xll.EQNXTDZ($A$1,$B63,F$1,$B$1)} -> 0 | G63: {=_xll.EQNXTDZ($A$1,$B63,G$1,$B$1)} -> 0 | H63: {=_xll.EQNXTDZ($A$1,$B63,H$1,$B$1)} -> 0 | I63: {=_xll.EQNXTDZ($A$1,$B63,I$1,$B$1)} -> 0 | J63: {=_xll.EQNXTDZ($A$1,$B63,J$1,$B$1)} -> 0 | ... AF63: {=_xll.EQNXTDZ($A$1,$B63,AF$1,$B$1)} -> 0
... A68: NIM_Reported (%) | B68: RBI_NIMAR | C68: {=_xll.EQNXTDZ($A$1,$B68,C$1,$B$1)} -> 0 | D68: {=_xll.EQNXTDZ($A$1,$B68,D$1,$B$1)} -> 0 | E68: {=_xll.EQNXTDZ($A$1,$B68,E$1,$B$1)} -> 0 | F68: {=_xll.EQNXTDZ($A$1,$B68,F$1,$B$1)} -> 0 | G68: {=_xll.EQNXTDZ($A$1,$B68,G$1,$B$1)} -> 0 | H68: {=_xll.EQNXTDZ($A$1,$B68,H$1,$B$1)} -> 0 | I68: {=_xll.EQNXTDZ($A$1,$B68,I$1,$B$1)} -> 0 | J68: {=_xll.EQNXTDZ($A$1,$B68,J$1,$B$1)} -> 0 | ... AF68: {=_xll.EQNXTDZ($A$1,$B68,AF$1,$B$1)} -> 0
A70: Assets | C70: =+C85+C105+C107-C108-C109+C111+C112+C114+C115+C116+C117+C118+C120+C121+C122+C123+C124+C125+C126+C106+C113 -> 0 | D70: =+D85+D105+D107-D108-D109+D111+D112+D114+D115+D116+D117+D118+D120+D121+D122+D123+D124+D125+D126+D106+D113 -> 0 | E70: =+E85+E105+E107-E108-E109+E111+E112+E114+E115+E116+E117+E118+E120+E121+E122+E123+E124+E125+E126+E106+E113 -> 0 | F70: =+F85+F105+F107-F108-F109+F111+F112+F114+F115+F116+F117+F118+F120+F121+F122+F123+F124+F125+F126+F106+F113 -> 0 | G70: =+G85+G105+G107-G108-G109+G111+G112+G114+G115+G116+G117+G118+G120+G121+G122+G123+G124+G125+G126+G106+G113 -> 0 | H70: =+H85+H105+H107-H108-H109+H111+H112+H114+H115+H116+H117+H118+H120+H121+H122+H123+H124+H125+H126+H106+H113 -> 0 | I70: =+I85+I105+I107-I108-I109+I111+I112+I114+I115+I116+I117+I118+I120+I121+I122+I123+I124+I125+I126+I106+I113 -> 0 | J70: =+J85+J105+J107-J108-J109+J111+J112+J114+J115+J116+J117+J118+J120+J121+J122+J123+J124+J125+J126+J106+J113 -> 0 | ... AF70: =+AF85+AF105+AF107-AF108-AF109+AF111+AF112+AF114+AF115+AF116+AF117+AF118+AF120+AF121+AF122+AF123+AF124+AF125+AF126+AF106+AF113 -> 0
A71: Liab | C71: =+C77+C78+C79+C81+C82+C83+C84+C86+C87+C88+C89+C90+C91+C93+C94+C100+C101+C102 -> 0 | D71: =+D77+D78+D79+D81+D82+D83+D84+D86+D87+D88+D89+D90+D91+D93+D94+D100+D101+D102 -> 0 | E71: =+E77+E78+E79+E81+E82+E83+E84+E86+E87+E88+E89+E90+E91+E93+E94+E100+E101+E102 -> 0 | F71: =+F77+F78+F79+F81+F82+F83+F84+F86+F87+F88+F89+F90+F91+F93+F94+F100+F101+F102 -> 0 | G71: =+G77+G78+G79+G81+G82+G83+G84+G86+G87+G88+G89+G90+G91+G93+G94+G100+G101+G102 -> 0 | H71: =+H77+H78+H79+H81+H82+H83+H84+H86+H87+H88+H89+H90+H91+H93+H94+H100+H101+H102 -> 0 | I71: =+I77+I78+I79+I81+I82+I83+I84+I86+I87+I88+I89+I90+I91+I93+I94+I100+I101+I102 -> 0 | J71: =+J77+J78+J79+J81+J82+J83+J84+J86+J87+J88+J89+J90+J91+J93+J94+J100+J101+J102 -> 0 | ... AF71: =+AF77+AF78+AF79+AF81+AF82+AF83+AF84+AF86+AF87+AF88+AF89+AF90+AF91+AF93+AF94+AF100+AF101+AF102 -> 0
A72: Field Description | B72: Field Name
A73: Year End | B73: BBS_YEAR_END | C73: {=_xll.EQNXTDZ($A$1,$B73,C$1,$B$1)} -> 0 | D73: {=_xll.EQNXTDZ($A$1,$B73,D$1,$B$1)} -> 0 | E73: {=_xll.EQNXTDZ($A$1,$B73,E$1,$B$1)} -> 0 | F73: {=_xll.EQNXTDZ($A$1,$B73,F$1,$B$1)} -> 0 | G73: {=_xll.EQNXTDZ($A$1,$B73,G$1,$B$1)} -> 0 | H73: {=_xll.EQNXTDZ($A$1,$B73,H$1,$B$1)} -> 0 | I73: {=_xll.EQNXTDZ($A$1,$B73,I$1,$B$1)} -> 0 | J73: {=_xll.EQNXTDZ($A$1,$B73,J$1,$B$1)} -> 0 | ... AF73: {=_xll.EQNXTDZ($A$1,$B73,AF$1,$B$1)} -> 0
A74: Year | B74: BBS_YEAR | C74: {=_xll.EQNXTDZ($A$1,$B74,C$1,$B$1)} -> 0 | D74: {=_xll.EQNXTDZ($A$1,$B74,D$1,$B$1)} -> 0 | E74: {=_xll.EQNXTDZ($A$1,$B74,E$1,$B$1)} -> 0 | F74: {=_xll.EQNXTDZ($A$1,$B74,F$1,$B$1)} -> 0 | G74: {=_xll.EQNXTDZ($A$1,$B74,G$1,$B$1)} -> 0 | H74: {=_xll.EQNXTDZ($A$1,$B74,H$1,$B$1)} -> 0 | I74: {=_xll.EQNXTDZ($A$1,$B74,I$1,$B$1)} -> 0 | J74: {=_xll.EQNXTDZ($A$1,$B74,J$1,$B$1)} -> 0 | ... AF74: {=_xll.EQNXTDZ($A$1,$B74,AF$1,$B$1)} -> 0
A75: No of Months | B75: BBS_NO_MONTHS | C75: {=_xll.EQNXTDZ($A$1,$B75,C$1,$B$1)} -> 0 | D75: {=_xll.EQNXTDZ($A$1,$B75,D$1,$B$1)} -> 0 | E75: {=_xll.EQNXTDZ($A$1,$B75,E$1,$B$1)} -> 0 | F75: {=_xll.EQNXTDZ($A$1,$B75,F$1,$B$1)} -> 0 | G75: {=_xll.EQNXTDZ($A$1,$B75,G$1,$B$1)} -> 0 | H75: {=_xll.EQNXTDZ($A$1,$B75,H$1,$B$1)} -> 0 | I75: {=_xll.EQNXTDZ($A$1,$B75,I$1,$B$1)} -> 0 | J75: {=_xll.EQNXTDZ($A$1,$B75,J$1,$B$1)} -> 0 | ... AF75: {=_xll.EQNXTDZ($A$1,$B75,AF$1,$B$1)} -> 0
A76: Year end date | B76: BBS_YEAR_ENDDATE | C76: {=_xll.EQNXTDZ($A$1,$B76,C$1,$B$1)} -> 0 | D76: {=_xll.EQNXTDZ($A$1,$B76,D$1,$B$1)} -> 0 | E76: {=_xll.EQNXTDZ($A$1,$B76,E$1,$B$1)} -> 0 | F76: {=_xll.EQNXTDZ($A$1,$B76,F$1,$B$1)} -> 0 | G76: {=_xll.EQNXTDZ($A$1,$B76,G$1,$B$1)} -> 0 | H76: {=_xll.EQNXTDZ($A$1,$B76,H$1,$B$1)} -> 0 | I76: {=_xll.EQNXTDZ($A$1,$B76,I$1,$B$1)} -> 0 | J76: {=_xll.EQNXTDZ($A$1,$B76,J$1,$B$1)} -> 0 | ... AF76: {=_xll.EQNXTDZ($A$1,$B76,AF$1,$B$1)} -> 0
A77: Share Capital | B77: BS_SHARE_CAPITAL | C77: {=_xll.EQNXTDZ($A$1,$B77,C$1,$B$1)} -> 0 | D77: {=_xll.EQNXTDZ($A$1,$B77,D$1,$B$1)} -> 0 | E77: {=_xll.EQNXTDZ($A$1,$B77,E$1,$B$1)} -> 0 | F77: {=_xll.EQNXTDZ($A$1,$B77,F$1,$B$1)} -> 0 | G77: {=_xll.EQNXTDZ($A$1,$B77,G$1,$B$1)} -> 0 | H77: {=_xll.EQNXTDZ($A$1,$B77,H$1,$B$1)} -> 0 | I77: {=_xll.EQNXTDZ($A$1,$B77,I$1,$B$1)} -> 0 | J77: {=_xll.EQNXTDZ($A$1,$B77,J$1,$B$1)} -> 0 | ... AF77: {=_xll.EQNXTDZ($A$1,$B77,AF$1,$B$1)} -> 0
A78: Share Warrants & Outstandings | B78: BS_SHAREWROUTST | C78: {=_xll.EQNXTDZ($A$1,$B78,C$1,$B$1)} -> 0 | D78: {=_xll.EQNXTDZ($A$1,$B78,D$1,$B$1)} -> 0 | E78: {=_xll.EQNXTDZ($A$1,$B78,E$1,$B$1)} -> 0 | F78: {=_xll.EQNXTDZ($A$1,$B78,F$1,$B$1)} -> 0 | G78: {=_xll.EQNXTDZ($A$1,$B78,G$1,$B$1)} -> 0 | H78: {=_xll.EQNXTDZ($A$1,$B78,H$1,$B$1)} -> 0 | I78: {=_xll.EQNXTDZ($A$1,$B78,I$1,$B$1)} -> 0 | J78: {=_xll.EQNXTDZ($A$1,$B78,J$1,$B$1)} -> 0 | ... AF78: {=_xll.EQNXTDZ($A$1,$B78,AF$1,$B$1)} -> 0
A79: Total Reserves | B79: BS_RESERVE | C79: {=_xll.EQNXTDZ($A$1,$B79,C$1,$B$1)} -> 0 | D79: {=_xll.EQNXTDZ($A$1,$B79,D$1,$B$1)} -> 0 | E79: {=_xll.EQNXTDZ($A$1,$B79,E$1,$B$1)} -> 0 | F79: {=_xll.EQNXTDZ($A$1,$B79,F$1,$B$1)} -> 0 | G79: {=_xll.EQNXTDZ($A$1,$B79,G$1,$B$1)} -> 0 | H79: {=_xll.EQNXTDZ($A$1,$B79,H$1,$B$1)} -> 0 | I79: {=_xll.EQNXTDZ($A$1,$B79,I$1,$B$1)} -> 0 | J79: {=_xll.EQNXTDZ($A$1,$B79,J$1,$B$1)} -> 0 | ... AF79: {=_xll.EQNXTDZ($A$1,$B79,AF$1,$B$1)} -> 0
A80: Shareholder's Funds | B80: BS_SHAREHODERS_FUNDS | C80: {=_xll.EQNXTDZ($A$1,$B80,C$1,$B$1)} -> 0 | D80: {=_xll.EQNXTDZ($A$1,$B80,D$1,$B$1)} -> 0 | E80: {=_xll.EQNXTDZ($A$1,$B80,E$1,$B$1)} -> 0 | F80: {=_xll.EQNXTDZ($A$1,$B80,F$1,$B$1)} -> 0 | G80: {=_xll.EQNXTDZ($A$1,$B80,G$1,$B$1)} -> 0 | H80: {=_xll.EQNXTDZ($A$1,$B80,H$1,$B$1)} -> 0 | I80: {=_xll.EQNXTDZ($A$1,$B80,I$1,$B$1)} -> 0 | J80: {=_xll.EQNXTDZ($A$1,$B80,J$1,$B$1)} -> 0 | ... AF80: {=_xll.EQNXTDZ($A$1,$B80,AF$1,$B$1)} -> 0
A81: Minority Interest | B81: BS_MINORITY_INTEREST | C81: {=_xll.EQNXTDZ($A$1,$B81,C$1,$B$1)} -> 0 | D81: {=_xll.EQNXTDZ($A$1,$B81,D$1,$B$1)} -> 0 | E81: {=_xll.EQNXTDZ($A$1,$B81,E$1,$B$1)} -> 0 | F81: {=_xll.EQNXTDZ($A$1,$B81,F$1,$B$1)} -> 0 | G81: {=_xll.EQNXTDZ($A$1,$B81,G$1,$B$1)} -> 0 | H81: {=_xll.EQNXTDZ($A$1,$B81,H$1,$B$1)} -> 0 | I81: {=_xll.EQNXTDZ($A$1,$B81,I$1,$B$1)} -> 0 | J81: {=_xll.EQNXTDZ($A$1,$B81,J$1,$B$1)} -> 0 | ... AF81: {=_xll.EQNXTDZ($A$1,$B81,AF$1,$B$1)} -> 0
A82: Long-Term Borrowings | B82: BS_LTRM_BORROWING | C82: {=_xll.EQNXTDZ($A$1,$B82,C$1,$B$1)} -> 0 | D82: {=_xll.EQNXTDZ($A$1,$B82,D$1,$B$1)} -> 0 | E82: {=_xll.EQNXTDZ($A$1,$B82,E$1,$B$1)} -> 0 | F82: {=_xll.EQNXTDZ($A$1,$B82,F$1,$B$1)} -> 0 | G82: {=_xll.EQNXTDZ($A$1,$B82,G$1,$B$1)} -> 0 | H82: {=_xll.EQNXTDZ($A$1,$B82,H$1,$B$1)} -> 0 | I82: {=_xll.EQNXTDZ($A$1,$B82,I$1,$B$1)} -> 0 | J82: {=_xll.EQNXTDZ($A$1,$B82,J$1,$B$1)} -> 0 | ... AF82: {=_xll.EQNXTDZ($A$1,$B82,AF$1,$B$1)} -> 0
A83: Secured Loans | B83: BS_SECURED_LOANS | C83: {=_xll.EQNXTDZ($A$1,$B83,C$1,$B$1)} -> 0 | D83: {=_xll.EQNXTDZ($A$1,$B83,D$1,$B$1)} -> 0 | E83: {=_xll.EQNXTDZ($A$1,$B83,E$1,$B$1)} -> 0 | F83: {=_xll.EQNXTDZ($A$1,$B83,F$1,$B$1)} -> 0 | G83: {=_xll.EQNXTDZ($A$1,$B83,G$1,$B$1)} -> 0 | H83: {=_xll.EQNXTDZ($A$1,$B83,H$1,$B$1)} -> 0 | I83: {=_xll.EQNXTDZ($A$1,$B83,I$1,$B$1)} -> 0 | J83: {=_xll.EQNXTDZ($A$1,$B83,J$1,$B$1)} -> 0 | ... AF83: {=_xll.EQNXTDZ($A$1,$B83,AF$1,$B$1)} -> 0
A84: Unsecured Loans | B84: BS_UNSECURED_LOANS_NF | C84: {=_xll.EQNXTDZ($A$1,$B84,C$1,$B$1)} -> 0 | D84: {=_xll.EQNXTDZ($A$1,$B84,D$1,$B$1)} -> 0 | E84: {=_xll.EQNXTDZ($A$1,$B84,E$1,$B$1)} -> 0 | F84: {=_xll.EQNXTDZ($A$1,$B84,F$1,$B$1)} -> 0 | G84: {=_xll.EQNXTDZ($A$1,$B84,G$1,$B$1)} -> 0 | H84: {=_xll.EQNXTDZ($A$1,$B84,H$1,$B$1)} -> 0 | I84: {=_xll.EQNXTDZ($A$1,$B84,I$1,$B$1)} -> 0 | J84: {=_xll.EQNXTDZ($A$1,$B84,J$1,$B$1)} -> 0 | ... AF84: {=_xll.EQNXTDZ($A$1,$B84,AF$1,$B$1)} -> 0
... A153: NIM(%) | B153: BFR_NETINTERESTINCOME_TOTALFUNDS | C153: {=_xll.EQNXTDZ($A$1,$B153,C$1,$B$1)} -> 0 | D153: {=_xll.EQNXTDZ($A$1,$B153,D$1,$B$1)} -> 0 | E153: {=_xll.EQNXTDZ($A$1,$B153,E$1,$B$1)} -> 0 | F153: {=_xll.EQNXTDZ($A$1,$B153,F$1,$B$1)} -> 0 | G153: {=_xll.EQNXTDZ($A$1,$B153,G$1,$B$1)} -> 0 | H153: {=_xll.EQNXTDZ($A$1,$B153,H$1,$B$1)} -> 0 | I153: {=_xll.EQNXTDZ($A$1,$B153,I$1,$B$1)} -> 0 | J153: {=_xll.EQNXTDZ($A$1,$B153,J$1,$B$1)} -> 0 | ... AF153: {=_xll.EQNXTDZ($A$1,$B153,AF$1,$B$1)} -> 0

Sheet QTR Raw
A1: =+'Annual Raw'!A1 -> 0 | B1: X | C1: 201503 | D1: 201506 | E1: 201509 | F1: 201512 | G1: 201603 | H1: 201606 | I1: 201609 | J1: 201612 | K1: 201703 | L1: 201706 | M1: 201709 | N1: 201712 | O1: 201803 | P1: 201806 | Q1: 201809 | R1: 201812 | S1: 201903 | T1: 201906 | U1: 201909 | V1: 201912 | W1: 202003 | X1: 202006 | Y1: 202009 | Z1: 202012 | AA1: 202103 | AB1: 202106 | AC1: 202109 | AD1: 202112 | AE1: 202203 | AF1: 202206 | AG1: 202209 | AH1: 202212 | AI1: 202303 | AJ1: 202306 | AK1: 202309 | AL1: 202312 | AM1: 202403 | AN1: 202406 | AO1: 202409 | AP1: 202412 | AQ1: 202503 | AR1: 202506 | AS1: 202509 | AT1: 202512 | AU1: 202603 | AV1: 202606 | AW1: 202609 | AX1: 202612 | AY1: 202703 | AZ1: 202706 | BA1: 202709 | BB1: 202712 | BC1: 202803 | BD1: 202806 | BE1: 202809 | BF1: 202812 | BG1: 202903 | BH1: 202906 | BI1: 202909 | BJ1: 202912 | BK1: 203003
A4: Field Description | B4: Field Name
A5: Date End | B5: BQTR_DATE_END | C5: {=+_xll.EQNXTDZ($A$1,$B5,C$1,$B$1)} -> 0 | D5: {=+_xll.EQNXTDZ($A$1,$B5,D$1,$B$1)} -> 0 | E5: {=+_xll.EQNXTDZ($A$1,$B5,E$1,$B$1)} -> 0 | F5: {=+_xll.EQNXTDZ($A$1,$B5,F$1,$B$1)} -> 0 | G5: {=+_xll.EQNXTDZ($A$1,$B5,G$1,$B$1)} -> 0 | H5: {=+_xll.EQNXTDZ($A$1,$B5,H$1,$B$1)} -> 0 | I5: {=+_xll.EQNXTDZ($A$1,$B5,I$1,$B$1)} -> 0 | J5: {=+_xll.EQNXTDZ($A$1,$B5,J$1,$B$1)} -> 0 | ... BK5: {=+_xll.EQNXTDZ($A$1,$B5,BK$1,$B$1)} -> 0
A6: Field Description | B6: Field Name
A7: Date End | B7: QTR_DATE_END | C7: {=+_xll.EQNXTDZ($A$1,$B7,C$1,$B$1)} -> 0 | D7: {=+_xll.EQNXTDZ($A$1,$B7,D$1,$B$1)} -> 0 | E7: {=+_xll.EQNXTDZ($A$1,$B7,E$1,$B$1)} -> 0 | F7: {=+_xll.EQNXTDZ($A$1,$B7,F$1,$B$1)} -> 0 | G7: {=+_xll.EQNXTDZ($A$1,$B7,G$1,$B$1)} -> 0 | H7: {=+_xll.EQNXTDZ($A$1,$B7,H$1,$B$1)} -> 0 | I7: {=+_xll.EQNXTDZ($A$1,$B7,I$1,$B$1)} -> 0 | J7: {=+_xll.EQNXTDZ($A$1,$B7,J$1,$B$1)} -> 0 | ... BK7: {=+_xll.EQNXTDZ($A$1,$B7,BK$1,$B$1)} -> 0
A8: Gross Sales | B8: QTR_GROSS_SALE | C8: {=+_xll.EQNXTDZ($A$1,$B8,C$1,$B$1)} -> 0 | D8: {=+_xll.EQNXTDZ($A$1,$B8,D$1,$B$1)} -> 0 | E8: {=+_xll.EQNXTDZ($A$1,$B8,E$1,$B$1)} -> 0 | F8: {=+_xll.EQNXTDZ($A$1,$B8,F$1,$B$1)} -> 0 | G8: {=+_xll.EQNXTDZ($A$1,$B8,G$1,$B$1)} -> 0 | H8: {=+_xll.EQNXTDZ($A$1,$B8,H$1,$B$1)} -> 0 | I8: {=+_xll.EQNXTDZ($A$1,$B8,I$1,$B$1)} -> 0 | J8: {=+_xll.EQNXTDZ($A$1,$B8,J$1,$B$1)} -> 0 | ... BK8: {=+_xll.EQNXTDZ($A$1,$B8,BK$1,$B$1)} -> 0
A9: Net Sales | B9: QTR_OTHER_NETSALES | C9: {=+_xll.EQNXTDZ($A$1,$B9,C$1,$B$1)} -> 0 | D9: {=+_xll.EQNXTDZ($A$1,$B9,D$1,$B$1)} -> 0 | E9: {=+_xll.EQNXTDZ($A$1,$B9,E$1,$B$1)} -> 0 | F9: {=+_xll.EQNXTDZ($A$1,$B9,F$1,$B$1)} -> 0 | G9: {=+_xll.EQNXTDZ($A$1,$B9,G$1,$B$1)} -> 0 | H9: {=+_xll.EQNXTDZ($A$1,$B9,H$1,$B$1)} -> 0 | I9: {=+_xll.EQNXTDZ($A$1,$B9,I$1,$B$1)} -> 0 | J9: {=+_xll.EQNXTDZ($A$1,$B9,J$1,$B$1)} -> 0 | ... BK9: {=+_xll.EQNXTDZ($A$1,$B9,BK$1,$B$1)} -> 0
A10: Share of Associates | B10: QTR_SHARE_ASSOCIATE_REVENUE | C10: {=+_xll.EQNXTDZ($A$1,$B10,C$1,$B$1)} -> 0 | D10: {=+_xll.EQNXTDZ($A$1,$B10,D$1,$B$1)} -> 0 | E10: {=+_xll.EQNXTDZ($A$1,$B10,E$1,$B$1)} -> 0 | F10: {=+_xll.EQNXTDZ($A$1,$B10,F$1,$B$1)} -> 0 | G10: {=+_xll.EQNXTDZ($A$1,$B10,G$1,$B$1)} -> 0 | H10: {=+_xll.EQNXTDZ($A$1,$B10,H$1,$B$1)} -> 0 | I10: {=+_xll.EQNXTDZ($A$1,$B10,I$1,$B$1)} -> 0 | J10: {=+_xll.EQNXTDZ($A$1,$B10,J$1,$B$1)} -> 0 | ... BK10: {=+_xll.EQNXTDZ($A$1,$B10,BK$1,$B$1)} -> 0
A11: Other operating income | B11: QTR_JOB_WORKS | C11: {=+_xll.EQNXTDZ($A$1,$B11,C$1,$B$1)} -> 0 | D11: {=+_xll.EQNXTDZ($A$1,$B11,D$1,$B$1)} -> 0 | E11: {=+_xll.EQNXTDZ($A$1,$B11,E$1,$B$1)} -> 0 | F11: {=+_xll.EQNXTDZ($A$1,$B11,F$1,$B$1)} -> 0 | G11: {=+_xll.EQNXTDZ($A$1,$B11,G$1,$B$1)} -> 0 | H11: {=+_xll.EQNXTDZ($A$1,$B11,H$1,$B$1)} -> 0 | I11: {=+_xll.EQNXTDZ($A$1,$B11,I$1,$B$1)} -> 0 | J11: {=+_xll.EQNXTDZ($A$1,$B11,J$1,$B$1)} -> 0 | ... BK11: {=+_xll.EQNXTDZ($A$1,$B11,BK$1,$B$1)} -> 0
A12: Income on Investments | B12: QTR_INC_INV | C12: {=+_xll.EQNXTDZ($A$1,$B12,C$1,$B$1)} -> 0 | D12: {=+_xll.EQNXTDZ($A$1,$B12,D$1,$B$1)} -> 0 | E12: {=+_xll.EQNXTDZ($A$1,$B12,E$1,$B$1)} -> 0 | F12: {=+_xll.EQNXTDZ($A$1,$B12,F$1,$B$1)} -> 0 | G12: {=+_xll.EQNXTDZ($A$1,$B12,G$1,$B$1)} -> 0 | H12: {=+_xll.EQNXTDZ($A$1,$B12,H$1,$B$1)} -> 0 | I12: {=+_xll.EQNXTDZ($A$1,$B12,I$1,$B$1)} -> 0 | J12: {=+_xll.EQNXTDZ($A$1,$B12,J$1,$B$1)} -> 0 | ... BK12: {=+_xll.EQNXTDZ($A$1,$B12,BK$1,$B$1)} -> 0
A13: Net Sales & Other Operating Income | B13: QTR_NET_SALES | C13: {=+_xll.EQNXTDZ($A$1,$B13,C$1,$B$1)} -> 0 | D13: {=+_xll.EQNXTDZ($A$1,$B13,D$1,$B$1)} -> 0 | E13: {=+_xll.EQNXTDZ($A$1,$B13,E$1,$B$1)} -> 0 | F13: {=+_xll.EQNXTDZ($A$1,$B13,F$1,$B$1)} -> 0 | G13: {=+_xll.EQNXTDZ($A$1,$B13,G$1,$B$1)} -> 0 | H13: {=+_xll.EQNXTDZ($A$1,$B13,H$1,$B$1)} -> 0 | I13: {=+_xll.EQNXTDZ($A$1,$B13,I$1,$B$1)} -> 0 | J13: {=+_xll.EQNXTDZ($A$1,$B13,J$1,$B$1)} -> 0 | ... BK13: {=+_xll.EQNXTDZ($A$1,$B13,BK$1,$B$1)} -> 0
A14: Interest Expended | B14: QTR_INTEREST_EX | C14: {=+_xll.EQNXTDZ($A$1,$B14,C$1,$B$1)} -> 0 | D14: {=+_xll.EQNXTDZ($A$1,$B14,D$1,$B$1)} -> 0 | E14: {=+_xll.EQNXTDZ($A$1,$B14,E$1,$B$1)} -> 0 | F14: {=+_xll.EQNXTDZ($A$1,$B14,F$1,$B$1)} -> 0 | G14: {=+_xll.EQNXTDZ($A$1,$B14,G$1,$B$1)} -> 0 | H14: {=+_xll.EQNXTDZ($A$1,$B14,H$1,$B$1)} -> 0 | I14: {=+_xll.EQNXTDZ($A$1,$B14,I$1,$B$1)} -> 0 | J14: {=+_xll.EQNXTDZ($A$1,$B14,J$1,$B$1)} -> 0 | ... BK14: {=+_xll.EQNXTDZ($A$1,$B14,BK$1,$B$1)} -> 0
A15: Operating & Manufacturing Expenses | B15: QTR_MFG_EXPS | C15: {=+_xll.EQNXTDZ($A$1,$B15,C$1,$B$1)} -> 0 | D15: {=+_xll.EQNXTDZ($A$1,$B15,D$1,$B$1)} -> 0 | E15: {=+_xll.EQNXTDZ($A$1,$B15,E$1,$B$1)} -> 0 | F15: {=+_xll.EQNXTDZ($A$1,$B15,F$1,$B$1)} -> 0 | G15: {=+_xll.EQNXTDZ($A$1,$B15,G$1,$B$1)} -> 0 | H15: {=+_xll.EQNXTDZ($A$1,$B15,H$1,$B$1)} -> 0 | I15: {=+_xll.EQNXTDZ($A$1,$B15,I$1,$B$1)} -> 0 | J15: {=+_xll.EQNXTDZ($A$1,$B15,J$1,$B$1)} -> 0 | ... BK15: {=+_xll.EQNXTDZ($A$1,$B15,BK$1,$B$1)} -> 0
A16: (Increase) / Decrease In Stocks | B16: QTR_INC_DEC_INVENTORY | C16: {=+_xll.EQNXTDZ($A$1,$B16,C$1,$B$1)} -> 0 | D16: {=+_xll.EQNXTDZ($A$1,$B16,D$1,$B$1)} -> 0 | E16: {=+_xll.EQNXTDZ($A$1,$B16,E$1,$B$1)} -> 0 | F16: {=+_xll.EQNXTDZ($A$1,$B16,F$1,$B$1)} -> 0 | G16: {=+_xll.EQNXTDZ($A$1,$B16,G$1,$B$1)} -> 0 | H16: {=+_xll.EQNXTDZ($A$1,$B16,H$1,$B$1)} -> 0 | I16: {=+_xll.EQNXTDZ($A$1,$B16,I$1,$B$1)} -> 0 | J16: {=+_xll.EQNXTDZ($A$1,$B16,J$1,$B$1)} -> 0 | ... BK16: {=+_xll.EQNXTDZ($A$1,$B16,BK$1,$B$1)} -> 0
A17: Cost of Services & Raw Materials | B17: QTR_RAW_MATERIAL_COST | C17: {=+_xll.EQNXTDZ($A$1,$B17,C$1,$B$1)} -> 0 | D17: {=+_xll.EQNXTDZ($A$1,$B17,D$1,$B$1)} -> 0 | E17: {=+_xll.EQNXTDZ($A$1,$B17,E$1,$B$1)} -> 0 | F17: {=+_xll.EQNXTDZ($A$1,$B17,F$1,$B$1)} -> 0 | G17: {=+_xll.EQNXTDZ($A$1,$B17,G$1,$B$1)} -> 0 | H17: {=+_xll.EQNXTDZ($A$1,$B17,H$1,$B$1)} -> 0 | I17: {=+_xll.EQNXTDZ($A$1,$B17,I$1,$B$1)} -> 0 | J17: {=+_xll.EQNXTDZ($A$1,$B17,J$1,$B$1)} -> 0 | ... BK17: {=+_xll.EQNXTDZ($A$1,$B17,BK$1,$B$1)} -> 0
A18: Purchase of Finished Goods | B18: QTR_PURCHASE_FIN_GOOD | C18: {=+_xll.EQNXTDZ($A$1,$B18,C$1,$B$1)} -> 0 | D18: {=+_xll.EQNXTDZ($A$1,$B18,D$1,$B$1)} -> 0 | E18: {=+_xll.EQNXTDZ($A$1,$B18,E$1,$B$1)} -> 0 | F18: {=+_xll.EQNXTDZ($A$1,$B18,F$1,$B$1)} -> 0 | G18: {=+_xll.EQNXTDZ($A$1,$B18,G$1,$B$1)} -> 0 | H18: {=+_xll.EQNXTDZ($A$1,$B18,H$1,$B$1)} -> 0 | I18: {=+_xll.EQNXTDZ($A$1,$B18,I$1,$B$1)} -> 0 | J18: {=+_xll.EQNXTDZ($A$1,$B18,J$1,$B$1)} -> 0 | ... BK18: {=+_xll.EQNXTDZ($A$1,$B18,BK$1,$B$1)} -> 0
... A47: Face Value | B47: QTR_FV | C47: {=+_xll.EQNXTDZ($A$1,$B47,C$1,$B$1)} -> 0 | D47: {=+_xll.EQNXTDZ($A$1,$B47,D$1,$B$1)} -> 0 | E47: {=+_xll.EQNXTDZ($A$1,$B47,E$1,$B$1)} -> 0 | F47: {=+_xll.EQNXTDZ($A$1,$B47,F$1,$B$1)} -> 0 | G47: {=+_xll.EQNXTDZ($A$1,$B47,G$1,$B$1)} -> 0 | H47: {=+_xll.EQNXTDZ($A$1,$B47,H$1,$B$1)} -> 0 | I47: {=+_xll.EQNXTDZ($A$1,$B47,I$1,$B$1)} -> 0 | J47: {=+_xll.EQNXTDZ($A$1,$B47,J$1,$B$1)} -> 0 | ... BK47: {=+_xll.EQNXTDZ($A$1,$B47,BK$1,$B$1)} -> 0
A50: Field Description | B50: Field Name
A51: Equity Paid Up | B51: QTR_EQUITY_CAP | C51: {=+_xll.EQNXTDZ($A$1,$B51,C$1,$B$1)} -> 0 | D51: {=+_xll.EQNXTDZ($A$1,$B51,D$1,$B$1)} -> 0 | E51: {=+_xll.EQNXTDZ($A$1,$B51,E$1,$B$1)} -> 0 | F51: {=+_xll.EQNXTDZ($A$1,$B51,F$1,$B$1)} -> 0 | G51: {=+_xll.EQNXTDZ($A$1,$B51,G$1,$B$1)} -> 0 | H51: {=+_xll.EQNXTDZ($A$1,$B51,H$1,$B$1)} -> 0 | I51: {=+_xll.EQNXTDZ($A$1,$B51,I$1,$B$1)} -> 0 | J51: {=+_xll.EQNXTDZ($A$1,$B51,J$1,$B$1)} -> 0 | ... BK51: {=+_xll.EQNXTDZ($A$1,$B51,BK$1,$B$1)} -> 0
A52: Face value | B52: QTR_FV | C52: {=+_xll.EQNXTDZ($A$1,$B52,C$1,$B$1)} -> 0 | D52: {=+_xll.EQNXTDZ($A$1,$B52,D$1,$B$1)} -> 0 | E52: {=+_xll.EQNXTDZ($A$1,$B52,E$1,$B$1)} -> 0 | F52: {=+_xll.EQNXTDZ($A$1,$B52,F$1,$B$1)} -> 0 | G52: {=+_xll.EQNXTDZ($A$1,$B52,G$1,$B$1)} -> 0 | H52: {=+_xll.EQNXTDZ($A$1,$B52,H$1,$B$1)} -> 0 | I52: {=+_xll.EQNXTDZ($A$1,$B52,I$1,$B$1)} -> 0 | J52: {=+_xll.EQNXTDZ($A$1,$B52,J$1,$B$1)} -> 0 | ... BK52: {=+_xll.EQNXTDZ($A$1,$B52,BK$1,$B$1)} -> 0
A55: Share Capital | B55: QTRB_SHARE_CAPITAL | C55: {=+_xll.EQNXTDZ($A$1,$B55,C$1,$B$1)} -> 0 | D55: {=+_xll.EQNXTDZ($A$1,$B55,D$1,$B$1)} -> 0 | E55: {=+_xll.EQNXTDZ($A$1,$B55,E$1,$B$1)} -> 0 | F55: {=+_xll.EQNXTDZ($A$1,$B55,F$1,$B$1)} -> 0 | G55: {=+_xll.EQNXTDZ($A$1,$B55,G$1,$B$1)} -> 0 | H55: {=+_xll.EQNXTDZ($A$1,$B55,H$1,$B$1)} -> 0 | I55: {=+_xll.EQNXTDZ($A$1,$B55,I$1,$B$1)} -> 0 | J55: {=+_xll.EQNXTDZ($A$1,$B55,J$1,$B$1)} -> 0 | ... BK55: {=+_xll.EQNXTDZ($A$1,$B55,BK$1,$B$1)} -> 0
A56: Share Warrants & outstandings | B56: QTRB_SHAREWARNDOUT | C56: {=+_xll.EQNXTDZ($A$1,$B56,C$1,$B$1)} -> 0 | D56: {=+_xll.EQNXTDZ($A$1,$B56,D$1,$B$1)} -> 0 | E56: {=+_xll.EQNXTDZ($A$1,$B56,E$1,$B$1)} -> 0 | F56: {=+_xll.EQNXTDZ($A$1,$B56,F$1,$B$1)} -> 0 | G56: {=+_xll.EQNXTDZ($A$1,$B56,G$1,$B$1)} -> 0 | H56: {=+_xll.EQNXTDZ($A$1,$B56,H$1,$B$1)} -> 0 | I56: {=+_xll.EQNXTDZ($A$1,$B56,I$1,$B$1)} -> 0 | J56: {=+_xll.EQNXTDZ($A$1,$B56,J$1,$B$1)} -> 0 | ... BK56: {=+_xll.EQNXTDZ($A$1,$B56,BK$1,$B$1)} -> 0
A57: Reserves & Surplus | B57: QTRB_RESERVE | C57: {=+_xll.EQNXTDZ($A$1,$B57,C$1,$B$1)} -> 0 | D57: {=+_xll.EQNXTDZ($A$1,$B57,D$1,$B$1)} -> 0 | E57: {=+_xll.EQNXTDZ($A$1,$B57,E$1,$B$1)} -> 0 | F57: {=+_xll.EQNXTDZ($A$1,$B57,F$1,$B$1)} -> 0 | G57: {=+_xll.EQNXTDZ($A$1,$B57,G$1,$B$1)} -> 0 | H57: {=+_xll.EQNXTDZ($A$1,$B57,H$1,$B$1)} -> 0 | I57: {=+_xll.EQNXTDZ($A$1,$B57,I$1,$B$1)} -> 0 | J57: {=+_xll.EQNXTDZ($A$1,$B57,J$1,$B$1)} -> 0 | ... BK57: {=+_xll.EQNXTDZ($A$1,$B57,BK$1,$B$1)} -> 0
A58: Shareholder's Funds | B58: QTRB_SHAREHODERS_FUNDS | C58: {=+_xll.EQNXTDZ($A$1,$B58,C$1,$B$1)} -> 0 | D58: {=+_xll.EQNXTDZ($A$1,$B58,D$1,$B$1)} -> 0 | E58: {=+_xll.EQNXTDZ($A$1,$B58,E$1,$B$1)} -> 0 | F58: {=+_xll.EQNXTDZ($A$1,$B58,F$1,$B$1)} -> 0 | G58: {=+_xll.EQNXTDZ($A$1,$B58,G$1,$B$1)} -> 0 | H58: {=+_xll.EQNXTDZ($A$1,$B58,H$1,$B$1)} -> 0 | I58: {=+_xll.EQNXTDZ($A$1,$B58,I$1,$B$1)} -> 0 | J58: {=+_xll.EQNXTDZ($A$1,$B58,J$1,$B$1)} -> 0 | ... BK58: {=+_xll.EQNXTDZ($A$1,$B58,BK$1,$B$1)} -> 0
A59: Minority Interest | B59: QTRB_MINORITY_INTEREST_BS | C59: {=+_xll.EQNXTDZ($A$1,$B59,C$1,$B$1)} -> 0 | D59: {=+_xll.EQNXTDZ($A$1,$B59,D$1,$B$1)} -> 0 | E59: {=+_xll.EQNXTDZ($A$1,$B59,E$1,$B$1)} -> 0 | F59: {=+_xll.EQNXTDZ($A$1,$B59,F$1,$B$1)} -> 0 | G59: {=+_xll.EQNXTDZ($A$1,$B59,G$1,$B$1)} -> 0 | H59: {=+_xll.EQNXTDZ($A$1,$B59,H$1,$B$1)} -> 0 | I59: {=+_xll.EQNXTDZ($A$1,$B59,I$1,$B$1)} -> 0 | J59: {=+_xll.EQNXTDZ($A$1,$B59,J$1,$B$1)} -> 0 | ... BK59: {=+_xll.EQNXTDZ($A$1,$B59,BK$1,$B$1)} -> 0
A60: Long Term Borrowings | B60: QTRB_TOTAL_DEBTS | C60: {=+_xll.EQNXTDZ($A$1,$B60,C$1,$B$1)} -> 0 | D60: {=+_xll.EQNXTDZ($A$1,$B60,D$1,$B$1)} -> 0 | E60: {=+_xll.EQNXTDZ($A$1,$B60,E$1,$B$1)} -> 0 | F60: {=+_xll.EQNXTDZ($A$1,$B60,F$1,$B$1)} -> 0 | G60: {=+_xll.EQNXTDZ($A$1,$B60,G$1,$B$1)} -> 0 | H60: {=+_xll.EQNXTDZ($A$1,$B60,H$1,$B$1)} -> 0 | I60: {=+_xll.EQNXTDZ($A$1,$B60,I$1,$B$1)} -> 0 | J60: {=+_xll.EQNXTDZ($A$1,$B60,J$1,$B$1)} -> 0 | ... BK60: {=+_xll.EQNXTDZ($A$1,$B60,BK$1,$B$1)} -> 0
A61: Secured Loans | B61: QTRB_SECURED_LOANS | C61: {=+_xll.EQNXTDZ($A$1,$B61,C$1,$B$1)} -> 0 | D61: {=+_xll.EQNXTDZ($A$1,$B61,D$1,$B$1)} -> 0 | E61: {=+_xll.EQNXTDZ($A$1,$B61,E$1,$B$1)} -> 0 | F61: {=+_xll.EQNXTDZ($A$1,$B61,F$1,$B$1)} -> 0 | G61: {=+_xll.EQNXTDZ($A$1,$B61,G$1,$B$1)} -> 0 | H61: {=+_xll.EQNXTDZ($A$1,$B61,H$1,$B$1)} -> 0 | I61: {=+_xll.EQNXTDZ($A$1,$B61,I$1,$B$1)} -> 0 | J61: {=+_xll.EQNXTDZ($A$1,$B61,J$1,$B$1)} -> 0 | ... BK61: {=+_xll.EQNXTDZ($A$1,$B61,BK$1,$B$1)} -> 0
A62: Unsecured Loans | B62: QTRB_UNSECURED_LOANS_NF | C62: {=+_xll.EQNXTDZ($A$1,$B62,C$1,$B$1)} -> 0 | D62: {=+_xll.EQNXTDZ($A$1,$B62,D$1,$B$1)} -> 0 | E62: {=+_xll.EQNXTDZ($A$1,$B62,E$1,$B$1)} -> 0 | F62: {=+_xll.EQNXTDZ($A$1,$B62,F$1,$B$1)} -> 0 | G62: {=+_xll.EQNXTDZ($A$1,$B62,G$1,$B$1)} -> 0 | H62: {=+_xll.EQNXTDZ($A$1,$B62,H$1,$B$1)} -> 0 | I62: {=+_xll.EQNXTDZ($A$1,$B62,I$1,$B$1)} -> 0 | J62: {=+_xll.EQNXTDZ($A$1,$B62,J$1,$B$1)} -> 0 | ... BK62: {=+_xll.EQNXTDZ($A$1,$B62,BK$1,$B$1)} -> 0
A63: Other Long Term Liabilities | B63: QTRB_OTHER_LT_LIABILITIES | C63: {=+_xll.EQNXTDZ($A$1,$B63,C$1,$B$1)} -> 0 | D63: {=+_xll.EQNXTDZ($A$1,$B63,D$1,$B$1)} -> 0 | E63: {=+_xll.EQNXTDZ($A$1,$B63,E$1,$B$1)} -> 0 | F63: {=+_xll.EQNXTDZ($A$1,$B63,F$1,$B$1)} -> 0 | G63: {=+_xll.EQNXTDZ($A$1,$B63,G$1,$B$1)} -> 0 | H63: {=+_xll.EQNXTDZ($A$1,$B63,H$1,$B$1)} -> 0 | I63: {=+_xll.EQNXTDZ($A$1,$B63,I$1,$B$1)} -> 0 | J63: {=+_xll.EQNXTDZ($A$1,$B63,J$1,$B$1)} -> 0 | ... BK63: {=+_xll.EQNXTDZ($A$1,$B63,BK$1,$B$1)} -> 0
A64: Long Term Trade Payables | B64: QTRB_LT_TRADE_PAYABLE | C64: {=+_xll.EQNXTDZ($A$1,$B64,C$1,$B$1)} -> 0 | D64: {=+_xll.EQNXTDZ($A$1,$B64,D$1,$B$1)} -> 0 | E64: {=+_xll.EQNXTDZ($A$1,$B64,E$1,$B$1)} -> 0 | F64: {=+_xll.EQNXTDZ($A$1,$B64,F$1,$B$1)} -> 0 | G64: {=+_xll.EQNXTDZ($A$1,$B64,G$1,$B$1)} -> 0 | H64: {=+_xll.EQNXTDZ($A$1,$B64,H$1,$B$1)} -> 0 | I64: {=+_xll.EQNXTDZ($A$1,$B64,I$1,$B$1)} -> 0 | J64: {=+_xll.EQNXTDZ($A$1,$B64,J$1,$B$1)} -> 0 | ... BK64: {=+_xll.EQNXTDZ($A$1,$B64,BK$1,$B$1)} -> 0
... A99: Book Value | B99: QTRB_BOOKVALUE | C99: {=+_xll.EQNXTDZ($A$1,$B99,C$1,$B$1)} -> 0 | D99: {=+_xll.EQNXTDZ($A$1,$B99,D$1,$B$1)} -> 0 | E99: {=+_xll.EQNXTDZ($A$1,$B99,E$1,$B$1)} -> 0 | F99: {=+_xll.EQNXTDZ($A$1,$B99,F$1,$B$1)} -> 0 | G99: {=+_xll.EQNXTDZ($A$1,$B99,G$1,$B$1)} -> 0 | H99: {=+_xll.EQNXTDZ($A$1,$B99,H$1,$B$1)} -> 0 | I99: {=+_xll.EQNXTDZ($A$1,$B99,I$1,$B$1)} -> 0 | J99: {=+_xll.EQNXTDZ($A$1,$B99,J$1,$B$1)} -> 0 | ... BK99: {=+_xll.EQNXTDZ($A$1,$B99,BK$1,$B$1)} -> 0
A105: Field Description | B105: Field Name
A106: Debt Securities | B106: QTRBIND_DEBT_SECURITIES

Sheet QTR Share Price
A1: =+'Annual Raw'!A1 -> 0 | C1: 201206 | D1: 201207 | E1: 201208 | F1: 201209 | G1: 201210 | H1: 201211 | I1: 201212 | J1: 201301 | K1: 201302 | L1: 201303 | M1: 201304 | N1: 201305 | O1: 201306 | P1: 201307 | Q1: 201308 | R1: 201309 | S1: 201310 | T1: 201311 | U1: 201312 | V1: 201401 | W1: 201402 | X1: 201403 | Y1: 201404 | Z1: 201405 | AA1: 201406 | AB1: 201407 | AC1: 201408 | AD1: 201409 | AE1: 201410 | AF1: 201411 | AG1: 201412 | AH1: 201501 | AI1: 201502 | AJ1: 201503 | AK1: 201504 | AL1: 201505 | AM1: 201506 | AN1: 201507 | AO1: 201508 | AP1: 201509 | AQ1: 201510 | AR1: 201511 | AS1: 201512 | AT1: 201601 | AU1: 201602 | AV1: 201603 | AW1: 201604 | AX1: 201605 | AY1: 201606 | AZ1: 201607 | BA1: 201608 | BB1: 201609 | BC1: 201610 | BD1: 201611 | BE1: 201612 | BF1: 201701 | BG1: 201702 | BH1: 201703 | BI1: 201704 | BJ1: 201705 | BK1: 201706 | BL1: 201707 | BM1: 201708 | BN1: 201709 | BO1: 201710 | BP1: 201711 | BQ1: 201712 | BR1: 201801 | BS1: 201802 | BT1: 201803 | BU1: 201804 | BV1: 201805 | BW1: 201806 | BX1: 201807 | BY1: 201808 | BZ1: 201809 | CA1: 201810 | CB1: 201811 | CC1: 201812 | CD1: 201901 | CE1: 201902 | CF1: 201903 | CG1: 201904 | CH1: 201905 | CI1: 201906 | CJ1: 201907 | CK1: 201908 | CL1: 201909 | CM1: 201910 | CN1: 201911 | CO1: 201912 | CP1: 202001 | CQ1: 202002 | CR1: 202003 | CS1: 202004 | CT1: 202005 | CU1: 202006 | CV1: 202007 | CW1: 202008 | CX1: 202009 | CY1: 202010 | CZ1: 202011 | DA1: 202012 | DB1: 202101 | DC1: 202102 | DD1: 202103 | DE1: 202104 | DF1: 202105 | DG1: 202106 | DH1: 202107 | DI1: 202108 | DJ1: 202109 | DK1: 202110 | DL1: 202111 | DM1: 202112 | DN1: 202201 | DO1: 202202 | DP1: 202203 | DQ1: 202204 | DR1: 202205 | DS1: 202206 | DT1: 202207 | DU1: 202208 | DV1: 202209 | DW1: 202210 | DX1: 202211 | DY1: 202212 | DZ1: 202301 | EA1: 202302 | EB1: 202303 | EC1: 202304 | ED1: 202305 | EE1: 202306 | EF1: 202307 | EG1: 202308 | EH1: 202309 | EI1: 202310 | EJ1: 202311 | EK1: 202312 | EL1: 202401 | EM1: 202402 | EN1: 202403 | EO1: 202404 | EP1: 202405 | EQ1: 202406 | ER1: 202407 | ES1: 202408 | ET1: 202409 | EU1: 202410 | EV1: 202411 | EW1: 202412 | EX1: 202501 | EY1: 202502 | EZ1: 202503 | FA1: 202504 | FB1: 202505 | FC1: 202506 | FD1: 202507 | FE1: 202508 | FF1: 202509 | FG1: 202510 | FH1: 202511 | FI1: 202512 | FJ1: 202601 | FK1: 202602 | FL1: 202603 | FM1: 202604 | FN1: 202605 | FO1: 202606 | FP1: 202607 | FQ1: 202608 | FR1: 202609 | FS1: 202610 | FT1: 202611 | FU1: 202612 | FV1: 202701 | FW1: 202702 | FX1: 202703 | FY1: 202704 | FZ1: 202705 | GA1: 202706 | GB1: 202707 | GC1: 202708 | GD1: 202709 | GE1: 202710 | GF1: 202711 | GG1: 202712 | GH1: 202801 | GI1: 202802 | GJ1: 202803 | GK1: 202804 | GL1: 202805 | GM1: 202806 | GN1: 202807 | GO1: 202808 | GP1: 202809 | GQ1: 202810 | GR1: 202811 | GS1: 202812 | GT1: 202901 | GU1: 202902 | GV1: 202903 | GW1: 202904 | GX1: 202905 | GY1: 202906 | GZ1: 202907 | HA1: 202908 | HB1: 202909 | HC1: 202910 | HD1: 202911 | HE1: 202912 | HF1: 203001 | HG1: 203002 | HH1: 203003 | HM1: 201206 | HN1: 201207 | HO1: 201208 | HP1: 201209 | HQ1: 201212 | HR1: 201303 | HS1: 201306 | HT1: 201309 | HU1: 201312 | HV1: 201403 | HW1: 201406 | HX1: 201409 | HY1: 201412 | HZ1: 201503 | IA1: 201506 | IB1: 201509 | IC1: 201512 | ID1: 201603 | IE1: 201606 | IF1: 201609 | IG1: 201612 | IH1: 201703 | II1: 201706 | IJ1: 201709 | IK1: 201712 | IL1: 201803 | IM1: 201806 | IN1: 201809 | IO1: 201812 | IP1: 201903 | IQ1: 201906 | IR1: 201909 | IS1: 201912 | IT1: 202003 | IU1: 202006 | IV1: 202009 | IW1: 202012 | IX1: 202103 | IY1: 202106 | IZ1: 202109 | JA1: 202112 | JB1: 202203 | JC1: 202206 | JD1: 202209 | JE1: 202212 | JF1: 202303 | JG1: 202306 | JH1: 202309 | JI1: 202312 | JJ1: 202403 | JK1: 202406 | JL1: 202409 | JM1: 202412 | JN1: 202503 | JO1: 202506 | JP1: 202509 | JQ1: 202512 | JR1: 202603 | JS1: 202606 | JT1: 202609 | JU1: 202612 | JV1: 202703 | JW1: 202706 | JX1: 202709 | JY1: 202712 | JZ1: 202803 | KA1: 202806 | KB1: 202809 | KC1: 202812 | KD1: 202903 | KE1: 202906 | KF1: 202909 | KG1: 202912 | KH1: 203003
A4: Field Description | B4: Field Name
A5: MonthEnd | B5: NMONTH_MONTHEND | C5: {=_xll.EQNXTDZ($A$1,$B5,C$1)} -> 0 | D5: {=_xll.EQNXTDZ($A$1,$B5,D$1)} -> 0 | E5: {=_xll.EQNXTDZ($A$1,$B5,E$1)} -> 0 | F5: {=_xll.EQNXTDZ($A$1,$B5,F$1)} -> 0 | G5: {=_xll.EQNXTDZ($A$1,$B5,G$1)} -> 0 | H5: {=_xll.EQNXTDZ($A$1,$B5,H$1)} -> 0 | I5: {=_xll.EQNXTDZ($A$1,$B5,I$1)} -> 0 | J5: {=_xll.EQNXTDZ($A$1,$B5,J$1)} -> 0 | ... HH5: {=_xll.EQNXTDZ($A$1,$B5,HH$1)} -> 0
A6: Open | B6: NMONTH_OPEN | C6: {=_xll.EQNXTDZ($A$1,$B6,C$1)} -> 0 | D6: {=_xll.EQNXTDZ($A$1,$B6,D$1)} -> 0 | E6: {=_xll.EQNXTDZ($A$1,$B6,E$1)} -> 0 | F6: {=_xll.EQNXTDZ($A$1,$B6,F$1)} -> 0 | G6: {=_xll.EQNXTDZ($A$1,$B6,G$1)} -> 0 | H6: {=_xll.EQNXTDZ($A$1,$B6,H$1)} -> 0 | I6: {=_xll.EQNXTDZ($A$1,$B6,I$1)} -> 0 | J6: {=_xll.EQNXTDZ($A$1,$B6,J$1)} -> 0 | ... HH6: {=_xll.EQNXTDZ($A$1,$B6,HH$1)} -> 0
A7: High | B7: NMONTH_HIGH | C7: {=_xll.EQNXTDZ($A$1,$B7,C$1)} -> 0 | D7: {=_xll.EQNXTDZ($A$1,$B7,D$1)} -> 0 | E7: {=_xll.EQNXTDZ($A$1,$B7,E$1)} -> 0 | F7: {=_xll.EQNXTDZ($A$1,$B7,F$1)} -> 0 | G7: {=_xll.EQNXTDZ($A$1,$B7,G$1)} -> 0 | H7: {=_xll.EQNXTDZ($A$1,$B7,H$1)} -> 0 | I7: {=_xll.EQNXTDZ($A$1,$B7,I$1)} -> 0 | J7: {=_xll.EQNXTDZ($A$1,$B7,J$1)} -> 0 | ... HH7: {=_xll.EQNXTDZ($A$1,$B7,HH$1)} -> 0 | HP7: =+MAX(D7:F7) -> 0 | HQ7: =+MAX(G7:I7) -> 0 | HR7: =+MAX(J7:L7) -> 0 | HS7: =+MAX(M7:O7) -> 0 | HT7: =+MAX(P7:R7) -> 0 | HU7: =+MAX(S7:U7) -> 0 | HV7: =+MAX(V7:X7) -> 0 | HW7: =+MAX(Y7:AA7) -> 0 | HX7: =+MAX(AB7:AD7) -> 0 | HY7: =+MAX(AE7:AG7) -> 0 | HZ7: =+MAX(AH7:AJ7) -> 0 | IA7: =+MAX(AK7:AM7) -> 0 | IB7: =+MAX(AN7:AP7) -> 0 | IC7: =+MAX(AQ7:AS7) -> 0 | ID7: =+MAX(AT7:AV7) -> 0 | IE7: =+MAX(AW7:AY7) -> 0 | IF7: =+MAX(AZ7:BB7) -> 0 | IG7: =+MAX(BC7:BE7) -> 0 | IH7: =+MAX(BF7:BH7) -> 0 | II7: =+MAX(BI7:BK7) -> 0 | IJ7: =+MAX(BL7:BN7) -> 0 | IK7: =+MAX(BO7:BQ7) -> 0 | IL7: =+MAX(BR7:BT7) -> 0 | IM7: =+MAX(BU7:BW7) -> 0 | IN7: =+MAX(BX7:BZ7) -> 0 | IO7: =+MAX(CA7:CC7) -> 0 | IP7: =+MAX(CD7:CF7) -> 0 | IQ7: =+MAX(CG7:CI7) -> 0 | IR7: =+MAX(CJ7:CL7) -> 0 | IS7: =+MAX(CM7:CO7) -> 0 | IT7: =+MAX(CP7:CR7) -> 0 | IU7: =+MAX(CS7:CU7) -> 0 | IV7: =+MAX(CV7:CX7) -> 0 | IW7: =+MAX(CY7:DA7) -> 0 | IX7: =+MAX(DB7:DD7) -> 0 | IY7: =+MAX(DE7:DG7) -> 0 | IZ7: =+MAX(DH7:DJ7) -> 0 | JA7: =+MAX(DK7:DM7) -> 0 | JB7: =+MAX(DN7:DP7) -> 0 | JC7: =+MAX(DQ7:DS7) -> 0 | JD7: =+MAX(DT7:DV7) -> 0 | JE7: =+MAX(DW7:DY7) -> 0 | JF7: =+MAX(DZ7:EB7) -> 0 | JG7: =+MAX(EC7:EE7) -> 0 | JH7: =+MAX(EF7:EH7) -> 0 | JI7: =+MAX(EI7:EK7) -> 0 | JJ7: =+MAX(EL7:EN7) -> 0 | JK7: =MAX(EO7:EQ7) -> 0 | JL7: =MAX(ER7:ET7) -> 0 | JM7: =MAX(EU7:EW7) -> 0 | JN7: =MAX(EX7:EZ7) -> 0 | JO7: =MAX(FA7:FC7) -> 0 | JP7: =MAX(FD7:FF7) -> 0 | JQ7: =MAX(FG7:FI7) -> 0 | JR7: =MAX(FJ7:FL7) -> 0 | JS7: =MAX(FM7:FO7) -> 0 | JT7: =MAX(FP7:FR7) -> 0 | JU7: =MAX(FS7:FU7) -> 0 | JV7: =MAX(FV7:FX7) -> 0 | JW7: =MAX(FY7:GA7) -> 0 | JX7: =MAX(GB7:GD7) -> 0 | JY7: =MAX(GE7:GG7) -> 0 | JZ7: =MAX(GH7:GJ7) -> 0 | KA7: =MAX(GK7:GM7) -> 0 | KB7: =MAX(GN7:GP7) -> 0 | KC7: =MAX(GQ7:GS7) -> 0 | KD7: =MAX(GT7:GV7) -> 0 | KE7: =MAX(GW7:GY7) -> 0 | KF7: =MAX(GZ7:HB7) -> 0 | KG7: =MAX(HC7:HE7) -> 0 | KH7: =MAX(HF7:HH7) -> 0
A8: Low | B8: NMONTH_LOW | C8: {=_xll.EQNXTDZ($A$1,$B8,C$1)} -> 0 | D8: {=_xll.EQNXTDZ($A$1,$B8,D$1)} -> 0 | E8: {=_xll.EQNXTDZ($A$1,$B8,E$1)} -> 0 | F8: {=_xll.EQNXTDZ($A$1,$B8,F$1)} -> 0 | G8: {=_xll.EQNXTDZ($A$1,$B8,G$1)} -> 0 | H8: {=_xll.EQNXTDZ($A$1,$B8,H$1)} -> 0 | I8: {=_xll.EQNXTDZ($A$1,$B8,I$1)} -> 0 | J8: {=_xll.EQNXTDZ($A$1,$B8,J$1)} -> 0 | ... HH8: {=_xll.EQNXTDZ($A$1,$B8,HH$1)} -> 0 | HP8: =+MIN(D8:F8) -> 0 | HQ8: =+MIN(G8:I8) -> 0 | HR8: =+MIN(J8:L8) -> 0 | HS8: =+MIN(M8:O8) -> 0 | HT8: =+MIN(P8:R8) -> 0 | HU8: =+MIN(S8:U8) -> 0 | HV8: =+MIN(V8:X8) -> 0 | HW8: =+MIN(Y8:AA8) -> 0 | HX8: =+MIN(AB8:AD8) -> 0 | HY8: =+MIN(AE8:AG8) -> 0 | HZ8: =+MIN(AH8:AJ8) -> 0 | IA8: =+MIN(AK8:AM8) -> 0 | IB8: =+MIN(AN8:AP8) -> 0 | IC8: =+MIN(AQ8:AS8) -> 0 | ID8: =+MIN(AT8:AV8) -> 0 | IE8: =+MIN(AW8:AY8) -> 0 | IF8: =+MIN(AZ8:BB8) -> 0 | IG8: =+MIN(BC8:BE8) -> 0 | IH8: =+MIN(BF8:BH8) -> 0 | II8: =+MIN(BI8:BK8) -> 0 | IJ8: =+MIN(BL8:BN8) -> 0 | IK8: =+MIN(BO8:BQ8) -> 0 | IL8: =+MIN(BR8:BT8) -> 0 | IM8: =+MIN(BU8:BW8) -> 0 | IN8: =+MIN(BX8:BZ8) -> 0 | IO8: =+MIN(CA8:CC8) -> 0 | IP8: =+MIN(CD8:CF8) -> 0 | IQ8: =+MIN(CG8:CI8) -> 0 | IR8: =+MIN(CJ8:CL8) -> 0 | IS8: =+MIN(CM8:CO8) -> 0 | IT8: =+MIN(CP8:CR8) -> 0 | IU8: =+MIN(CS8:CU8) -> 0 | IV8: =+MIN(CV8:CX8) -> 0 | IW8: =+MIN(CY8:DA8) -> 0 | IX8: =+MIN(DB8:DD8) -> 0 | IY8: =+MIN(DE8:DG8) -> 0 | IZ8: =+MIN(DH8:DJ8) -> 0 | JA8: =+MIN(DK8:DM8) -> 0 | JB8: =+MIN(DN8:DP8) -> 0 | JC8: =+MIN(DQ8:DS8) -> 0 | JD8: =+MIN(DT8:DV8) -> 0 | JE8: =+MIN(DW8:DY8) -> 0 | JF8: =+MIN(DZ8:EB8) -> 0 | JG8: =+MIN(EC8:EE8) -> 0 | JH8: =+MIN(EF8:EH8) -> 0 | JI8: =+MIN(EI8:EK8) -> 0 | JJ8: =+MIN(EL8:EN8) -> 0 | JK8: =MIN(EO8:EQ8) -> 0 | JL8: =MIN(ER8:ET8) -> 0 | JM8: =MIN(EU8:EW8) -> 0 | JN8: =MIN(EX8:EZ8) -> 0 | JO8: =MIN(FA8:FC8) -> 0 | JP8: =MIN(FD8:FF8) -> 0 | JQ8: =MIN(FG8:FI8) -> 0 | JR8: =MIN(FJ8:FL8) -> 0 | JS8: =MIN(FM8:FO8) -> 0 | JT8: =MIN(FP8:FR8) -> 0 | JU8: =MIN(FS8:FU8) -> 0 | JV8: =MIN(FV8:FX8) -> 0 | JW8: =MIN(FY8:GA8) -> 0 | JX8: =MIN(GB8:GD8) -> 0 | JY8: =MIN(GE8:GG8) -> 0 | JZ8: =MIN(GH8:GJ8) -> 0 | KA8: =MIN(GK8:GM8) -> 0 | KB8: =MIN(GN8:GP8) -> 0 | KC8: =MIN(GQ8:GS8) -> 0 | KD8: =MIN(GT8:GV8) -> 0 | KE8: =MIN(GW8:GY8) -> 0 | KF8: =MIN(GZ8:HB8) -> 0 | KG8: =MIN(HC8:HE8) -> 0 | KH8: =MIN(HF8:HH8) -> 0
A9: Close | B9: NMONTH_CLOSE | C9: {=_xll.EQNXTDZ($A$1,$B9,C$1)} -> 0 | D9: {=_xll.EQNXTDZ($A$1,$B9,D$1)} -> 0 | E9: {=_xll.EQNXTDZ($A$1,$B9,E$1)} -> 0 | F9: {=_xll.EQNXTDZ($A$1,$B9,F$1)} -> 0 | G9: {=_xll.EQNXTDZ($A$1,$B9,G$1)} -> 0 | H9: {=_xll.EQNXTDZ($A$1,$B9,H$1)} -> 0 | I9: {=_xll.EQNXTDZ($A$1,$B9,I$1)} -> 0 | J9: {=_xll.EQNXTDZ($A$1,$B9,J$1)} -> 0 | ... HH9: {=_xll.EQNXTDZ($A$1,$B9,HH$1)} -> 0 | HP9: =+F9 -> 0 | HQ9: =+I9 -> 0 | HR9: =+L9 -> 0 | HS9: =+O9 -> 0 | HT9: =+R9 -> 0 | HU9: =+U9 -> 0 | HV9: =+X9 -> 0 | HW9: =+AA9 -> 0 | HX9: =+AD9 -> 0 | HY9: =+AG9 -> 0 | HZ9: =+AJ9 -> 0 | IA9: =+AM9 -> 0 | IB9: =+AP9 -> 0 | IC9: =+AS9 -> 0 | ID9: =+AV9 -> 0 | IE9: =+AY9 -> 0 | IF9: =+BB9 -> 0 | IG9: =+BE9 -> 0 | IH9: =+BH9 -> 0 | II9: =+BK9 -> 0 | IJ9: =+BN9 -> 0 | IK9: =+BQ9 -> 0 | IL9: =+BT9 -> 0 | IM9: =+BW9 -> 0 | IN9: =+BZ9 -> 0 | IO9: =+CC9 -> 0 | IP9: =+CF9 -> 0 | IQ9: =+CI9 -> 0 | IR9: =+CL9 -> 0 | IS9: =+CO9 -> 0 | IT9: =+CR9 -> 0 | IU9: =+CU9 -> 0 | IV9: =+CX9 -> 0 | IW9: =+DA9 -> 0 | IX9: =+DD9 -> 0 | IY9: =+DG9 -> 0 | IZ9: =+DJ9 -> 0 | JA9: =+DM9 -> 0 | JB9: =+DP9 -> 0 | JC9: =+DS9 -> 0 | JD9: =+DV9 -> 0 | JE9: =+DY9 -> 0 | JF9: =+EB9 -> 0 | JG9: =+EE9 -> 0 | JH9: =+EH9 -> 0 | JI9: =+EK9 -> 0 | JJ9: =+EN9 -> 0 | JK9: =EQ9 -> 0 | JL9: =ET9 -> 0 | JM9: =EW9 -> 0 | JN9: =EZ9 -> 0 | JO9: =FC9 -> 0 | JP9: =FF9 -> 0 | JQ9: =FI9 -> 0 | JR9: =FL9 -> 0 | JS9: =FO9 -> 0 | JT9: =FR9 -> 0 | JU9: =FU9 -> 0 | JV9: =FX9 -> 0 | JW9: =GA9 -> 0 | JX9: =GD9 -> 0 | JY9: =GG9 -> 0 | JZ9: =GJ9 -> 0 | KA9: =GM9 -> 0 | KB9: =GP9 -> 0 | KC9: =GS9 -> 0 | KD9: =GV9 -> 0 | KE9: =GY9 -> 0 | KF9: =HB9 -> 0 | KG9: =HE9 -> 0 | KH9: =HH9 -> 0
A11: Field Description | B11: Field Name | C11: {=_xll.EQNXTDZ($A$1,$B11,C$1)} -> 0 | D11: {=_xll.EQNXTDZ($A$1,$B11,D$1)} -> 0 | E11: {=_xll.EQNXTDZ($A$1,$B11,E$1)} -> 0 | F11: {=_xll.EQNXTDZ($A$1,$B11,F$1)} -> 0 | G11: {=_xll.EQNXTDZ($A$1,$B11,G$1)} -> 0 | H11: {=_xll.EQNXTDZ($A$1,$B11,H$1)} -> 0 | I11: {=_xll.EQNXTDZ($A$1,$B11,I$1)} -> 0 | J11: {=_xll.EQNXTDZ($A$1,$B11,J$1)} -> 0 | ... HH11: {=_xll.EQNXTDZ($A$1,$B11,HH$1)} -> 0
A12: Month End | B12: BMONTH_MONTHEND | C12: {=_xll.EQNXTDZ($A$1,$B12,C$1)} -> 0 | D12: {=_xll.EQNXTDZ($A$1,$B12,D$1)} -> 0 | E12: {=_xll.EQNXTDZ($A$1,$B12,E$1)} -> 0 | F12: {=_xll.EQNXTDZ($A$1,$B12,F$1)} -> 0 | G12: {=_xll.EQNXTDZ($A$1,$B12,G$1)} -> 0 | H12: {=_xll.EQNXTDZ($A$1,$B12,H$1)} -> 0 | I12: {=_xll.EQNXTDZ($A$1,$B12,I$1)} -> 0 | J12: {=_xll.EQNXTDZ($A$1,$B12,J$1)} -> 0 | ... HH12: {=_xll.EQNXTDZ($A$1,$B12,HH$1)} -> 0
A13: Open | B13: BMONTH_OPEN | C13: {=_xll.EQNXTDZ($A$1,$B13,C$1)} -> 0 | D13: {=_xll.EQNXTDZ($A$1,$B13,D$1)} -> 0 | E13: {=_xll.EQNXTDZ($A$1,$B13,E$1)} -> 0 | F13: {=_xll.EQNXTDZ($A$1,$B13,F$1)} -> 0 | G13: {=_xll.EQNXTDZ($A$1,$B13,G$1)} -> 0 | H13: {=_xll.EQNXTDZ($A$1,$B13,H$1)} -> 0 | I13: {=_xll.EQNXTDZ($A$1,$B13,I$1)} -> 0 | J13: {=_xll.EQNXTDZ($A$1,$B13,J$1)} -> 0 | ... HH13: {=_xll.EQNXTDZ($A$1,$B13,HH$1)} -> 0
A14: High | B14: BMONTH_HIGH | C14: {=_xll.EQNXTDZ($A$1,$B14,C$1)} -> 0 | D14: {=_xll.EQNXTDZ($A$1,$B14,D$1)} -> 0 | E14: {=_xll.EQNXTDZ($A$1,$B14,E$1)} -> 0 | F14: {=_xll.EQNXTDZ($A$1,$B14,F$1)} -> 0 | G14: {=_xll.EQNXTDZ($A$1,$B14,G$1)} -> 0 | H14: {=_xll.EQNXTDZ($A$1,$B14,H$1)} -> 0 | I14: {=_xll.EQNXTDZ($A$1,$B14,I$1)} -> 0 | J14: {=_xll.EQNXTDZ($A$1,$B14,J$1)} -> 0 | ... HH14: {=_xll.EQNXTDZ($A$1,$B14,HH$1)} -> 0 | HP14: =+MAX(D14:F14) -> 0 | HQ14: =+MAX(G14:I14) -> 0 | HR14: =+MAX(J14:L14) -> 0 | HS14: =+MAX(M14:O14) -> 0 | HT14: =+MAX(P14:R14) -> 0 | HU14: =+MAX(S14:U14) -> 0 | HV14: =+MAX(V14:X14) -> 0 | HW14: =+MAX(Y14:AA14) -> 0 | HX14: =+MAX(AB14:AD14) -> 0 | HY14: =+MAX(AE14:AG14) -> 0 | HZ14: =+MAX(AH14:AJ14) -> 0 | IA14: =+MAX(AK14:AM14) -> 0 | IB14: =+MAX(AN14:AP14) -> 0 | IC14: =+MAX(AQ14:AS14) -> 0 | ID14: =+MAX(AT14:AV14) -> 0 | IE14: =+MAX(AW14:AY14) -> 0 | IF14: =+MAX(AZ14:BB14) -> 0 | IG14: =+MAX(BC14:BE14) -> 0 | IH14: =+MAX(BF14:BH14) -> 0 | II14: =+MAX(BI14:BK14) -> 0 | IJ14: =+MAX(BL14:BN14) -> 0 | IK14: =+MAX(BO14:BQ14) -> 0 | IL14: =+MAX(BR14:BT14) -> 0 | IM14: =+MAX(BU14:BW14) -> 0 | IN14: =+MAX(BX14:BZ14) -> 0 | IO14: =+MAX(CA14:CC14) -> 0 | IP14: =+MAX(CD14:CF14) -> 0 | IQ14: =+MAX(CG14:CI14) -> 0 | IR14: =+MAX(CJ14:CL14) -> 0 | IS14: =+MAX(CM14:CO14) -> 0 | IT14: =+MAX(CP14:CR14) -> 0 | IU14: =+MAX(CS14:CU14) -> 0 | IV14: =+MAX(CV14:CX14) -> 0 | IW14: =+MAX(CY14:DA14) -> 0 | IX14: =+MAX(DB14:DD14) -> 0 | IY14: =+MAX(DE14:DG14) -> 0 | IZ14: =+MAX(DH14:DJ14) -> 0 | JA14: =+MAX(DK14:DM14) -> 0 | JB14: =+MAX(DN14:DP14) -> 0 | JC14: =+MAX(DQ14:DS14) -> 0 | JD14: =+MAX(DT14:DV14) -> 0 | JE14: =+MAX(DW14:DY14) -> 0 | JF14: =+MAX(DZ14:EB14) -> 0 | JG14: =+MAX(EC14:EE14) -> 0 | JH14: =+MAX(EF14:EH14) -> 0 | JI14: =+MAX(EI14:EK14) -> 0 | JJ14: =+MAX(EL14:EN14) -> 0 | JK14: =MAX(EO14:EQ14) -> 0 | JL14: =MAX(ER14:ET14) -> 0 | JM14: =MAX(EU14:EW14) -> 0 | JN14: =MAX(EX14:EZ14) -> 0 | JO14: =MAX(FA14:FC14) -> 0 | JP14: =MAX(FD14:FF14) -> 0 | JQ14: =MAX(FG14:FI14) -> 0 | JR14: =MAX(FJ14:FL14) -> 0 | JS14: =MAX(FM14:FO14) -> 0 | JT14: =MAX(FP14:FR14) -> 0 | JU14: =MAX(FS14:FU14) -> 0 | JV14: =MAX(FV14:FX14) -> 0 | JW14: =MAX(FY14:GA14) -> 0 | JX14: =MAX(GB14:GD14) -> 0 | JY14: =MAX(GE14:GG14) -> 0 | JZ14: =MAX(GH14:GJ14) -> 0 | KA14: =MAX(GK14:GM14) -> 0 | KB14: =MAX(GN14:GP14) -> 0 | KC14: =MAX(GQ14:GS14) -> 0 | KD14: =MAX(GT14:GV14) -> 0 | KE14: =MAX(GW14:GY14) -> 0 | KF14: =MAX(GZ14:HB14) -> 0 | KG14: =MAX(HC14:HE14) -> 0 | KH14: =MAX(HF14:HH14) -> 0
A15: Low | B15: BMONTH_LOW | C15: {=_xll.EQNXTDZ($A$1,$B15,C$1)} -> 0 | D15: {=_xll.EQNXTDZ($A$1,$B15,D$1)} -> 0 | E15: {=_xll.EQNXTDZ($A$1,$B15,E$1)} -> 0 | F15: {=_xll.EQNXTDZ($A$1,$B15,F$1)} -> 0 | G15: {=_xll.EQNXTDZ($A$1,$B15,G$1)} -> 0 | H15: {=_xll.EQNXTDZ($A$1,$B15,H$1)} -> 0 | I15: {=_xll.EQNXTDZ($A$1,$B15,I$1)} -> 0 | J15: {=_xll.EQNXTDZ($A$1,$B15,J$1)} -> 0 | ... HH15: {=_xll.EQNXTDZ($A$1,$B15,HH$1)} -> 0 | HP15: =+MIN(D15:F15) -> 0 | HQ15: =+MIN(G15:I15) -> 0 | HR15: =+MIN(J15:L15) -> 0 | HS15: =+MIN(M15:O15) -> 0 | HT15: =+MIN(P15:R15) -> 0 | HU15: =+MIN(S15:U15) -> 0 | HV15: =+MIN(V15:X15) -> 0 | HW15: =+MIN(Y15:AA15) -> 0 | HX15: =+MIN(AB15:AD15) -> 0 | HY15: =+MIN(AE15:AG15) -> 0 | HZ15: =+MIN(AH15:AJ15) -> 0 | IA15: =+MIN(AK15:AM15) -> 0 | IB15: =+MIN(AN15:AP15) -> 0 | IC15: =+MIN(AQ15:AS15) -> 0 | ID15: =+MIN(AT15:AV15) -> 0 | IE15: =+MIN(AW15:AY15) -> 0 | IF15: =+MIN(AZ15:BB15) -> 0 | IG15: =+MIN(BC15:BE15) -> 0 | IH15: =+MIN(BF15:BH15) -> 0 | II15: =+MIN(BI15:BK15) -> 0 | IJ15: =+MIN(BL15:BN15) -> 0 | IK15: =+MIN(BO15:BQ15) -> 0 | IL15: =+MIN(BR15:BT15) -> 0 | IM15: =+MIN(BU15:BW15) -> 0 | IN15: =+MIN(BX15:BZ15) -> 0 | IO15: =+MIN(CA15:CC15) -> 0 | IP15: =+MIN(CD15:CF15) -> 0 | IQ15: =+MIN(CG15:CI15) -> 0 | IR15: =+MIN(CJ15:CL15) -> 0 | IS15: =+MIN(CM15:CO15) -> 0 | IT15: =+MIN(CP15:CR15) -> 0 | IU15: =+MIN(CS15:CU15) -> 0 | IV15: =+MIN(CV15:CX15) -> 0 | IW15: =+MIN(CY15:DA15) -> 0 | IX15: =+MIN(DB15:DD15) -> 0 | IY15: =+MIN(DE15:DG15) -> 0 | IZ15: =+MIN(DH15:DJ15) -> 0 | JA15: =+MIN(DK15:DM15) -> 0 | JB15: =+MIN(DN15:DP15) -> 0 | JC15: =+MIN(DQ15:DS15) -> 0 | JD15: =+MIN(DT15:DV15) -> 0 | JE15: =+MIN(DW15:DY15) -> 0 | JF15: =+MIN(DZ15:EB15) -> 0 | JG15: =+MIN(EC15:EE15) -> 0 | JH15: =+MIN(EF15:EH15) -> 0 | JI15: =+MIN(EI15:EK15) -> 0 | JJ15: =+MIN(EL15:EN15) -> 0 | JK15: =MIN(EO15:EQ15) -> 0 | JL15: =MIN(ER15:ET15) -> 0 | JM15: =MIN(EU15:EW15) -> 0 | JN15: =MIN(EX15:EZ15) -> 0 | JO15: =MIN(FA15:FC15) -> 0 | JP15: =MIN(FD15:FF15) -> 0 | JQ15: =MIN(FG15:FI15) -> 0 | JR15: =MIN(FJ15:FL15) -> 0 | JS15: =MIN(FM15:FO15) -> 0 | JT15: =MIN(FP15:FR15) -> 0 | JU15: =MIN(FS15:FU15) -> 0 | JV15: =MIN(FV15:FX15) -> 0 | JW15: =MIN(FY15:GA15) -> 0 | JX15: =MIN(GB15:GD15) -> 0 | JY15: =MIN(GE15:GG15) -> 0 | JZ15: =MIN(GH15:GJ15) -> 0 | KA15: =MIN(GK15:GM15) -> 0 | KB15: =MIN(GN15:GP15) -> 0 | KC15: =MIN(GQ15:GS15) -> 0 | KD15: =MIN(GT15:GV15) -> 0 | KE15: =MIN(GW15:GY15) -> 0 | KF15: =MIN(GZ15:HB15) -> 0 | KG15: =MIN(HC15:HE15) -> 0 | KH15: =MIN(HF15:HH15) -> 0
A16: Close | B16: BMONTH_CLOSE | C16: {=_xll.EQNXTDZ($A$1,$B16,C$1)} -> 0 | D16: {=_xll.EQNXTDZ($A$1,$B16,D$1)} -> 0 | E16: {=_xll.EQNXTDZ($A$1,$B16,E$1)} -> 0 | F16: {=_xll.EQNXTDZ($A$1,$B16,F$1)} -> 0 | G16: {=_xll.EQNXTDZ($A$1,$B16,G$1)} -> 0 | H16: {=_xll.EQNXTDZ($A$1,$B16,H$1)} -> 0 | I16: {=_xll.EQNXTDZ($A$1,$B16,I$1)} -> 0 | J16: {=_xll.EQNXTDZ($A$1,$B16,J$1)} -> 0 | ... HH16: {=_xll.EQNXTDZ($A$1,$B16,HH$1)} -> 0 | HP16: =+F16 -> 0 | HQ16: =+I16 -> 0 | HR16: =+L16 -> 0 | HS16: =+O16 -> 0 | HT16: =+R16 -> 0 | HU16: =+U16 -> 0 | HV16: =+X16 -> 0 | HW16: =+AA16 -> 0 | HX16: =+AD16 -> 0 | HY16: =+AG16 -> 0 | HZ16: =+AJ16 -> 0 | IA16: =+AM16 -> 0 | IB16: =+AP16 -> 0 | IC16: =+AS16 -> 0 | ID16: =+AV16 -> 0 | IE16: =+AY16 -> 0 | IF16: =+BB16 -> 0 | IG16: =+BE16 -> 0 | IH16: =+BH16 -> 0 | II16: =+BK16 -> 0 | IJ16: =+BN16 -> 0 | IK16: =+BQ16 -> 0 | IL16: =+BT16 -> 0 | IM16: =+BW16 -> 0 | IN16: =+BZ16 -> 0 | IO16: =+CC16 -> 0 | IP16: =+CF16 -> 0 | IQ16: =+CI16 -> 0 | IR16: =+CL16 -> 0 | IS16: =+CO16 -> 0 | IT16: =+CR16 -> 0 | IU16: =+CU16 -> 0 | IV16: =+CX16 -> 0 | IW16: =+DA16 -> 0 | IX16: =+DD16 -> 0 | IY16: =+DG16 -> 0 | IZ16: =+DJ16 -> 0 | JA16: =+DM16 -> 0 | JB16: =+DP16 -> 0 | JC16: =+DS16 -> 0 | JD16: =+DV16 -> 0 | JE16: =+DY16 -> 0 | JF16: =+EB16 -> 0 | JG16: =+EE16 -> 0 | JH16: =+EH16 -> 0 | JI16: =+EK16 -> 0 | JJ16: =+EN16 -> 0 | JK16: =EQ16 -> 0 | JL16: =ET16 -> 0 | JM16: =EW16 -> 0 | JN16: =EZ16 -> 0 | JO16: =FC16 -> 0 | JP16: =FF16 -> 0 | JQ16: =FI16 -> 0 | JR16: =FL16 -> 0 | JS16: =FO16 -> 0 | JT16: =FR16 -> 0 | JU16: =FU16 -> 0 | JV16: =FX16 -> 0 | JW16: =GA16 -> 0 | JX16: =GD16 -> 0 | JY16: =GG16 -> 0 | JZ16: =GJ16 -> 0 | KA16: =GM16 -> 0 | KB16: =GP16 -> 0 | KC16: =GS16 -> 0 | KD16: =GV16 -> 0 | KE16: =GY16 -> 0 | KF16: =HB16 -> 0 | KG16: =HE16 -> 0 | KH16: =HH16 -> 0
A19: High | HP19: =+IF(HP14=0,HP7,HP14) -> 0 | HQ19: =+IF(HQ14=0,HQ7,HQ14) -> 0 | HR19: =+IF(HR14=0,HR7,HR14) -> 0 | HS19: =+IF(HS14=0,HS7,HS14) -> 0 | HT19: =+IF(HT14=0,HT7,HT14) -> 0 | HU19: =+IF(HU14=0,HU7,HU14) -> 0 | HV19: =+IF(HV14=0,HV7,HV14) -> 0 | HW19: =+IF(HW14=0,HW7,HW14) -> 0 | ... KH19: =+IF(KH14=0,KH7,KH14) -> 0
A20: Low | HP20: =+IF(HP15=0,HP8,HP15) -> 0 | HQ20: =+IF(HQ15=0,HQ8,HQ15) -> 0 | HR20: =+IF(HR15=0,HR8,HR15) -> 0 | HS20: =+IF(HS15=0,HS8,HS15) -> 0 | HT20: =+IF(HT15=0,HT8,HT15) -> 0 | HU20: =+IF(HU15=0,HU8,HU15) -> 0 | HV20: =+IF(HV15=0,HV8,HV15) -> 0 | HW20: =+IF(HW15=0,HW8,HW15) -> 0 | ... KH20: =+IF(KH15=0,KH8,KH15) -> 0
A21: Close | HP21: =+IF(HP16=0,HP9,HP16) -> 0 | HQ21: =+IF(HQ16=0,HQ9,HQ16) -> 0 | HR21: =+IF(HR16=0,HR9,HR16) -> 0 | HS21: =+IF(HS16=0,HS9,HS16) -> 0 | HT21: =+IF(HT16=0,HT9,HT16) -> 0 | HU21: =+IF(HU16=0,HU9,HU16) -> 0 | HV21: =+IF(HV16=0,HV9,HV16) -> 0 | HW21: =+IF(HW16=0,HW9,HW16) -> 0 | ... KH21: =+IF(KH16=0,KH9,KH16) -> 0

Sheet Share price Daily
A1: =_xll.EQNXTH(B1,"[ADJC];[ADJH];[ADJL];[ADJO];[UCLS];[VOLUME]","2015-Jan-01","Y","All traded days","Asc") -> Fetching Data | B1: =+'Annual Raw'!A1 -> 0 | L1: =_xll.EQNXTH(B1,"[NADJC];[NADJH];[NADJLOW];[NADJOPEN];[NUCLOSE];[NVOLUME]","2015-Jan-01","Y","All traded days","Asc") -> Fetching Data
A154: 42223 | B154: 136.56 | C154: 130.02 | D154: 129.4 | E154: 134.66 | F154: 650.1 | G154: 19836 | L154: 42223 | M154: 131 | N154: 136.73 | O154: 129.62 | P154: 134.02 | Q154: 655 | R154: 35076
A155: 42226 | B155: 133.4 | C155: 130.07 | D155: 128.1 | E155: 131.8 | F155: 650.35 | G155: 3756 | L155: 42226 | M155: 129.7 | N155: 133.58 | O155: 127.71 | P155: 132.58 | Q155: 648.5 | R155: 29284
A156: 42227 | B156: 131 | C156: 129.85 | D156: 129 | E156: 129.2 | F156: 649.25 | G156: 15693 | L156: 42227 | M156: 129.47 | N156: 131.2 | O156: 129 | P156: 130.2 | Q156: 647.35 | R156: 11805
A157: 42228 | B157: 131.38 | C157: 127.93 | D157: 126.4 | E157: 130 | F157: 639.65 | G157: 5106 | L157: 42228 | M157: 128.97 | N157: 131.47 | O157: 126 | P157: 129.87 | Q157: 644.85 | R157: 21163
A158: 42229 | B158: 129.01 | C158: 125.63 | D158: 124.59 | E158: 128.48 | F158: 628.15 | G158: 2840 | L158: 42229 | M158: 125.56 | N158: 129.36 | O158: 125 | P158: 128.4 | Q158: 627.8 | R158: 11891
A159: 42230 | B159: 131.64 | C159: 129.28 | D159: 125.3 | E159: 125.4 | F159: 646.4 | G159: 13562 | L159: 42230 | M159: 128.8 | N159: 131.8 | O159: 125.16 | P159: 125.78 | Q159: 644 | R159: 95841
A160: 42233 | B160: 131.96 | C160: 130.53 | D160: 126.8 | E160: 129.22 | F160: 652.65 | G160: 5310 | L160: 42233 | M160: 130.6 | N160: 131.8 | O160: 126.2 | P160: 127.91 | Q160: 653 | R160: 13448
A161: 42234 | B161: 132 | C161: 129.7 | D161: 127 | E161: 130.22 | F161: 648.5 | G161: 8254 | L161: 42234 | M161: 131.13 | N161: 132.6 | O161: 129.03 | P161: 130.41 | Q161: 655.65 | R161: 19275
A162: 42235 | B162: 136 | C162: 133.53 | D162: 130.63 | E162: 131.6 | F162: 667.65 | G162: 10909 | L162: 42235 | M162: 132.61 | N162: 135.74 | O162: 130.08 | P162: 133.39 | Q162: 663.05 | R162: 15526
A163: 42236 | B163: 142.2 | C163: 126.97 | D163: 125.65 | E163: 137.99 | F163: 634.85 | G163: 49628 | L163: 42236 | M163: 126.93 | N163: 142 | O163: 125.32 | P163: 139 | Q163: 634.65 | R163: 201049
A164: 42237 | B164: 128.35 | C164: 124.74 | D164: 120.6 | E164: 125 | F164: 623.7 | G164: 14645 | L164: 42237 | M164: 124.55 | N164: 128.19 | O164: 120.2 | P164: 125.07 | Q164: 622.75 | R164: 55828
A165: 42240 | B165: 122.2 | C165: 118.26 | D165: 117 | E165: 121 | F165: 591.3 | G165: 14768 | L165: 42240 | M165: 120.18 | N165: 122.94 | O165: 118.25 | P165: 122.94 | Q165: 600.9 | R165: 59123
... A2845: 46196 | B2845: 1742.9 | C2845: 1723.95 | D2845: 1717.7 | E2845: 1729.6 | F2845: 1723.95 | G2845: 716099 | L2845: 46196 | M2845: 1725.9 | N2845: 1742.8 | O2845: 1711.7 | P2845: 1719.9 | Q2845: 1725.9 | R2845: 1934588

Sheet 4_Axis Bank Ltd._Balance Sheet
A1: 132215
A3: =_xll.EQNXTV("Company-Profit And Loss",A1,"Crores/INR/40/Asc/N2",C3,D3,E3,F3,G3,H3) -> EQNXTV | C3: Standalone | D3: Abridged | E3: Actual | F3: 202503 | G3: Reported | H3: Gross Sales
A5: Profit And Loss - Standalone
A6: DESCRIPTION | B6: 34759 | C6: 35490 | D6: 35855 | E6: 36220 | F6: 36586 | G6: 36951 | H6: 37316 | I6: 37681 | J6: 38047 | K6: 38412 | L6: 38777 | M6: 39142 | N6: 39508 | O6: 39873 | P6: 40238 | Q6: 40603 | R6: 40969 | S6: 41334 | T6: 41699 | U6: 42064 | V6: 42430 | W6: 42795 | X6: 43160 | Y6: 43525 | Z6: 43891 | AA6: 44256 | AB6: 44621 | AC6: 44986 | AD6: 45352 | AE6: 45717
A8: No of Months | B8: 12 | C8: 12 | D8: 12 | E8: 12 | F8: 12 | G8: 12 | H8: 12 | I8: 12 | J8: 12 | K8: 12 | L8: 12 | M8: 12 | N8: 12 | O8: 12 | P8: 12 | Q8: 12 | R8: 12 | S8: 12 | T8: 12 | U8: 12 | V8: 12 | W8: 12 | X8: 12 | Y8: 12 | Z8: 12 | AA8: 12 | AB8: 12 | AC8: 12 | AD8: 12 | AE8: 12
A9: I. INCOME
A10: Interest Earned | B10: 29.1719 | C10: 157.6474 | D10: 255.61 | E10: 373.281 | F10: 483.2599 | G10: 889.6314 | H10: 1178.53 | I10: 1464.81 | J10: 1598.543 | K10: 1924.1582 | L10: 2888.7904 | M10: 4461.6552 | N10: 7005.3151 | O10: 10835.486 | P10: 11638.022 | Q10: 15154.806 | R10: 21994.647 | S10: 27182.574 | T10: 30641.155 | U10: 35478.598 | V10: 40988.036 | W10: 44542.158 | X10: 45780.312 | Y10: 54985.771 | Z10: 62635.157 | AA10: 63346.232 | AB10: 67376.83 | AC10: 85163.766 | AD10: 109368.63 | AE10: 122677.04
A11: Other Income | B11: 1.8346 | C11: 24.1029 | D11: 60.8991 | E11: 46.6287 | F11: 91.1659 | G11: 163.0001 | H11: 415.87 | I11: 410.47 | J11: 540.1456 | K11: 415.8196 | L11: 729.6344 | M11: 1010.1113 | N11: 1795.4888 | O11: 2896.8781 | P11: 3945.7819 | Q11: 4632.1338 | R11: 5420.2163 | S11: 6551.1063 | T11: 7405.2247 | U11: 8365.0458 | V11: 9371.4644 | W11: 11691.311 | X11: 10967.086 | Y11: 13130.339 | Z11: 15536.561 | AA11: 12263.599 | AB11: 15220.545 | AC11: 16143.419 | AD11: 22441.955 | AE11: 25257.056
A12: Total Income | B12: 31.0065 | C12: 181.7503 | D12: 316.5091 | E12: 419.9097 | F12: 574.4258 | G12: 1052.6315 | H12: 1594.4 | I12: 1875.28 | J12: 2138.6886 | K12: 2339.9778 | L12: 3618.4248 | M12: 5471.7665 | N12: 8800.8039 | O12: 13732.364 | P12: 15583.803 | Q12: 19786.94 | R12: 27414.864 | S12: 33733.681 | T12: 38046.38 | U12: 43843.643 | V12: 50359.501 | W12: 56233.469 | X12: 56747.399 | Y12: 68116.11 | Z12: 78171.718 | AA12: 75609.831 | AB12: 82597.375 | AC12: 101307.19 | AD12: 131810.59 | AE12: 147934.1
A13: II. EXPENDITURE
A14: Interest Expended | B14: 14.0985 | C14: 122.0736 | D14: 222.1898 | E14: 300.6328 | F14: 392.8564 | G14: 791.3638 | H14: 980 | I14: 1142.41 | J14: 1021.4487 | K14: 1192.9808 | L14: 1810.556 | M14: 2993.3172 | N14: 4419.9617 | O14: 7149.2742 | P14: 6633.5261 | Q14: 8591.823 | R14: 13976.902 | S14: 17516.311 | T14: 18689.522 | U14: 21254.46 | V14: 24155.068 | W14: 26449.042 | X14: 27162.582 | Y14: 33277.597 | Z14: 37428.954 | AA14: 34107.11 | AB14: 34244.613 | AC14: 42218.021 | AD14: 59474.146 | AE14: 68329.221
A15: Operating Expenses | B15: 7.8485 | C15: 26.6971 | D15: 39.7558 | E15: 51.0262 | F15: 65.4009 | G15: 128.7637 | H15: 207.12 | I15: 322.85 | J15: 419.2055 | K15: 581.3789 | L15: 814.0507 | M15: 1214.5984 | N15: 2154.9269 | O15: 2858.2127 | P15: 3709.7223 | Q15: 4779.4281 | R15: 6007.0995 | S15: 6914.2375 | T15: 7900.7739 | U15: 9203.7456 | V15: 10100.819 | W15: 12199.905 | X15: 13990.34 | Y15: 15833.408 | Z15: 17304.624 | AA15: 18375.149 | AB15: 23610.754 | AC15: 39298.538 | AD15: 35213.284 | AE15: 37499.943
A16: Provisions and Contingencies | B16: 3.077 | C16: 17.7587 | D16: 25.2068 | E16: 21.9707 | F16: 37.4932 | G16: 28.0513 | H16: 193.91 | I16: 108.73 | J16: 268.6724 | K16: 51.0104 | L16: 262.3844 | M16: 267.3626 | N16: 579.4163 | O16: 939.3984 | P16: 1388.8417 | Q16: 1279.2779 | R16: 1142.6664 | S16: 1750.0592 | T16: 2107.0376 | U16: 2327.6761 | V16: 3709.9119 | W16: 12116.962 | X16: 15472.906 | Y16: 12031.017 | Z16: 18533.915 | AA16: 14321.721 | AB16: 7359.4491 | AC16: 2884.7777 | AD16: 4063.0948 | AE16: 7758.3504
A17: Profit Before Tax | B17: 5.9825 | C17: 15.2209 | D17: 29.3567 | E17: 46.28 | F17: 78.6753 | G17: 104.4527 | H17: 213.37 | I17: 301.29 | J17: 429.362 | K17: 514.6077 | L17: 731.4337 | M17: 996.4883 | N17: 1646.499 | O17: 2785.4784 | P17: 3851.7133 | Q17: 5136.4106 | R17: 6288.1954 | S17: 7553.0729 | T17: 9349.0466 | U17: 11057.762 | V17: 12393.703 | W17: 5467.5592 | X17: 121.5713 | Y17: 6974.0883 | Z17: 4904.2254 | AA17: 8805.8506 | AB17: 17382.558 | AC17: 16905.849 | AD17: 33060.063 | AE17: 34346.582
A18: Taxes | B18: 3.6733 | C18: 0 | D18: 11.7398 | E18: 15.21 | F18: 27.75 | G18: 18.33 | H18: 79.23 | I18: 109.11 | J18: 151.05 | K18: 180.03 | L18: 246.35 | M18: 337.46 | N18: 575.47 | O18: 970.12 | P18: 1337.18 | Q18: 1747.92 | R18: 2045.99 | S18: 2373.64 | T18: 3131.38 | U18: 3699.94 | V18: 4170.04 | W18: 1788.28 | X18: -154.11 | Y18: 2297.48 | Z18: 3277.01 | AA18: 2217.35 | AB18: 4357.08 | AC18: 7326.17 | AD18: 8198.63 | AE18: 7973.1
A19: Total | B19: 28.6973 | C19: 166.5294 | D19: 298.8922 | E19: 388.8397 | F19: 523.5005 | G19: 966.5088 | H19: 1460.26 | I19: 1683.1 | J19: 1860.3766 | K19: 2005.4001 | L19: 3133.3411 | M19: 4812.7382 | N19: 7729.7749 | O19: 11917.005 | P19: 13069.27 | Q19: 16398.449 | R19: 23172.658 | S19: 28554.248 | T19: 31828.714 | U19: 36485.821 | V19: 42135.838 | W19: 52554.189 | X19: 56471.717 | Y19: 63439.502 | Z19: 76544.503 | AA19: 69021.33 | AB19: 69571.897 | AC19: 91727.507 | AD19: 106949.15 | AE19: 121560.61
A20: III. PROFIT AND LOSS
A21: Profit After Tax | B21: 2.3092 | C21: 15.2209 | D21: 17.6169 | E21: 31.07 | F21: 50.9253 | G21: 86.1227 | H21: 134.14 | I21: 192.18 | J21: 278.312 | K21: 334.5777 | L21: 485.0837 | M21: 659.0283 | N21: 1071.029 | O21: 1815.3584 | P21: 2514.5333 | Q21: 3388.4906 | R21: 4242.2054 | S21: 5179.4329 | T21: 6217.6666 | U21: 7357.8223 | V21: 8223.6628 | W21: 3679.2792 | X21: 275.6813 | Y21: 4676.6083 | Z21: 1627.2154 | AA21: 6588.5006 | AB21: 13025.478 | AC21: 9579.6785 | AD21: 24861.433 | AE21: 26373.482
A22: Extra items | C22: 0 | D22: -1.0307 | L22: 0 | M22: 0 | N22: 0 | O22: 0 | P22: 0 | R22: 0
A23: Profit brought forward | C23: 10.8176 | D23: 20.5338 | E23: 30.7108 | F23: 41.9893 | G23: 52.598 | H23: 74.37 | I23: 78.64 | J23: 122.4667 | K23: 182.1024 | L23: 197.4076 | M23: 731.039 | N23: 1029.074 | O23: 1553.8689 | P23: 2348.0865 | Q23: 3427.4337 | R23: 4969.7707 | S23: 7329.4476 | T23: 10029.262 | U23: 13501.446 | V23: 17623.491 | W23: 23766.456 | X23: 24448.327 | Y23: 23043.052 | Z23: 24322.995 | AA23: 26190.455 | AB23: 29985.281 | AC23: 38100.659 | AD23: 44144.93 | AE23: 60254.056
A24: Adjustments to PAT | C24: -0.2039 | D24: -0.5614 | E24: 0.0124 | F24: 0.1358 | G24: 0.0014 | H24: 2.39 | M24: -31.8028
A25: Total Profit & Loss | B25: 2.3092 | C25: 25.8346 | D25: 37.5893 | E25: 61.7932 | F25: 93.0504 | G25: 138.7221 | H25: 210.9 | I25: 270.82 | J25: 400.7787 | K25: 516.6801 | L25: 682.4913 | M25: 1358.2645 | N25: 2100.103 | O25: 3369.2273 | P25: 4862.6198 | Q25: 6815.9243 | R25: 9211.9761 | S25: 12508.88 | T25: 16246.929 | U25: 20859.268 | V25: 25847.154 | W25: 27445.735 | X25: 24724.009 | Y25: 27719.66 | Z25: 25950.211 | AA25: 32778.955 | AB25: 43010.759 | AC25: 47680.338 | AD25: 69006.363 | AE25: 86627.538
A26: IV. APPROPRIATIONS | B26: 2.3092 | C26: 25.8346 | D26: 36.5586 | E26: 61.7932 | F26: 93.0504 | G26: 138.7221 | H26: 210.9 | I26: 270.82 | J26: 400.7787 | K26: 516.6801 | L26: 682.4913 | M26: 1358.2645 | N26: 2100.103 | O26: 3369.2273 | P26: 4862.6198 | Q26: 6815.9243 | R26: 9211.9761 | S26: 12508.88 | T26: 16246.929 | U26: 20859.268 | V26: 25847.154 | W26: 27445.735 | X26: 24724.009 | Y26: 27719.66 | Z26: 25950.211 | AA26: 32778.955 | AB26: 43010.759 | AC26: 47680.338 | AD26: 69006.363 | AE26: 86627.538
A27: Equity Dividend % | E27: 10 | F27: 12 | G27: 15 | H27: 20 | I27: 22 | J27: 25 | K27: 28 | L27: 35 | M27: 45 | N27: 60 | O27: 100 | P27: 120 | Q27: 140 | R27: 160 | S27: 180 | T27: 200 | U27: 230 | V27: 250 | W27: 250 | Y27: 50 | AB27: 50 | AC27: 50 | AD27: 50 | AE27: 50
A28: Earnings Per Share(Calculated) | B28: 0.20079983 | C28: 1.3235554 | D28: 1.531903 | E28: 2.3555153 | F28: 3.8608085 | G28: 6.5292351 | H28: 6.9933789 | I28: 8.3487554 | J28: 12.017932 | K28: 12.219945 | L28: 17.4058 | M28: 23.4004 | N28: 29.9413 | O28: 50.5664 | P28: 62.0606 | Q28: 82.5362 | R28: 102.6662 | S28: 110.6824 | T28: 132.3345 | U28: 31.0388 | V28: 34.5121 | W28: 15.3621 | X28: 1.0741 | Y28: 18.1853 | Z28: 5.7668 | AA28: 21.5047 | AB28: 42.4318 | AC28: 31.134674 | AD28: 80.5471 | AE28: 85.148
A29: Adjusted EPS | B29: 0.040159965 | C29: 0.26471107 | D29: 0.3063806 | E29: 0.47110305 | F29: 0.77216171 | G29: 1.305847 | H29: 1.3986758 | I29: 1.6697511 | J29: 2.4035865 | K29: 2.443989 | L29: 3.4812 | M29: 4.6801 | N29: 5.9883 | O29: 10.1133 | P29: 12.4121 | Q29: 16.5072 | R29: 20.5332 | S29: 22.1365 | T29: 26.4669 | U29: 31.0388 | V29: 34.5121 | W29: 15.3621 | X29: 1.0741 | Y29: 18.1853 | Z29: 5.7668 | AA29: 21.5047 | AB29: 42.4318 | AC29: 31.1347 | AD29: 80.5471 | AE29: 85.148
A30: EPS - Basic (Reported) | E30: 2.36 | F30: 3.86 | G30: 6.53 | H30: 6.99 | I30: 8.35 | J30: 12.02 | K30: 12.22 | L30: 17.45 | M30: 23.5 | N30: 32.15 | O30: 50.61 | P30: 65.78 | Q30: 82.95 | R30: 102.94 | S30: 119.67 | T30: 26.51 | U30: 31.18 | V30: 34.59 | W30: 15.4 | X30: 1.13 | Y30: 18.2 | Z30: 5.99 | AA30: 22.15 | AB30: 42.48 | AC30: 31.17 | AD30: 80.67 | AE30: 85.28
A31: EPS - Diluted (Reported) | Q31: 81.61 | R31: 102.2 | U31: 30.85 | V31: 34.4 | X31: 1.12 | Y31: 18.09 | Z31: 5.97 | AA31: 22.09 | AB31: 42.35 | AC31: 31.02 | AD31: 80.1 | AE31: 84.77
